Workbook

Sheet Start Here
A1: Fantasy & High-Fantasy Comparative Archetype Atlas — Version 4.0
A2: Normalized-concept visual layer with 1568 citation-backed character evidence records, 1252 character-only evidence relationships, and 281 scoped source passes; focused independent review is recorded for 90 sources and remains pending for 191.
A3: A normalized-concept atlas: being/entity and role/vocation concepts are visual marks; characters and source-native terms are cited evidence
A5: Edition | B5: 4.0 | D5: Key Metric | E5: Value | G5: How to read the atlas
A6: Source fingerprint | B6: sha256:56b3c048fdce9c10348aaa9ed9abe7fefd683df2f7f8db9d9511b7ebf960a1be | D6: Normalized archetypes | E6: =COUNTA('Master Taxonomy'!$A$2:$A$1656) | G6: 1 | H6: Find a source-specific term in Seed Catalogue.
A7: Framework model | B7: Source records + normalized crosswalks | D7: Source corpus records | E7: =COUNTA('Source Corpus'!$A$2:$A$282) | G7: 2 | H7: Follow its Primary and Additional Archetype IDs into Master Taxonomy.
A8: Primary use | B8: Comparative literary/media analysis | D8: Source-specific seed entries | E8: =COUNTA('Seed Catalogue'!$A$2:$A$452) | G8: 3 | H8: Compare only along named axes: ontology, role, power, institution, mechanics, or narrative function.
A9: Secondary use | B9: Encyclopedia/database and reusable archetype discovery | D9: Top-level domains | E9: =COUNTIF('Master Taxonomy'!$M$2:$M$1656,"Domain Root") | G9: 4 | H9: Use Relationship Rules instead of assuming that identical labels are equivalent.
A10: Version policy | B10: Continuity- and edition-specific where material differences exist | G10: 5 | H10: Check Evidence Level, Canon Status, continuity, and Reference URL before making source claims.
G11: 6 | H11: Use Source Priority and Research Queue to extend the corpus without changing the core schema.
G12: 7 | H12: Use Term Metadata for language/witness controls and Adaptation Crosswalk to study how concepts change across media.
A13: Completeness contract
A14: Structural completeness | B14: The schema can represent peoples, beings, roles, powers, institutions, transformations, civilizations, narrative patterns, game mechanics, artifacts, cosmologies, sacred geography, metaphysical laws, rituals, and exchanges without forcing them into race/class bins.
A15: Taxonomic completeness | B15: The normalized hierarchy covers the major reusable archetype families encountered across fantasy traditions and media, with explicit room for culture-specific subfamilies.
A16: Corpus completeness | B16: The source list is intentionally expandable. No finite edition can literally include every fantasy work, edition, adaptation, folk tradition, or live-service update.
A17: Claim discipline | B17: A catalogue entry is not considered fully source-verified until its Evidence Level and Source Reference support the specific continuity claim.
A18: Non-equivalence rule | B18: A normalized family provides a comparison coordinate; it never erases the source concept's distinct metaphysics, history, or cultural meaning.
A20: Eleven analytical domains
A21: People & Beings | B21: Species, peoples, spirits, gods, undead, constructs, monsters, hybrids, and mutable beings. | G21: Roles & Vocations | H21: Martial, rogue, magical, sacred, social, technical, hybrid, and progression roles.
A22: Power Traditions | B22: Sources, domains, methods, costs, techniques, and theories of supernatural power. | G22: States & Transformations | H22: Undeath, curse, possession, mutation, ascension, bond, displacement, and other acquired states.
A23: Institutions & Affiliations | B23: Guilds, orders, schools, sects, parties, factions, castes, states, and social structures. | G23: Narrative Archetypes | H23: Character, antagonist, party, quest, plot, and thematic story functions.
A24: Civilization & Culture Archetypes | B24: States, settlements, ecologies, economies, social organizations, and historical patterns. | G24: Game-Mechanical Archetypes | H24: Combat roles, resources, class structures, progression systems, and unit functions.
A25: Cross-axis rule | B25: One source concept may occupy several domains simultaneously. A witcher, for example, is a transformed human, professional monster hunter, order member, alchemical user, and game build. | G25: Hierarchy rule | H25: Broad families support retrieval; lower tiers preserve distinctions. Parent-child placement is analytical, not a claim of fictional genealogy.
A26: Terminology rule | B26: Preserve source-native terms, translations, and edition labels. Use 'people/being type' as the umbrella rather than treating every distinction as race. | G26: Adaptation rule | H26: Separate adaptations when ontology, powers, institutions, available classes, or world history materially diverge.
A27: Cultural caution | B27: Religious, folkloric, and living traditions require culture-specific scholarship. Similarity is not proof of direct influence or equivalence. | G27: Moral caution | H27: Record source-stated alignments and stereotypes without naturalizing morality as biological fact.
A28: Database rule | B28: Stable IDs remain fixed; deprecated concepts are merged by status rather than deleted or silently reused. | G28: Citation rule | H28: URLs are stored for orientation; deep passes should add edition, chapter, page, episode, codex, or rules-section references.
A30: Relationship ladder: strongest claim to weakest claim
A31: Canonical alias | B31: Same concept in the same continuity. | D31: Exact equivalent | E31: Same across all material dimensions; exceptionally rare. | G31: Close analogue | H31: Strong similarity with source-specific differences. | J31: Partial analogue | K31: Similarity on selected axes only.
A32: Functional analogue | B32: Same social or narrative job. | D32: Mechanical analogue | E32: Same game role or progression function. | G32: Visual analogue | H32: Similar appearance only. | J32: Inspired-by | K32: Requires influence evidence.
A33: Subtype-of | B33: Narrower taxonomic category. | D33: Member-of | E33: Institutional or social membership. | G33: Hybrid-of | H33: Combines multiple normalized families. | J33: Transformed-into | K33: Temporal ontological change.
A34: Adaptation-of | B34: Cross-media or continuity transformation. | D34: Version-of | E34: Edition or incarnation relationship. | G34: Inversion | H34: Deliberate reversal or critique. | J34: Frequently confused-with | K34: Quality-control warning.
A35: Uncertain / disputed | B35: Use when canon, scholarship, translation, or influence remains unresolved.
A37: Recommended research workflow
A38: 1. Define continuity | B38: Choose the exact book corpus, edition, game build, adaptation, or mythic source layer.
A39: 2. Record native type | B39: Ask what the source says the concept is: people, spirit, office, order, profession, class, condition, or mechanic.
A40: 3. Decompose axes | B40: Separate ontology, culture, role, power source, institution, mechanics, and narrative function.
A41: 4. Crosswalk conservatively | B41: Assign a primary archetype and additional axes; document the key distinction.
A42: 5. Cite and version | B42: Add the most precise available source reference and date/version for changing material.
A43: 6. Compare with typed links | B43: State why two entries are analogous rather than merely placing them under one vague label.
A45: Version 2.0 domain expansion
A46: Artifacts, Relics, Weapons & Vehicles | B46: Objects and conveyances whose provenance, agency, ritual status, cosmological position, or mechanical function warrants a source-faithful record.
A47: Cosmologies, Realms & Sacred Geography | B47: Heavens, underworlds, spirit worlds, cosmic structures, thresholds, sacred landscapes, afterlives, cycles, and models of reality.
A48: Metaphysical Laws, Rituals & Exchanges | B48: Vows, boons, curses, sacrifice, hospitality, fate, moral causation, purity, initiation, true names, reciprocity, and other binding structures.
A50: New research and comparison controls
A51: Source Priority | B51: Weighted marginal-archetype-value model with editable criteria, redundancy penalty, treatment thresholds, editorial rationale, and a top-source chart.
A52: Term Metadata | B52: Original language, script, transliteration, textual witness, period/layer, translation variants, sacred-context caution, and novelty classification.
A53: Adaptation Crosswalk | B53: Typed records for factionalization, unitization, mechanization, resource abstraction, itemization, bossification, decontextualization, and related operations.
A55: Current source-complex and adaptation passes
A56: Mahābhārata | B56: Foundational source-complex pass covering beings, roles, divine weapons, vows, boons, curses, ritual, cosmology, institutions, and narrative structures, with witness and sacred-context controls.
A57: Age of Mythology: Retold | B57: Adaptation pass focused on how pantheons and traditional concepts become factions, units, heroes, god powers, resources, ages, relics, and strategic counters.
A58: Darkest Dungeon | B58: Selective innovation pass centered on stress, affliction/virtue crises, quirks, expedition attrition, position systems, recovery institutions, roster mortality, and inherited ruin.

Sheet V3 Viz Archive
B2: Version 3 Interactive Relationship Atlas
B3: Deliverable | C3: TypeScript + Sigma.js + Graphology WebGL explorer generated from this workbook.
B4: Run locally | C4: From the project directory: npm install, then npm run dev. Open the local URL printed by Vite.
B5: Build | C5: npm run build regenerates this workbook's JSON graph projection, type-checks the app, and creates dist/.
B7: Semantic zoom | C7: Far: eleven domains and all sources. Middle: archetype families and source bridges. Near: source concepts, canonical entries, adaptations, evidence, and citations.
B8: Coverage view | C8: Separates orientation coverage (281/281 sources) from canonical source-pass coverage (currently 21/281 sources).
B9: Integrity rule | C9: Source Concept Map rows are orientation coordinates derived from editorial corpus notes. They must not be cited as canonical claims. Seed Catalogue remains the canonical source-entry layer.
B11: Graph node types | C11: Domain · normalized archetype · source/tradition · orientation concept · canonical source entry · adaptation crosswalk.
B12: Graph edge types | C12: taxonomy · canonical mapping · orientation mapping · source containment · adaptation · version · influence · implementation.
B14: Version 3 counts | C14: 281 sources · 1655 archetypes · 451 canonical entries · 1465 orientation concepts · 54 source relationships.

Sheet Master Taxonomy
A1: Archetype_ID | B1: Preferred_Name | C1: Domain | D1: Parent_ID | E1: Parent_Name | F1: Tier | G1: Core_Definition | H1: Key_Distinctions | I1: Common_Variants | J1: Typical_Functions | K1: Representative_Terms | L1: Cross_Cultural_Caution | M1: Framework_Status
A2: PPL-000 | B2: People & Beings | C2: People & Beings | E2: =IF(D2="","",IFERROR(VLOOKUP(D2,$A$2:$B$1656,2,FALSE),"")) | F2: 1 | G2: Biological peoples, metaphysical kinds, monsters, spirits, constructs, and other sentient or narratively significant beings. | H2: A top-level analytical domain. Entries may link across domains but should not be collapsed into one another. | J2: Provides the first classification axis for the database. | K2: People & Beings | L2: Preserve each source's ontology, culture, history, and terminology when making comparisons. | M2: Domain Root
A3: ROL-000 | B3: Roles & Vocations | C3: Roles & Vocations | E3: =IF(D3="","",IFERROR(VLOOKUP(D3,$A$2:$B$1656,2,FALSE),"")) | F3: 1 | G3: Professions, combat roles, social offices, religious vocations, magical callings, and formal game classes. | H3: A top-level analytical domain. Entries may link across domains but should not be collapsed into one another. | J3: Provides the first classification axis for the database. | K3: Roles & Vocations | L3: Preserve each source's ontology, culture, history, and terminology when making comparisons. | M3: Domain Root
A4: PWR-000 | B4: Power Traditions | C4: Power Traditions | E4: =IF(D4="","",IFERROR(VLOOKUP(D4,$A$2:$B$1656,2,FALSE),"")) | F4: 1 | G4: Repeatable sources, methods, and logics through which extraordinary power is acquired or exercised. | H4: A top-level analytical domain. Entries may link across domains but should not be collapsed into one another. | J4: Provides the first classification axis for the database. | K4: Power Traditions | L4: Preserve each source's ontology, culture, history, and terminology when making comparisons. | M4: Domain Root
A5: STA-000 | B5: States & Transformations | C5: States & Transformations | E5: =IF(D5="","",IFERROR(VLOOKUP(D5,$A$2:$B$1656,2,FALSE),"")) | F5: 1 | G5: Acquired conditions, templates, curses, awakenings, and changes of body, soul, identity, or status. | H5: A top-level analytical domain. Entries may link across domains but should not be collapsed into one another. | J5: Provides the first classification axis for the database. | K5: States & Transformations | L5: Preserve each source's ontology, culture, history, and terminology when making comparisons. | M5: Domain Root
A6: INS-000 | B6: Institutions & Affiliations | C6: Institutions & Affiliations | E6: =IF(D6="","",IFERROR(VLOOKUP(D6,$A$2:$B$1656,2,FALSE),"")) | F6: 1 | G6: Orders, schools, guilds, sects, castes, houses, armies, and other organized identities. | H6: A top-level analytical domain. Entries may link across domains but should not be collapsed into one another. | J6: Provides the first classification axis for the database. | K6: Institutions & Affiliations | L6: Preserve each source's ontology, culture, history, and terminology when making comparisons. | M6: Domain Root
A7: NAR-000 | B7: Narrative Archetypes | C7: Narrative Archetypes | E7: =IF(D7="","",IFERROR(VLOOKUP(D7,$A$2:$B$1656,2,FALSE),"")) | F7: 1 | G7: Recurring character, party, antagonist, and plot functions used across fantasy media. | H7: A top-level analytical domain. Entries may link across domains but should not be collapsed into one another. | J7: Provides the first classification axis for the database. | K7: Narrative Archetypes | L7: Preserve each source's ontology, culture, history, and terminology when making comparisons. | M7: Domain Root
A8: CIV-000 | B8: Civilization & Culture Archetypes | C8: Civilization & Culture Archetypes | E8: =IF(D8="","",IFERROR(VLOOKUP(D8,$A$2:$B$1656,2,FALSE),"")) | F8: 1 | G8: Reusable patterns for societies, polities, economies, and cultural organization. | H8: A top-level analytical domain. Entries may link across domains but should not be collapsed into one another. | J8: Provides the first classification axis for the database. | K8: Civilization & Culture Archetypes | L8: Preserve each source's ontology, culture, history, and terminology when making comparisons. | M8: Domain Root
A9: MEC-000 | B9: Game-Mechanical Archetypes | C9: Game-Mechanical Archetypes | E9: =IF(D9="","",IFERROR(VLOOKUP(D9,$A$2:$B$1656,2,FALSE),"")) | F9: 1 | G9: Roles and resource patterns defined primarily by rules, encounter design, or player progression. | H9: A top-level analytical domain. Entries may link across domains but should not be collapsed into one another. | J9: Provides the first classification axis for the database. | K9: Game-Mechanical Archetypes | L9: Preserve each source's ontology, culture, history, and terminology when making comparisons. | M9: Domain Root
A10: PPL-100 | B10: Mortal and Natural Peoples | C10: People & Beings | D10: PPL-000 | E10: =IF(D10="","",IFERROR(VLOOKUP(D10,$A$2:$B$1656,2,FALSE),"")) | F10: 2 | G10: Peoples presented as ordinary inhabitants of the setting's natural world, even when their biology differs from humans. | H10: Classify by ontology first; morphology, culture, and game creature type are separate axes. | J10: Organizes source-specific peoples and creatures by the kind of being they are. | K10: Player ancestries; nations; ethnicized fantasy peoples | L10: Preserve each source's ontology, culture, history, and terminology when making comparisons. | M10: Category
A11: PPL-200 | B11: Fae, Nature, and Liminal Beings | C11: People & Beings | D11: PPL-000 | E11: =IF(D11="","",IFERROR(VLOOKUP(D11,$A$2:$B$1656,2,FALSE),"")) | F11: 2 | G11: Beings tied to wilderness, place, season, threshold, enchantment, or an otherworld adjacent to mortal reality. | H11: Classify by ontology first; morphology, culture, and game creature type are separate axes. | J11: Organizes source-specific peoples and creatures by the kind of being they are. | K11: Fae courts; land spirits; trickster beings | L11: Preserve each source's ontology, culture, history, and terminology when making comparisons. | M11: Category
A12: PPL-300 | B12: Spirits and Elementals | C12: People & Beings | D12: PPL-000 | E12: =IF(D12="","",IFERROR(VLOOKUP(D12,$A$2:$B$1656,2,FALSE),"")) | F12: 2 | G12: Incorporeal or semi-corporeal beings constituted by soul, element, concept, memory, dream, or place. | H12: Classify by ontology first; morphology, culture, and game creature type are separate axes. | J12: Organizes source-specific peoples and creatures by the kind of being they are. | K12: Elementals; ancestors; guardian spirits | L12: Preserve each source's ontology, culture, history, and terminology when making comparisons. | M12: Category
A13: PPL-400 | B13: Divine and Celestial Beings | C13: People & Beings | D13: PPL-000 | E13: =IF(D13="","",IFERROR(VLOOKUP(D13,$A$2:$B$1656,2,FALSE),"")) | F13: 2 | G13: Gods, divine emanations, celestial servants, ascended mortals, and beings aligned with sacred cosmic order. | H13: Classify by ontology first; morphology, culture, and game creature type are separate axes. | J13: Organizes source-specific peoples and creatures by the kind of being they are. | K13: Gods; angels; saints; avatars | L13: Preserve each source's ontology, culture, history, and terminology when making comparisons. | M13: Category
A14: PPL-500 | B14: Infernal and Corruptive Beings | C14: People & Beings | D14: PPL-000 | E14: =IF(D14="","",IFERROR(VLOOKUP(D14,$A$2:$B$1656,2,FALSE),"")) | F14: 2 | G14: Demons, devils, fallen celestials, chaos-spawn, and entities whose existence centers on corruption, domination, temptation, or metaphysical disorder. | H14: Classify by ontology first; morphology, culture, and game creature type are separate axes. | J14: Organizes source-specific peoples and creatures by the kind of being they are. | K14: Fiends; demon lords; possessors | L14: Preserve each source's ontology, culture, history, and terminology when making comparisons. | M14: Category
A15: PPL-600 | B15: Undead Beings | C15: People & Beings | D15: PPL-000 | E15: =IF(D15="","",IFERROR(VLOOKUP(D15,$A$2:$B$1656,2,FALSE),"")) | F15: 2 | G15: Beings that persist after biological death through animation, trapped soul, curse, hunger, ritual, or necromantic structure. | H15: Classify by ontology first; morphology, culture, and game creature type are separate axes. | J15: Organizes source-specific peoples and creatures by the kind of being they are. | K15: Ghosts; vampires; liches; revenants | L15: Preserve each source's ontology, culture, history, and terminology when making comparisons. | M15: Category
A16: PPL-700 | B16: Constructs and Artificial Life | C16: People & Beings | D16: PPL-000 | E16: =IF(D16="","",IFERROR(VLOOKUP(D16,$A$2:$B$1656,2,FALSE),"")) | F16: 2 | G16: Created beings whose bodies or minds are deliberately manufactured, assembled, grown, enchanted, or replicated. | H16: Classify by ontology first; morphology, culture, and game creature type are separate axes. | J16: Organizes source-specific peoples and creatures by the kind of being they are. | K16: Golems; homunculi; clockwork people | L16: Preserve each source's ontology, culture, history, and terminology when making comparisons. | M16: Category
A17: PPL-800 | B17: Dragons and Legendary Beasts | C17: People & Beings | D17: PPL-000 | E17: =IF(D17="","",IFERROR(VLOOKUP(D17,$A$2:$B$1656,2,FALSE),"")) | F17: 2 | G17: Iconic nonhuman beasts whose intelligence, scale, magical potency, or symbolic role exceeds ordinary fauna. | H17: Classify by ontology first; morphology, culture, and game creature type are separate axes. | J17: Organizes source-specific peoples and creatures by the kind of being they are. | K17: Dragons; griffins; hydras; world beasts | L17: Preserve each source's ontology, culture, history, and terminology when making comparisons. | M17: Category
A18: PPL-900 | B18: Plant, Fungal, Ooze, and Collective Life | C18: People & Beings | D18: PPL-000 | E18: =IF(D18="","",IFERROR(VLOOKUP(D18,$A$2:$B$1656,2,FALSE),"")) | F18: 2 | G18: Beings based on non-animal life, amorphous bodies, swarms, colonies, or distributed consciousness. | H18: Classify by ontology first; morphology, culture, and game creature type are separate axes. | J18: Organizes source-specific peoples and creatures by the kind of being they are. | K18: Plantfolk; slimes; hive minds | L18: Preserve each source's ontology, culture, history, and terminology when making comparisons. | M18: Category
A19: PPL-1000 | B19: Shapeshifters, Hybrids, and Mutable Peoples | C19: People & Beings | D19: PPL-000 | E19: =IF(D19="","",IFERROR(VLOOKUP(D19,$A$2:$B$1656,2,FALSE),"")) | F19: 2 | G19: Beings defined by mixed ancestry, mutable form, copied identity, animal transformation, possession, or body exchange. | H19: Classify by ontology first; morphology, culture, and game creature type are separate axes. | J19: Organizes source-specific peoples and creatures by the kind of being they are. | K19: Therianthropes; doppelgangers; chimeras | L19: Preserve each source's ontology, culture, history, and terminology when making comparisons. | M19: Category
A20: PPL-1100 | B20: Cosmic, Aberrant, and Otherworldly Beings | C20: People & Beings | D20: PPL-000 | E20: =IF(D20="","",IFERROR(VLOOKUP(D20,$A$2:$B$1656,2,FALSE),"")) | F20: 2 | G20: Entities whose bodies, minds, origins, or causal rules lie outside the setting's normal natural and supernatural orders. | H20: Classify by ontology first; morphology, culture, and game creature type are separate axes. | J20: Organizes source-specific peoples and creatures by the kind of being they are. | K20: Aberrations; void beings; reality parasites | L20: Preserve each source's ontology, culture, history, and terminology when making comparisons. | M20: Category
A21: PPL-101 | B21: Human and Near-Human Peoples | C21: People & Beings | D21: PPL-100 | E21: =IF(D21="","",IFERROR(VLOOKUP(D21,$A$2:$B$1656,2,FALSE),"")) | F21: 3 | G21: Humans or humanlike peoples whose differences are primarily cultural, historical, adaptive, or mildly supernatural rather than a separate metaphysical kind. | H21: Source-specific examples may differ biologically, metaphysically, culturally, and morally; map them as analogues unless equivalence is explicit. | I21: human; mortal; man; tall-man; near-human | J21: Playable ancestry, neighboring civilization, minority people, enemy people, or cultural foil. | K21: human; mortal; man; tall-man; near-human | L21: Preserve each source's ontology, culture, history, and terminology when making comparisons. | M21: Core Family
A22: PPL-102 | B22: Elf-Derived Peoples | C22: People & Beings | D22: PPL-100 | E22: =IF(D22="","",IFERROR(VLOOKUP(D22,$A$2:$B$1656,2,FALSE),"")) | F22: 3 | G22: Graceful or otherworldly humanoids commonly associated with longevity, heightened perception, magic, nature, memory, or a fading elder civilization. | H22: Source-specific examples may differ biologically, metaphysically, culturally, and morally; map them as analogues unless equivalence is explicit. | I22: elf; elven; elvish; elder folk; faerie-blooded | J22: Playable ancestry, neighboring civilization, minority people, enemy people, or cultural foil. | K22: elf; elven; elvish; elder folk; faerie-blooded | L22: Do not treat Tolkien's Quendi, folkloric elves, game ancestries, and modern anime elves as one ontology. | M22: Core Family
A23: PPL-103 | B23: Dwarf-Derived Peoples | C23: People & Beings | D23: PPL-100 | E23: =IF(D23="","",IFERROR(VLOOKUP(D23,$A$2:$B$1656,2,FALSE),"")) | F23: 3 | G23: Compact, hardy humanoids often linked with stone, mining, smithcraft, clan memory, subterranean halls, or martial resilience. | H23: Source-specific examples may differ biologically, metaphysically, culturally, and morally; map them as analogues unless equivalence is explicit. | I23: dwarf; dwarven; dwarf-kind; mountain folk | J23: Playable ancestry, neighboring civilization, minority people, enemy people, or cultural foil. | K23: dwarf; dwarven; dwarf-kind; mountain folk | L23: Preserve each source's ontology, culture, history, and terminology when making comparisons. | M23: Core Family
A24: PPL-104 | B24: Halfling and Smallfolk Peoples | C24: People & Beings | D24: PPL-100 | E24: =IF(D24="","",IFERROR(VLOOKUP(D24,$A$2:$B$1656,2,FALSE),"")) | F24: 3 | G24: Small-statured humanoids whose archetype emphasizes domesticity, stealth, luck, community, mobility, or being overlooked by larger powers. | H24: Source-specific examples may differ biologically, metaphysically, culturally, and morally; map them as analogues unless equivalence is explicit. | I24: halfling; hobbit-like; kender-like; smallfolk | J24: Playable ancestry, neighboring civilization, minority people, enemy people, or cultural foil. | K24: halfling; hobbit-like; kender-like; smallfolk | L24: Preserve each source's ontology, culture, history, and terminology when making comparisons. | M24: Core Family
A25: PPL-105 | B25: Gnome and Tinkerfolk Peoples | C25: People & Beings | D25: PPL-100 | E25: =IF(D25="","",IFERROR(VLOOKUP(D25,$A$2:$B$1656,2,FALSE),"")) | F25: 3 | G25: Small humanoids associated with craft, curiosity, illusion, engineering, alchemy, scholarship, or hidden communities. | H25: Source-specific examples may differ biologically, metaphysically, culturally, and morally; map them as analogues unless equivalence is explicit. | I25: gnome; tinkerfolk; deep gnome; garden-gnome analogue | J25: Playable ancestry, neighboring civilization, minority people, enemy people, or cultural foil. | K25: gnome; tinkerfolk; deep gnome; garden-gnome analogue | L25: Preserve each source's ontology, culture, history, and terminology when making comparisons. | M25: Core Family
A26: PPL-106 | B26: Orc-Derived Peoples | C26: People & Beings | D26: PPL-100 | E26: =IF(D26="","",IFERROR(VLOOKUP(D26,$A$2:$B$1656,2,FALSE),"")) | F26: 3 | G26: Powerfully built humanoids often framed through warfare, marginalization, corruption, honor culture, clan identity, or contested personhood. | H26: Source-specific examples may differ biologically, metaphysically, culturally, and morally; map them as analogues unless equivalence is explicit. | I26: orc; orcish; ork; half-orc | J26: Playable ancestry, neighboring civilization, minority people, enemy people, or cultural foil. | K26: orc; orcish; ork; half-orc | L26: Track whether 'orc' denotes a created enemy species, an ethnicized people, a playable ancestry, or a reclaimed identity. | M26: Core Family
A27: PPL-107 | B27: Goblinoid Peoples | C27: People & Beings | D27: PPL-100 | E27: =IF(D27="","",IFERROR(VLOOKUP(D27,$A$2:$B$1656,2,FALSE),"")) | F27: 3 | G27: Small or medium humanoids associated with subterranean life, scavenging, ambush, craft, trickery, militarized hierarchy, or outsider societies. | H27: Source-specific examples may differ biologically, metaphysically, culturally, and morally; map them as analogues unless equivalence is explicit. | I27: goblin; hobgoblin; bugbear; gremlin-like | J27: Playable ancestry, neighboring civilization, minority people, enemy people, or cultural foil. | K27: goblin; hobgoblin; bugbear; gremlin-like | L27: Preserve each source's ontology, culture, history, and terminology when making comparisons. | M27: Core Family
A28: PPL-108 | B28: Giantkin Peoples | C28: People & Beings | D28: PPL-100 | E28: =IF(D28="","",IFERROR(VLOOKUP(D28,$A$2:$B$1656,2,FALSE),"")) | F28: 3 | G28: Humanoid peoples of exceptional scale, often linked with primordial ancestry, mountains, elemental forces, divine lineage, or fading ages. | H28: Source-specific examples may differ biologically, metaphysically, culturally, and morally; map them as analogues unless equivalence is explicit. | I28: giant; jotunn-like; titan-blooded; goliath | J28: Playable ancestry, neighboring civilization, minority people, enemy people, or cultural foil. | K28: giant; jotunn-like; titan-blooded; goliath | L28: Preserve each source's ontology, culture, history, and terminology when making comparisons. | M28: Core Family
A29: PPL-109 | B29: Ogrekin Peoples | C29: People & Beings | D29: PPL-100 | E29: =IF(D29="","",IFERROR(VLOOKUP(D29,$A$2:$B$1656,2,FALSE),"")) | F29: 3 | G29: Large humanoids commonly framed as physically powerful, socially marginal, cannibalistic, mercenary, clan-based, or unexpectedly sophisticated. | H29: Source-specific examples may differ biologically, metaphysically, culturally, and morally; map them as analogues unless equivalence is explicit. | I29: ogre; ogrekin; oni-like giant humanoid | J29: Playable ancestry, neighboring civilization, minority people, enemy people, or cultural foil. | K29: ogre; ogrekin; oni-like giant humanoid | L29: Preserve each source's ontology, culture, history, and terminology when making comparisons. | M29: Core Family
A30: PPL-110 | B30: Trollkin Peoples | C30: People & Beings | D30: PPL-100 | E30: =IF(D30="","",IFERROR(VLOOKUP(D30,$A$2:$B$1656,2,FALSE),"")) | F30: 3 | G30: Regenerative, stone-associated, monstrous, folkloric, or tribal humanoids whose meanings range from person to predator. | H30: Source-specific examples may differ biologically, metaphysically, culturally, and morally; map them as analogues unless equivalence is explicit. | I30: troll; trollkin; troll-blooded | J30: Playable ancestry, neighboring civilization, minority people, enemy people, or cultural foil. | K30: troll; trollkin; troll-blooded | L30: Separate Scandinavian folkloric trolls, Tolkienian trolls, and game troll peoples. | M30: Core Family
A31: PPL-111 | B31: Cyclopean Peoples | C31: People & Beings | D31: PPL-100 | E31: =IF(D31="","",IFERROR(VLOOKUP(D31,$A$2:$B$1656,2,FALSE),"")) | F31: 3 | G31: One-eyed or otherwise singular-sensed giant humanoids, often connected with smithing, prophecy, isolation, or brute force. | H31: Source-specific examples may differ biologically, metaphysically, culturally, and morally; map them as analogues unless equivalence is explicit. | I31: cyclops; one-eyed giant | J31: Playable ancestry, neighboring civilization, minority people, enemy people, or cultural foil. | K31: cyclops; one-eyed giant | L31: Preserve each source's ontology, culture, history, and terminology when making comparisons. | M31: Core Family
A32: PPL-112 | B32: Lizardfolk and Reptilian Peoples | C32: People & Beings | D32: PPL-100 | E32: =IF(D32="","",IFERROR(VLOOKUP(D32,$A$2:$B$1656,2,FALSE),"")) | F32: 3 | G32: Humanoid reptiles whose settings may emphasize alien cognition, ancient civilizations, survival ecology, or draconic ancestry. | H32: Source-specific examples may differ biologically, metaphysically, culturally, and morally; map them as analogues unless equivalence is explicit. | I32: lizardfolk; saurian; argonian-like; reptilian | J32: Playable ancestry, neighboring civilization, minority people, enemy people, or cultural foil. | K32: lizardfolk; saurian; argonian-like; reptilian | L32: Preserve each source's ontology, culture, history, and terminology when making comparisons. | M32: Core Family
... A177: PPL-1112 | B177: Incomprehensible Collective Intelligences | C177: People & Beings | D177: PPL-1100 | E177: =IF(D177="","",IFERROR(VLOOKUP(D177,$A$2:$B$1656,2,FALSE),"")) | F177: 3 | G177: Vast minds distributed across species, dimensions, stars, or informational systems beyond individual-scale personhood. | H177: Source-specific examples may differ biologically, metaphysically, culturally, and morally; map them as analogues unless equivalence is explicit. | I177: cosmic hive mind; overmind | J177: Cosmic threat, reality challenge, alien civilization, metaphysical mystery, or boundary of comprehension. | K177: cosmic hive mind; overmind | L177: Preserve each source's ontology, culture, history, and terminology when making comparisons. | M177: Core Family
A178: ROL-100 | B178: Martial Roles | C178: Roles & Vocations | D178: ROL-000 | E178: =IF(D178="","",IFERROR(VLOOKUP(D178,$A$2:$B$1656,2,FALSE),"")) | F178: 2 | G178: Combatants whose primary expertise is weapons, armor, physical discipline, command, or battlefield endurance. | H178: A role may be a profession, class, office, order, build, or narrative identity; record the native type separately. | J178: Groups source-specific classes and vocations by practical and symbolic function. | K178: Martial Roles | L178: Preserve each source's ontology, culture, history, and terminology when making comparisons. | M178: Category
A179: ROL-200 | B179: Rogue and Underworld Roles | C179: Roles & Vocations | D179: ROL-000 | E179: =IF(D179="","",IFERROR(VLOOKUP(D179,$A$2:$B$1656,2,FALSE),"")) | F179: 2 | G179: Stealth, infiltration, theft, assassination, deception, sabotage, and informal survival professions. | H179: A role may be a profession, class, office, order, build, or narrative identity; record the native type separately. | J179: Groups source-specific classes and vocations by practical and symbolic function. | K179: Rogue and Underworld Roles | L179: Preserve each source's ontology, culture, history, and terminology when making comparisons. | M179: Category
A180: ROL-300 | B180: Arcane and Scholarly Magic Roles | C180: Roles & Vocations | D180: ROL-000 | E180: =IF(D180="","",IFERROR(VLOOKUP(D180,$A$2:$B$1656,2,FALSE),"")) | F180: 2 | G180: Practitioners whose extraordinary abilities are framed as learned, innate, technical, symbolic, or occult magic. | H180: A role may be a profession, class, office, order, build, or narrative identity; record the native type separately. | J180: Groups source-specific classes and vocations by practical and symbolic function. | K180: Arcane and Scholarly Magic Roles | L180: Preserve each source's ontology, culture, history, and terminology when making comparisons. | M180: Category
A181: ROL-400 | B181: Divine and Religious Roles | C181: Roles & Vocations | D181: ROL-000 | E181: =IF(D181="","",IFERROR(VLOOKUP(D181,$A$2:$B$1656,2,FALSE),"")) | F181: 2 | G181: Vocations grounded in worship, sacred authority, miracles, prophecy, ritual office, or opposition to spiritual threats. | H181: A role may be a profession, class, office, order, build, or narrative identity; record the native type separately. | J181: Groups source-specific classes and vocations by practical and symbolic function. | K181: Divine and Religious Roles | L181: Preserve each source's ontology, culture, history, and terminology when making comparisons. | M181: Category
A182: ROL-500 | B182: Nature and Spirit Roles | C182: Roles & Vocations | D182: ROL-000 | E182: =IF(D182="","",IFERROR(VLOOKUP(D182,$A$2:$B$1656,2,FALSE),"")) | F182: 2 | G182: Vocations that mediate wilderness, animals, elements, ancestors, land spirits, or ecological reciprocity. | H182: A role may be a profession, class, office, order, build, or narrative identity; record the native type separately. | J182: Groups source-specific classes and vocations by practical and symbolic function. | K182: Nature and Spirit Roles | L182: Preserve each source's ontology, culture, history, and terminology when making comparisons. | M182: Category
A183: ROL-600 | B183: Healing, Craft, and Knowledge Roles | C183: Roles & Vocations | D183: ROL-000 | E183: =IF(D183="","",IFERROR(VLOOKUP(D183,$A$2:$B$1656,2,FALSE),"")) | F183: 2 | G183: Supportive, productive, scholarly, artistic, and technical professions that sustain people and institutions. | H183: A role may be a profession, class, office, order, build, or narrative identity; record the native type separately. | J183: Groups source-specific classes and vocations by practical and symbolic function. | K183: Healing, Craft, and Knowledge Roles | L183: Preserve each source's ontology, culture, history, and terminology when making comparisons. | M183: Category
A184: ROL-700 | B184: Leadership and Social Office Roles | C184: Roles & Vocations | D184: ROL-000 | E184: =IF(D184="","",IFERROR(VLOOKUP(D184,$A$2:$B$1656,2,FALSE),"")) | F184: 2 | G184: Roles defined by authority, status, governance, diplomacy, lineage, administration, or command. | H184: A role may be a profession, class, office, order, build, or narrative identity; record the native type separately. | J184: Groups source-specific classes and vocations by practical and symbolic function. | K184: Leadership and Social Office Roles | L184: Preserve each source's ontology, culture, history, and terminology when making comparisons. | M184: Category
A185: ROL-800 | B185: Hybrid and Specialist Fantasy Roles | C185: Roles & Vocations | D185: ROL-000 | E185: =IF(D185="","",IFERROR(VLOOKUP(D185,$A$2:$B$1656,2,FALSE),"")) | F185: 2 | G185: Composite, setting-specific, transformational, or strongly genre-coded roles that combine multiple domains. | H185: A role may be a profession, class, office, order, build, or narrative identity; record the native type separately. | J185: Groups source-specific classes and vocations by practical and symbolic function. | K185: Hybrid and Specialist Fantasy Roles | L185: Preserve each source's ontology, culture, history, and terminology when making comparisons. | M185: Category
A186: ROL-900 | B186: Progression, Cultivation, and Adventure Roles | C186: Roles & Vocations | D186: ROL-000 | E186: =IF(D186="","",IFERROR(VLOOKUP(D186,$A$2:$B$1656,2,FALSE),"")) | F186: 2 | G186: Roles defined by advancement systems, guild ranks, cultivation paths, reincarnation structures, or exploratory play. | H186: A role may be a profession, class, office, order, build, or narrative identity; record the native type separately. | J186: Groups source-specific classes and vocations by practical and symbolic function. | K186: Progression, Cultivation, and Adventure Roles | L186: Preserve each source's ontology, culture, history, and terminology when making comparisons. | M186: Category
A187: ROL-101 | B187: Warrior or Fighter | C187: Roles & Vocations | D187: ROL-100 | E187: =IF(D187="","",IFERROR(VLOOKUP(D187,$A$2:$B$1656,2,FALSE),"")) | F187: 3 | G187: Broad weapon-using combatant whose competence is defined by martial training rather than a narrower social office or weapon style. | H187: Do not assume identical training, social status, powers, or mechanics across settings. | I187: warrior; fighter; man-at-arms; combatant | J187: Front-line combat, defense, mobility, command, hunting, or weapon mastery. | K187: warrior; fighter; man-at-arms; combatant | L187: Preserve each source's ontology, culture, history, and terminology when making comparisons. | M187: Core Family
A188: ROL-102 | B188: Soldier | C188: Roles & Vocations | D188: ROL-100 | E188: =IF(D188="","",IFERROR(VLOOKUP(D188,$A$2:$B$1656,2,FALSE),"")) | F188: 3 | G188: Combatant trained and organized as part of a formal military institution. | H188: Do not assume identical training, social status, powers, or mechanics across settings. | I188: soldier; trooper; legionary; regular | J188: Front-line combat, defense, mobility, command, hunting, or weapon mastery. | K188: soldier; trooper; legionary; regular | L188: Preserve each source's ontology, culture, history, and terminology when making comparisons. | M188: Core Family
A189: ROL-103 | B189: Militia and Levy | C189: Roles & Vocations | D189: ROL-100 | E189: =IF(D189="","",IFERROR(VLOOKUP(D189,$A$2:$B$1656,2,FALSE),"")) | F189: 3 | G189: Part-time or conscripted defender mobilized from civilian society. | H189: Do not assume identical training, social status, powers, or mechanics across settings. | I189: militia; levy; town guard | J189: Front-line combat, defense, mobility, command, hunting, or weapon mastery. | K189: militia; levy; town guard | L189: Preserve each source's ontology, culture, history, and terminology when making comparisons. | M189: Core Family
A190: ROL-104 | B190: Heavy Infantry | C190: Roles & Vocations | D190: ROL-100 | E190: =IF(D190="","",IFERROR(VLOOKUP(D190,$A$2:$B$1656,2,FALSE),"")) | F190: 3 | G190: Armored foot soldier designed to hold ground, absorb pressure, and fight in formation. | H190: Do not assume identical training, social status, powers, or mechanics across settings. | I190: heavy infantry; armored foot; linebreaker | J190: Front-line combat, defense, mobility, command, hunting, or weapon mastery. | K190: heavy infantry; armored foot; linebreaker | L190: Preserve each source's ontology, culture, history, and terminology when making comparisons. | M190: Core Family
A191: ROL-105 | B191: Light Infantry and Skirmisher | C191: Roles & Vocations | D191: ROL-100 | E191: =IF(D191="","",IFERROR(VLOOKUP(D191,$A$2:$B$1656,2,FALSE),"")) | F191: 3 | G191: Mobile foot soldier specializing in harassment, screening, scouting, or flexible engagement. | H191: Do not assume identical training, social status, powers, or mechanics across settings. | I191: skirmisher; light infantry; peltast-like | J191: Front-line combat, defense, mobility, command, hunting, or weapon mastery. | K191: skirmisher; light infantry; peltast-like | L191: Preserve each source's ontology, culture, history, and terminology when making comparisons. | M191: Core Family
A192: ROL-106 | B192: Spearfighter and Pikeman | C192: Roles & Vocations | D192: ROL-100 | E192: =IF(D192="","",IFERROR(VLOOKUP(D192,$A$2:$B$1656,2,FALSE),"")) | F192: 3 | G192: Combatant specializing in spears, polearms, pikes, reach, formation fighting, or anti-cavalry tactics. | H192: Do not assume identical training, social status, powers, or mechanics across settings. | I192: spearman; pikeman; lancer; polearm master | J192: Front-line combat, defense, mobility, command, hunting, or weapon mastery. | K192: spearman; pikeman; lancer; polearm master | L192: Preserve each source's ontology, culture, history, and terminology when making comparisons. | M192: Core Family
A193: ROL-107 | B193: Swordsman | C193: Roles & Vocations | D193: ROL-100 | E193: =IF(D193="","",IFERROR(VLOOKUP(D193,$A$2:$B$1656,2,FALSE),"")) | F193: 3 | G193: Combatant whose identity centers on sword mastery, often as a generalized heroic martial archetype. | H193: Do not assume identical training, social status, powers, or mechanics across settings. | I193: swordsman; swordfighter; blade master | J193: Front-line combat, defense, mobility, command, hunting, or weapon mastery. | K193: swordsman; swordfighter; blade master | L193: Preserve each source's ontology, culture, history, and terminology when making comparisons. | M193: Core Family
A194: ROL-108 | B194: Axefighter | C194: Roles & Vocations | D194: ROL-100 | E194: =IF(D194="","",IFERROR(VLOOKUP(D194,$A$2:$B$1656,2,FALSE),"")) | F194: 3 | G194: Combatant specializing in axes and commonly framed through power, aggression, woodcraft, or northern warrior imagery. | H194: Do not assume identical training, social status, powers, or mechanics across settings. | I194: axeman; axe warrior | J194: Front-line combat, defense, mobility, command, hunting, or weapon mastery. | K194: axeman; axe warrior | L194: Preserve each source's ontology, culture, history, and terminology when making comparisons. | M194: Core Family
A195: ROL-109 | B195: Hammer and Mace Fighter | C195: Roles & Vocations | D195: ROL-100 | E195: =IF(D195="","",IFERROR(VLOOKUP(D195,$A$2:$B$1656,2,FALSE),"")) | F195: 3 | G195: Blunt-weapon specialist associated with armor-breaking, sacred warfare, smithing cultures, or crushing force. | H195: Do not assume identical training, social status, powers, or mechanics across settings. | I195: hammerer; mace fighter; maul warrior | J195: Front-line combat, defense, mobility, command, hunting, or weapon mastery. | K195: hammerer; mace fighter; maul warrior | L195: Preserve each source's ontology, culture, history, and terminology when making comparisons. | M195: Core Family
A196: ROL-110 | B196: Shieldbearer and Guardian | C196: Roles & Vocations | D196: ROL-100 | E196: =IF(D196="","",IFERROR(VLOOKUP(D196,$A$2:$B$1656,2,FALSE),"")) | F196: 3 | G196: Defensive combatant who protects allies, controls space, or embodies duty through shield and armor. | H196: Do not assume identical training, social status, powers, or mechanics across settings. | I196: shieldbearer; guardian; defender; sentinel | J196: Front-line combat, defense, mobility, command, hunting, or weapon mastery. | K196: shieldbearer; guardian; defender; sentinel | L196: Preserve each source's ontology, culture, history, and terminology when making comparisons. | M196: Core Family
A197: ROL-111 | B197: Berserker | C197: Roles & Vocations | D197: ROL-100 | E197: =IF(D197="","",IFERROR(VLOOKUP(D197,$A$2:$B$1656,2,FALSE),"")) | F197: 3 | G197: Warrior who enters a heightened state of rage, trance, pain suppression, possession, or self-destructive power. | H197: Do not assume identical training, social status, powers, or mechanics across settings. | I197: berserker; rager; frenzy warrior | J197: Front-line combat, defense, mobility, command, hunting, or weapon mastery. | K197: berserker; rager; frenzy warrior | L197: The historical Norse term and modern game mechanic are related but not interchangeable. | M197: Core Family
A198: ROL-112 | B198: Barbarian | C198: Roles & Vocations | D198: ROL-100 | E198: =IF(D198="","",IFERROR(VLOOKUP(D198,$A$2:$B$1656,2,FALSE),"")) | F198: 3 | G198: Warrior archetype coded as outside urban civilization and associated with physical prowess, survival, rage, or anti-imperial freedom. | H198: Do not assume identical training, social status, powers, or mechanics across settings. | I198: barbarian; wild warrior | J198: Front-line combat, defense, mobility, command, hunting, or weapon mastery. | K198: barbarian; wild warrior | L198: The label often carries colonial or civilizational bias; prefer source-specific cultural terms where possible. | M198: Core Family
... A488: ROL-932 | B488: Classless Skill-Builder | C488: Roles & Vocations | D488: ROL-900 | E488: =IF(D488="","",IFERROR(VLOOKUP(D488,$A$2:$B$1656,2,FALSE),"")) | F488: 3 | G488: Character developed through freely chosen skills, attributes, perks, or techniques rather than a fixed class. | H488: Do not assume identical training, social status, powers, or mechanics across settings. | I488: classless build; skill-based adventurer | J488: Advancement, ranking, exploration, guild economy, cultivation, and system-mediated identity. | K488: classless build; skill-based adventurer | L488: Preserve each source's ontology, culture, history, and terminology when making comparisons. | M488: Core Family
A489: PWR-100 | B489: Source and Authorization Models | C489: Power Traditions | D489: PWR-000 | E489: =IF(D489="","",IFERROR(VLOOKUP(D489,$A$2:$B$1656,2,FALSE),"")) | F489: 2 | G489: How power is granted, inherited, learned, bargained for, or embodied. | H489: A power tradition describes source and method, not the user's profession or moral alignment. | J489: Allows classes and beings to be compared independently of local job names. | K489: Source and Authorization Models | L489: Preserve each source's ontology, culture, history, and terminology when making comparisons. | M489: Category
A490: PWR-200 | B490: Elemental and Natural Domains | C490: Power Traditions | D490: PWR-000 | E490: =IF(D490="","",IFERROR(VLOOKUP(D490,$A$2:$B$1656,2,FALSE),"")) | F490: 2 | G490: Power organized around matter, energy, weather, life, animals, and environments. | H490: A power tradition describes source and method, not the user's profession or moral alignment. | J490: Allows classes and beings to be compared independently of local job names. | K490: Elemental and Natural Domains | L490: Preserve each source's ontology, culture, history, and terminology when making comparisons. | M490: Category
A491: PWR-300 | B491: Soul, Death, and Body Domains | C491: Power Traditions | D491: PWR-000 | E491: =IF(D491="","",IFERROR(VLOOKUP(D491,$A$2:$B$1656,2,FALSE),"")) | F491: 2 | G491: Power acting on life force, blood, flesh, memory, souls, death, and transformation. | H491: A power tradition describes source and method, not the user's profession or moral alignment. | J491: Allows classes and beings to be compared independently of local job names. | K491: Soul, Death, and Body Domains | L491: Preserve each source's ontology, culture, history, and terminology when making comparisons. | M491: Category
A492: PWR-400 | B492: Mind, Perception, Fate, and Reality Domains | C492: Power Traditions | D492: PWR-000 | E492: =IF(D492="","",IFERROR(VLOOKUP(D492,$A$2:$B$1656,2,FALSE),"")) | F492: 2 | G492: Power acting on thought, dreams, information, probability, time, space, and causality. | H492: A power tradition describes source and method, not the user's profession or moral alignment. | J492: Allows classes and beings to be compared independently of local job names. | K492: Mind, Perception, Fate, and Reality Domains | L492: Preserve each source's ontology, culture, history, and terminology when making comparisons. | M492: Category
A493: PWR-500 | B493: Symbolic, Performative, and Technical Methods | C493: Power Traditions | D493: PWR-000 | E493: =IF(D493="","",IFERROR(VLOOKUP(D493,$A$2:$B$1656,2,FALSE),"")) | F493: 2 | G493: Power encoded in words, names, runes, music, dance, mathematics, artifacts, craft, or technology. | H493: A power tradition describes source and method, not the user's profession or moral alignment. | J493: Allows classes and beings to be compared independently of local job names. | K493: Symbolic, Performative, and Technical Methods | L493: Preserve each source's ontology, culture, history, and terminology when making comparisons. | M493: Category
A494: PWR-600 | B494: Oppositional and Meta-Magical Traditions | C494: Power Traditions | D494: PWR-000 | E494: =IF(D494="","",IFERROR(VLOOKUP(D494,$A$2:$B$1656,2,FALSE),"")) | F494: 2 | G494: Power that copies, suppresses, corrupts, randomizes, or otherwise modifies other powers and systems. | H494: A power tradition describes source and method, not the user's profession or moral alignment. | J494: Allows classes and beings to be compared independently of local job names. | K494: Oppositional and Meta-Magical Traditions | L494: Preserve each source's ontology, culture, history, and terminology when making comparisons. | M494: Category
A495: PWR-101 | B495: Learned Arcana | C495: Power Traditions | D495: PWR-100 | E495: =IF(D495="","",IFERROR(VLOOKUP(D495,$A$2:$B$1656,2,FALSE),"")) | F495: 3 | G495: Power acquired through study, practice, notation, memorization, experimentation, and teachable technique. | H495: Record source, method, cost, limits, access, and social control separately. | I495: wizardry; learned magic; scholastic arcana | J495: Defines who can access power, why it works, and what obligations accompany it. | K495: wizardry; learned magic; scholastic arcana | L495: Preserve each source's ontology, culture, history, and terminology when making comparisons. | M495: Core Family
A496: PWR-102 | B496: Innate Sorcery | C496: Power Traditions | D496: PWR-100 | E496: =IF(D496="","",IFERROR(VLOOKUP(D496,$A$2:$B$1656,2,FALSE),"")) | F496: 3 | G496: Power arising from birth, bloodline, species, mutation, emotion, or an internal supernatural faculty. | H496: Record source, method, cost, limits, access, and social control separately. | I496: sorcery; innate magic; bloodline gift | J496: Defines who can access power, why it works, and what obligations accompany it. | K496: sorcery; innate magic; bloodline gift | L496: Preserve each source's ontology, culture, history, and terminology when making comparisons. | M496: Core Family
A497: PWR-103 | B497: Divine Miracle | C497: Power Traditions | D497: PWR-100 | E497: =IF(D497="","",IFERROR(VLOOKUP(D497,$A$2:$B$1656,2,FALSE),"")) | F497: 3 | G497: Power granted, mediated, or authorized by a deity, sacred order, cosmic law, or religious covenant. | H497: Record source, method, cost, limits, access, and social control separately. | I497: divine magic; miracle; blessing | J497: Defines who can access power, why it works, and what obligations accompany it. | K497: divine magic; miracle; blessing | L497: Preserve each source's ontology, culture, history, and terminology when making comparisons. | M497: Core Family
A498: PWR-104 | B498: Pact and Contract Magic | C498: Power Traditions | D498: PWR-100 | E498: =IF(D498="","",IFERROR(VLOOKUP(D498,$A$2:$B$1656,2,FALSE),"")) | F498: 3 | G498: Power obtained through negotiated obligation with a spirit, fiend, deity, patron, artifact, or institution. | H498: Record source, method, cost, limits, access, and social control separately. | I498: pact magic; contract; bargain | J498: Defines who can access power, why it works, and what obligations accompany it. | K498: pact magic; contract; bargain | L498: Preserve each source's ontology, culture, history, and terminology when making comparisons. | M498: Core Family
A499: PWR-105 | B499: Spirit Mediation | C499: Power Traditions | D499: PWR-100 | E499: =IF(D499="","",IFERROR(VLOOKUP(D499,$A$2:$B$1656,2,FALSE),"")) | F499: 3 | G499: Power exercised by communicating with, hosting, appeasing, bargaining with, or directing spirits. | H499: Record source, method, cost, limits, access, and social control separately. | I499: spirit magic; shamanism; mediumship | J499: Defines who can access power, why it works, and what obligations accompany it. | K499: spirit magic; shamanism; mediumship | L499: Preserve each source's ontology, culture, history, and terminology when making comparisons. | M499: Core Family
A500: PWR-106 | B500: Animistic Reciprocity | C500: Power Traditions | D500: PWR-100 | E500: =IF(D500="","",IFERROR(VLOOKUP(D500,$A$2:$B$1656,2,FALSE),"")) | F500: 3 | G500: Power grounded in reciprocal relationships with places, animals, ancestors, objects, and nonhuman persons. | H500: Record source, method, cost, limits, access, and social control separately. | I500: animism; reciprocal spirit practice | J500: Defines who can access power, why it works, and what obligations accompany it. | K500: animism; reciprocal spirit practice | L500: Preserve each source's ontology, culture, history, and terminology when making comparisons. | M500: Core Family
A501: PWR-107 | B501: Ancestral Power | C501: Power Traditions | D501: PWR-100 | E501: =IF(D501="","",IFERROR(VLOOKUP(D501,$A$2:$B$1656,2,FALSE),"")) | F501: 3 | G501: Abilities inherited from or actively supplied by ancestors, lineage memory, relics, or clan spirits. | H501: Record source, method, cost, limits, access, and social control separately. | I501: ancestor magic; lineage blessing | J501: Defines who can access power, why it works, and what obligations accompany it. | K501: ancestor magic; lineage blessing | L501: Preserve each source's ontology, culture, history, and terminology when making comparisons. | M501: Core Family
A502: PWR-108 | B502: Bloodline Inheritance | C502: Power Traditions | D502: PWR-100 | E502: =IF(D502="","",IFERROR(VLOOKUP(D502,$A$2:$B$1656,2,FALSE),"")) | F502: 3 | G502: Power transmitted genealogically through family, species, royal descent, or magical heredity. | H502: Record source, method, cost, limits, access, and social control separately. | I502: bloodline power; inherited gift | J502: Defines who can access power, why it works, and what obligations accompany it. | K502: bloodline power; inherited gift | L502: Preserve each source's ontology, culture, history, and terminology when making comparisons. | M502: Core Family
A503: PWR-109 | B503: Chosen or Invested Power | C503: Power Traditions | D503: PWR-100 | E503: =IF(D503="","",IFERROR(VLOOKUP(D503,$A$2:$B$1656,2,FALSE),"")) | F503: 3 | G503: Power bestowed by selection, office, prophecy, relic, crown, deity, or institution. | H503: Record source, method, cost, limits, access, and social control separately. | I503: chosen power; investiture; mantle | J503: Defines who can access power, why it works, and what obligations accompany it. | K503: chosen power; investiture; mantle | L503: Preserve each source's ontology, culture, history, and terminology when making comparisons. | M503: Core Family
A504: PWR-110 | B504: Artifact-Mediated Power | C504: Power Traditions | D504: PWR-100 | E504: =IF(D504="","",IFERROR(VLOOKUP(D504,$A$2:$B$1656,2,FALSE),"")) | F504: 3 | G504: Abilities accessible primarily through a weapon, relic, book, ring, mask, suit, or other external object. | H504: Record source, method, cost, limits, access, and social control separately. | I504: artifact magic; relic power; focus-dependent power | J504: Defines who can access power, why it works, and what obligations accompany it. | K504: artifact magic; relic power; focus-dependent power | L504: Preserve each source's ontology, culture, history, and terminology when making comparisons. | M504: Core Family
A505: PWR-111 | B505: Symbiotic Power | C505: Power Traditions | D505: PWR-100 | E505: =IF(D505="","",IFERROR(VLOOKUP(D505,$A$2:$B$1656,2,FALSE),"")) | F505: 3 | G505: Abilities produced by partnership or entanglement with another organism, spirit, machine, or entity. | H505: Record source, method, cost, limits, access, and social control separately. | I505: symbiote power; bonded entity; host power | J505: Defines who can access power, why it works, and what obligations accompany it. | K505: symbiote power; bonded entity; host power | L505: Preserve each source's ontology, culture, history, and terminology when making comparisons. | M505: Core Family
A506: PWR-112 | B506: Possession and Channeling | C506: Power Traditions | D506: PWR-100 | E506: =IF(D506="","",IFERROR(VLOOKUP(D506,$A$2:$B$1656,2,FALSE),"")) | F506: 3 | G506: Power gained by allowing another being to inhabit, speak through, or partially control the user. | H506: Record source, method, cost, limits, access, and social control separately. | I506: channeling; possession power; vessel | J506: Defines who can access power, why it works, and what obligations accompany it. | K506: channeling; possession power; vessel | L506: Preserve each source's ontology, culture, history, and terminology when making comparisons. | M506: Core Family
... A634: PWR-622 | B634: World-System Authority | C634: Power Traditions | D634: PWR-600 | E634: =IF(D634="","",IFERROR(VLOOKUP(D634,$A$2:$B$1656,2,FALSE),"")) | F634: 3 | G634: Administrative or interface-like power to inspect, assign, edit, spawn, or override system rules. | H634: Record source, method, cost, limits, access, and social control separately. | I634: system authority; administrator power; game master power | J634: Counters, escalation, copying, corruption, rule modification, and system-level interaction. | K634: system authority; administrator power; game master power | L634: Preserve each source's ontology, culture, history, and terminology when making comparisons. | M634: Core Family
A635: STA-100 | B635: Death and Undeath States | C635: States & Transformations | D635: STA-000 | E635: =IF(D635="","",IFERROR(VLOOKUP(D635,$A$2:$B$1656,2,FALSE),"")) | F635: 2 | G635: Conditions arising from death, interrupted death, postmortem persistence, or necromantic continuation. | H635: A state is acquired or changeable; do not automatically treat it as a species, culture, or profession. | J635: Models templates, curses, awakenings, and transformations independently of the base person. | K635: Death and Undeath States | L635: Preserve each source's ontology, culture, history, and terminology when making comparisons. | M635: Category
A636: STA-200 | B636: Bodily Transformation States | C636: States & Transformations | D636: STA-000 | E636: =IF(D636="","",IFERROR(VLOOKUP(D636,$A$2:$B$1656,2,FALSE),"")) | F636: 2 | G636: Changes to species, anatomy, scale, material, health, or biological capability. | H636: A state is acquired or changeable; do not automatically treat it as a species, culture, or profession. | J636: Models templates, curses, awakenings, and transformations independently of the base person. | K636: Bodily Transformation States | L636: Preserve each source's ontology, culture, history, and terminology when making comparisons. | M636: Category
A637: STA-300 | B637: Spiritual and Identity States | C637: States & Transformations | D637: STA-000 | E637: =IF(D637="","",IFERROR(VLOOKUP(D637,$A$2:$B$1656,2,FALSE),"")) | F637: 2 | G637: Changes to soul, memory, possession, consciousness, destiny, or continuity of self. | H637: A state is acquired or changeable; do not automatically treat it as a species, culture, or profession. | J637: Models templates, curses, awakenings, and transformations independently of the base person. | K637: Spiritual and Identity States | L637: Preserve each source's ontology, culture, history, and terminology when making comparisons. | M637: Category
A638: STA-400 | B638: Empowerment, Bond, and Alignment States | C638: States & Transformations | D638: STA-000 | E638: =IF(D638="","",IFERROR(VLOOKUP(D638,$A$2:$B$1656,2,FALSE),"")) | F638: 2 | G638: Acquired affiliations, awakenings, blessings, pacts, attunements, and power-bearing conditions. | H638: A state is acquired or changeable; do not automatically treat it as a species, culture, or profession. | J638: Models templates, curses, awakenings, and transformations independently of the base person. | K638: Empowerment, Bond, and Alignment States | L638: Preserve each source's ontology, culture, history, and terminology when making comparisons. | M638: Category
A639: STA-500 | B639: Displacement and Meta-Narrative States | C639: States & Transformations | D639: STA-000 | E639: =IF(D639="","",IFERROR(VLOOKUP(D639,$A$2:$B$1656,2,FALSE),"")) | F639: 2 | G639: Conditions involving reincarnation, summoning, time travel, systemization, or migration between worlds. | H639: A state is acquired or changeable; do not automatically treat it as a species, culture, or profession. | J639: Models templates, curses, awakenings, and transformations independently of the base person. | K639: Displacement and Meta-Narrative States | L639: Preserve each source's ontology, culture, history, and terminology when making comparisons. | M639: Category
A640: STA-101 | B640: Dead | C640: States & Transformations | D640: STA-100 | E640: =IF(D640="","",IFERROR(VLOOKUP(D640,$A$2:$B$1656,2,FALSE),"")) | F640: 3 | G640: Biological life has ended and no continuing agency is assumed. | H640: Record reversibility, agency, transmission, cost, social recognition, and identity continuity. | I640: death; deceased | J640: Horror, immortality, grief, persistence, postmortem duty, and life-death cosmology. | K640: death; deceased | L640: Preserve each source's ontology, culture, history, and terminology when making comparisons. | M640: Core Family
A641: STA-102 | B641: Ghosthood | C641: States & Transformations | D641: STA-100 | E641: =IF(D641="","",IFERROR(VLOOKUP(D641,$A$2:$B$1656,2,FALSE),"")) | F641: 3 | G641: The deceased persists as a disembodied spirit retaining some identity or attachment. | H641: Record reversibility, agency, transmission, cost, social recognition, and identity continuity. | I641: ghost; shade; spirit | J641: Horror, immortality, grief, persistence, postmortem duty, and life-death cosmology. | K641: ghost; shade; spirit | L641: Preserve each source's ontology, culture, history, and terminology when making comparisons. | M641: Core Family
A642: STA-103 | B642: Revenant Return | C642: States & Transformations | D642: STA-100 | E642: =IF(D642="","",IFERROR(VLOOKUP(D642,$A$2:$B$1656,2,FALSE),"")) | F642: 3 | G642: A dead person returns bodily or spiritually to complete a specific purpose. | H642: Record reversibility, agency, transmission, cost, social recognition, and identity continuity. | I642: revenant; returned dead | J642: Horror, immortality, grief, persistence, postmortem duty, and life-death cosmology. | K642: revenant; returned dead | L642: Preserve each source's ontology, culture, history, and terminology when making comparisons. | M642: Core Family
A643: STA-104 | B643: Zombification | C643: States & Transformations | D643: STA-100 | E643: =IF(D643="","",IFERROR(VLOOKUP(D643,$A$2:$B$1656,2,FALSE),"")) | F643: 3 | G643: A corpse or living person becomes a decayed, controlled, infected, or hunger-driven undead body. | H643: Record reversibility, agency, transmission, cost, social recognition, and identity continuity. | I643: zombie; walking dead; infection | J643: Horror, immortality, grief, persistence, postmortem duty, and life-death cosmology. | K643: zombie; walking dead; infection | L643: Preserve each source's ontology, culture, history, and terminology when making comparisons. | M643: Core Family
A644: STA-105 | B644: Skeletal Animation | C644: States & Transformations | D644: STA-100 | E644: =IF(D644="","",IFERROR(VLOOKUP(D644,$A$2:$B$1656,2,FALSE),"")) | F644: 3 | G644: Bones are animated as a servant, soldier, or autonomous undead form. | H644: Record reversibility, agency, transmission, cost, social recognition, and identity continuity. | I644: skeleton; bone animation | J644: Horror, immortality, grief, persistence, postmortem duty, and life-death cosmology. | K644: skeleton; bone animation | L644: Preserve each source's ontology, culture, history, and terminology when making comparisons. | M644: Core Family
A645: STA-106 | B645: Vampirism | C645: States & Transformations | D645: STA-100 | E645: =IF(D645="","",IFERROR(VLOOKUP(D645,$A$2:$B$1656,2,FALSE),"")) | F645: 3 | G645: A person becomes a blood-, life-, emotion-, or soul-feeding immortal or undead being. | H645: Record reversibility, agency, transmission, cost, social recognition, and identity continuity. | I645: vampire; blood curse | J645: Horror, immortality, grief, persistence, postmortem duty, and life-death cosmology. | K645: vampire; blood curse | L645: Preserve each source's ontology, culture, history, and terminology when making comparisons. | M645: Core Family
A646: STA-107 | B646: Lichdom | C646: States & Transformations | D646: STA-100 | E646: =IF(D646="","",IFERROR(VLOOKUP(D646,$A$2:$B$1656,2,FALSE),"")) | F646: 3 | G646: A person deliberately converts into an undead, soul-anchored form to preserve intellect and power. | H646: Record reversibility, agency, transmission, cost, social recognition, and identity continuity. | I646: lich; soul vessel | J646: Horror, immortality, grief, persistence, postmortem duty, and life-death cosmology. | K646: lich; soul vessel | L646: Preserve each source's ontology, culture, history, and terminology when making comparisons. | M646: Core Family
A647: STA-108 | B647: Wight or Wraith Transformation | C647: States & Transformations | D647: STA-100 | E647: =IF(D647="","",IFERROR(VLOOKUP(D647,$A$2:$B$1656,2,FALSE),"")) | F647: 3 | G647: A person becomes a powerful spectral or preserved undead associated with draining, curse, or barrow power. | H647: Record reversibility, agency, transmission, cost, social recognition, and identity continuity. | I647: wight; wraith; shade | J647: Horror, immortality, grief, persistence, postmortem duty, and life-death cosmology. | K647: wight; wraith; shade | L647: Preserve each source's ontology, culture, history, and terminology when making comparisons. | M647: Core Family
A648: STA-109 | B648: Mummification and Tomb Binding | C648: States & Transformations | D648: STA-100 | E648: =IF(D648="","",IFERROR(VLOOKUP(D648,$A$2:$B$1656,2,FALSE),"")) | F648: 3 | G648: A preserved dead body is animated or bound to royal, funerary, or territorial duties. | H648: Record reversibility, agency, transmission, cost, social recognition, and identity continuity. | I648: mummy; tomb guardian | J648: Horror, immortality, grief, persistence, postmortem duty, and life-death cosmology. | K648: mummy; tomb guardian | L648: Preserve each source's ontology, culture, history, and terminology when making comparisons. | M648: Core Family
A649: STA-110 | B649: Death-Knight Transformation | C649: States & Transformations | D649: STA-100 | E649: =IF(D649="","",IFERROR(VLOOKUP(D649,$A$2:$B$1656,2,FALSE),"")) | F649: 3 | G649: A martial figure becomes undead or death-bound while retaining skill, armor, and command. | H649: Record reversibility, agency, transmission, cost, social recognition, and identity continuity. | I649: death knight; grave knight | J649: Horror, immortality, grief, persistence, postmortem duty, and life-death cosmology. | K649: death knight; grave knight | L649: Preserve each source's ontology, culture, history, and terminology when making comparisons. | M649: Core Family
A650: STA-111 | B650: Soul Trapping | C650: States & Transformations | D650: STA-100 | E650: =IF(D650="","",IFERROR(VLOOKUP(D650,$A$2:$B$1656,2,FALSE),"")) | F650: 3 | G650: A soul is confined in an object, body, location, spell, or captor rather than passing on. | H650: Record reversibility, agency, transmission, cost, social recognition, and identity continuity. | I650: soul trap; spirit prison | J650: Horror, immortality, grief, persistence, postmortem duty, and life-death cosmology. | K650: soul trap; spirit prison | L650: Preserve each source's ontology, culture, history, and terminology when making comparisons. | M650: Core Family
A651: STA-112 | B651: Soul Fragmentation | C651: States & Transformations | D651: STA-100 | E651: =IF(D651="","",IFERROR(VLOOKUP(D651,$A$2:$B$1656,2,FALSE),"")) | F651: 3 | G651: A person's soul or identity is divided into pieces, vessels, copies, or incomplete aspects. | H651: Record reversibility, agency, transmission, cost, social recognition, and identity continuity. | I651: soul split; horcrux-like division; fragment | J651: Horror, immortality, grief, persistence, postmortem duty, and life-death cosmology. | K651: soul split; horcrux-like division; fragment | L651: Preserve each source's ontology, culture, history, and terminology when making comparisons. | M651: Core Family
... A756: STA-520 | B756: Dream Incarnation | C756: States & Transformations | D756: STA-500 | E756: =IF(D756="","",IFERROR(VLOOKUP(D756,$A$2:$B$1656,2,FALSE),"")) | F756: 3 | G756: A person or being manifests from dream, story, imagination, or collective belief. | H756: Record reversibility, agency, transmission, cost, social recognition, and identity continuity. | I756: dreamborn; thoughtform; tulpa-like | J756: Second-life narratives, portal fantasy, game systems, time travel, and alternate identity. | K756: dreamborn; thoughtform; tulpa-like | L756: The term 'tulpa' has specific Tibetan Buddhist roots and a modern occult history; use with care. | M756: Core Family
A757: INS-100 | B757: Professional and Economic Organizations | C757: Institutions & Affiliations | D757: INS-000 | E757: =IF(D757="","",IFERROR(VLOOKUP(D757,$A$2:$B$1656,2,FALSE),"")) | F757: 2 | G757: Guilds, companies, colleges, and networks organized around work, trade, craft, or adventure. | H757: An institution is an organized collective; membership may confer a role, identity, power, or status without being any of those itself. | J757: Supports comparison of guilds, orders, schools, factions, and political structures. | K757: Professional and Economic Organizations | L757: Preserve each source's ontology, culture, history, and terminology when making comparisons. | M757: Category
A758: INS-200 | B758: Martial and Protective Organizations | C758: Institutions & Affiliations | D758: INS-000 | E758: =IF(D758="","",IFERROR(VLOOKUP(D758,$A$2:$B$1656,2,FALSE),"")) | F758: 2 | G758: Armies, knightly orders, guards, ranger lodges, mercenary companies, and specialist hunters. | H758: An institution is an organized collective; membership may confer a role, identity, power, or status without being any of those itself. | J758: Supports comparison of guilds, orders, schools, factions, and political structures. | K758: Martial and Protective Organizations | L758: Preserve each source's ontology, culture, history, and terminology when making comparisons. | M758: Category
A759: INS-300 | B759: Religious and Magical Organizations | C759: Institutions & Affiliations | D759: INS-000 | E759: =IF(D759="","",IFERROR(VLOOKUP(D759,$A$2:$B$1656,2,FALSE),"")) | F759: 2 | G759: Churches, cults, temples, covens, circles, academies, sects, and initiatory traditions. | H759: An institution is an organized collective; membership may confer a role, identity, power, or status without being any of those itself. | J759: Supports comparison of guilds, orders, schools, factions, and political structures. | K759: Religious and Magical Organizations | L759: Preserve each source's ontology, culture, history, and terminology when making comparisons. | M759: Category
A760: INS-400 | B760: Kinship, Political, and Secret Organizations | C760: Institutions & Affiliations | D760: INS-000 | E760: =IF(D760="","",IFERROR(VLOOKUP(D760,$A$2:$B$1656,2,FALSE),"")) | F760: 2 | G760: Clans, houses, tribes, courts, castes, councils, conspiracies, and covert networks. | H760: An institution is an organized collective; membership may confer a role, identity, power, or status without being any of those itself. | J760: Supports comparison of guilds, orders, schools, factions, and political structures. | K760: Kinship, Political, and Secret Organizations | L760: Preserve each source's ontology, culture, history, and terminology when making comparisons. | M760: Category
A761: INS-101 | B761: Adventurers' Guild | C761: Institutions & Affiliations | D761: INS-100 | E761: =IF(D761="","",IFERROR(VLOOKUP(D761,$A$2:$B$1656,2,FALSE),"")) | F761: 3 | G761: Organization that registers, ranks, contracts, equips, regulates, or rewards adventurers. | H761: Record membership rules, hierarchy, resources, jurisdiction, ideology, and relation to the state. | I761: adventurer guild; quest guild; hunters' association | J761: Labor regulation, training, contracting, economic coordination, and social mobility. | K761: adventurer guild; quest guild; hunters' association | L761: Preserve each source's ontology, culture, history, and terminology when making comparisons. | M761: Core Family
A762: INS-102 | B762: Mage Guild | C762: Institutions & Affiliations | D762: INS-100 | E762: =IF(D762="","",IFERROR(VLOOKUP(D762,$A$2:$B$1656,2,FALSE),"")) | F762: 3 | G762: Professional body that licenses, trains, employs, protects, or controls magic users. | H762: Record membership rules, hierarchy, resources, jurisdiction, ideology, and relation to the state. | I762: mages' guild; wizard guild; arcane association | J762: Labor regulation, training, contracting, economic coordination, and social mobility. | K762: mages' guild; wizard guild; arcane association | L762: Preserve each source's ontology, culture, history, and terminology when making comparisons. | M762: Core Family
A763: INS-103 | B763: Thieves' Guild | C763: Institutions & Affiliations | D763: INS-100 | E763: =IF(D763="","",IFERROR(VLOOKUP(D763,$A$2:$B$1656,2,FALSE),"")) | F763: 3 | G763: Organized network that coordinates theft, fences goods, enforces territory, and regulates underworld conduct. | H763: Record membership rules, hierarchy, resources, jurisdiction, ideology, and relation to the state. | I763: thieves guild; criminal guild | J763: Labor regulation, training, contracting, economic coordination, and social mobility. | K763: thieves guild; criminal guild | L763: Preserve each source's ontology, culture, history, and terminology when making comparisons. | M763: Core Family
A764: INS-104 | B764: Assassins' Guild | C764: Institutions & Affiliations | D764: INS-100 | E764: =IF(D764="","",IFERROR(VLOOKUP(D764,$A$2:$B$1656,2,FALSE),"")) | F764: 3 | G764: Institution that trains, contracts, legitimizes, or ritualizes professional killing. | H764: Record membership rules, hierarchy, resources, jurisdiction, ideology, and relation to the state. | I764: assassin guild; killers' order | J764: Labor regulation, training, contracting, economic coordination, and social mobility. | K764: assassin guild; killers' order | L764: Preserve each source's ontology, culture, history, and terminology when making comparisons. | M764: Core Family
...

Sheet Source Corpus
A1: Source_ID | B1: Title_or_Franchise | C1: Creator_Studio | D1: Medium | E1: Region_Tradition | F1: First_Appearance | G1: Continuity_Unit | H1: Priority_Tier | I1: Distinctive_Contribution | J1: Scope_Note | K1: Reference_URL | L1: Status
A2: SRC-001 | B2: Ancient Greek Mythology | C2: Multiple oral and literary traditions | D2: Mythology / Folklore | E2: Mediterranean / Greek | F2: Archaic–Classical antiquity | G2: Culture-specific corpus | H2: Tier 1 | I2: Gods, demigods, heroes, monsters, nymphs, underworld journeys, metamorphosis, prophecy. | J2: Treat adaptations/editions separately when taxonomically material. | K2: https://en.wikipedia.org/wiki/Ancient_Greek_Mythology | L2: Included
A3: SRC-002 | B3: Norse Mythology | C3: Old Norse oral and literary traditions | D3: Mythology / Folklore | E3: Northern Europe / Norse | F3: Medieval textual witnesses | G3: Poetic Edda, Prose Edda, sagas | H3: Tier 1 | I3: Jötnar, elves, dwarfs, draugr, world serpent, valkyries, fate, cyclical apocalypse. | J3: Treat adaptations/editions separately when taxonomically material. | K3: https://en.wikipedia.org/wiki/Norse_Mythology | L3: Included
A4: SRC-003 | B4: Irish Mythological Cycle | C4: Irish oral and manuscript traditions | D4: Mythology / Folklore | E4: Ireland | F4: Medieval textual witnesses | G4: Mythological, Ulster, Fenian, and Kings' cycles | H4: Tier 1 | I4: Otherworld peoples, geasa, heroic warbands, sovereignty, transformation, fairy mounds. | J4: Treat adaptations/editions separately when taxonomically material. | K4: https://en.wikipedia.org/wiki/Irish_Mythological_Cycle | L4: Included
A5: SRC-004 | B5: The Mabinogion | C5: Medieval Welsh authors and oral traditions | D5: Literature / Mythic Cycle | E5: Wales | F5: 12th–14th centuries | G5: Welsh tale collection | H5: Tier 1 | I5: Otherworld journeys, enchantment, shapechange, cursed sovereignty, heroic kinship. | J5: Treat adaptations/editions separately when taxonomically material. | K5: https://en.wikipedia.org/wiki/The_Mabinogion | L5: Included
A6: SRC-005 | B6: Arthurian Legend | C6: Multiple medieval and later authors | D6: Literature / Mythic Cycle | E6: Britain / France / Europe | F6: 12th century onward | G6: Romance tradition | H6: Tier 1 | I6: Knights, quests, holy relics, enchanted weapons, courtly orders, grail patterns. | J6: Treat adaptations/editions separately when taxonomically material. | K6: https://en.wikipedia.org/wiki/Arthurian_Legend | L6: Included
A7: SRC-006 | B7: Kalevala | C7: Compiled by Elias Lönnrot from Finnish and Karelian oral poetry | D7: Epic / Folklore | E7: Finland / Karelia | F7: 1835/1849 | G7: National epic compilation | H7: Tier 1 | I7: Song magic, smithing, shamanic heroes, artifact quest, rival cultures. | J7: Treat adaptations/editions separately when taxonomically material. | K7: https://en.wikipedia.org/wiki/Kalevala | L7: Included
A8: SRC-007 | B8: Slavic Folklore | C8: Multiple regional traditions | D8: Mythology / Folklore | E8: Eastern and Central Europe | F8: Premodern and modern collections | G8: Culture-specific corpus | H8: Tier 1 | I8: Vampiric revenants, household spirits, witches, forest beings, dragons, deathless sorcerers. | J8: Treat adaptations/editions separately when taxonomically material. | K8: https://en.wikipedia.org/wiki/Slavic_Folklore | L8: Included
A9: SRC-008 | B9: Grimm Fairy Tales | C9: Jacob and Wilhelm Grimm, collectors/editors | D9: Fairy Tale Collection | E9: German-speaking Europe | F9: 1812 onward | G9: Multiple editions | H9: Tier 1 | I9: Witches, enchanted animals, curses, helpers, trials, transformed royals, household magic. | J9: Treat adaptations/editions separately when taxonomically material. | K9: https://en.wikipedia.org/wiki/Grimm_Fairy_Tales | L9: Included
A10: SRC-009 | B10: One Thousand and One Nights | C10: Multiple Arabic, Persian, South Asian, and later compilers | D10: Frame Tale / Folklore | E10: Middle East / South Asia | F10: Medieval compilation | G10: Multiple manuscript and translation traditions | H10: Tier 1 | I10: Djinn, sorcerers, talismans, magical travel, tricksters, merchants, nested stories. | J10: Treat adaptations/editions separately when taxonomically material. | K10: https://en.wikipedia.org/wiki/One_Thousand_and_One_Nights | L10: Included
A11: SRC-010 | B11: Jinn Traditions | C11: Arabic and Islamic religious, folkloric, and literary traditions | D11: Mythology / Folklore | E11: Middle East / Islamic world | F11: Qur'anic and later traditions | G11: Culture-specific corpus | H11: Tier 1 | I11: Spirit personhood, free will, binding, possession, fire origins, parallel societies. | J11: Treat adaptations/editions separately when taxonomically material. | K11: https://en.wikipedia.org/wiki/Jinn_Traditions | L11: Included
A12: SRC-011 | B12: Shahnameh | C12: Ferdowsi | D12: Epic Literature | E12: Persian / Iranian | F12: c. 1010 | G12: Persian epic | H12: Tier 1 | I12: Heroic warriors, kingship, demons, magical birds, tragic champions, dynastic cycles. | J12: Treat adaptations/editions separately when taxonomically material. | K12: https://en.wikipedia.org/wiki/Shahnameh | L12: Included
... A282: SRC-281 | B282: Age of Mythology: Retold | C282: World's Edge, Forgotten Empires, and Xbox Game Studios | D282: Video Game / Real-Time Strategy | E282: United States / global commercial adaptation | F282: 2024; Version 2.0 snapshot through August 2, 2026 | G282: Retold base game plus dated official pantheon and god-pack expansions | H282: Tier 1 | I282: A major adaptation laboratory that converts deities into faction and technology choices, worship into favor economies, myths into units and counters, divine intervention into activated god powers, relics into map objectives, and cosmic ages into progression tiers. | J282: Commercial game adaptation, not evidence for the source traditions it represents. Version-stamp pantheon rosters, expansions, balance changes, and names; analyze Greek, Egyptian, Norse, Atlantean, Chinese, Japanese, and Mexica/Aztec adaptation layers separately. | K282: https://www.ageofempires.com/games/age-of-mythology-retold/ | L282: Included

Sheet Seed Catalogue
A1: Entry_ID | B1: Canonical_Name | C1: Source_ID | D1: Source_Title | E1: Continuity | F1: Native_Record_Type | G1: Primary_Archetype_ID | H1: Primary_Archetype_Name | I1: Additional_Archetype_IDs | J1: Additional_Archetype_Names | K1: Ontology_or_Role_Summary | L1: Power_Basis | M1: Key_Distinction | N1: Comparative_Notes | O1: Canon_Status | P1: Evidence_Level | Q1: Source_Reference | R1: Reference_URL | S1: Review_Status
A2: ENT-0001 | B2: Quendi (Elves) | C2: SRC-026 | D2: Tolkien's Legendarium | E2: Legendarium (literary corpus) | F2: People / metaphysical kind | G2: PPL-102 | H2: =IFERROR(VLOOKUP(G2,'Master Taxonomy'!$A$2:$B$1656,2,FALSE),"") | K2: The awakened Firstborn Children of Ilúvatar, with multiple historical and cultural divisions. | L2: Created people; embodied immortal life bound to Arda. | M2: Their immortality, fate, and relation to Arda differ fundamentally from most game-elves. | N2: Primary reference point for the modern high-fantasy elf family. | O2: Primary canon | P2: Official reference reviewed | Q2: Tolkien Estate setting overview and primary legendarium corpus. | R2: https://www.tolkienestate.com/writing/ | S2: Seeded
A3: ENT-0002 | B3: Vanyar | C3: SRC-026 | D3: Tolkien's Legendarium | E3: Legendarium (literary corpus) | F3: Elven people | G3: PPL-102 | H3: =IFERROR(VLOOKUP(G3,'Master Taxonomy'!$A$2:$B$1656,2,FALSE),"") | K3: One of the principal Eldarin peoples, associated with Aman and the Valar. | L3: Lineage, migration history, and culture. | M3: A canonical subgroup, not a separate biological species. | N3: High or celestial elf analogues are only partial. | O3: Primary canon | P3: Official reference reviewed | Q3: Tolkien Estate setting overview and primary legendarium corpus. | R3: https://www.tolkienestate.com/writing/ | S3: Seeded
A4: ENT-0003 | B4: Noldor | C4: SRC-026 | D4: Tolkien's Legendarium | E4: Legendarium (literary corpus) | F4: Elven people | G4: PPL-102 | H4: =IFERROR(VLOOKUP(G4,'Master Taxonomy'!$A$2:$B$1656,2,FALSE),"") | I4: ROL-306 | J4: Magical Scholar | K4: An Eldarin people renowned for craft, knowledge, political tragedy, and exile. | L4: Cultural learning, craft, and personal spiritual stature. | M4: Their defining traits are historical and cultural rather than a game-stat package. | N4: Influential on learned, tragic, and high-elven archetypes. | O4: Primary canon | P4: Official reference reviewed | Q4: Tolkien Estate setting overview and primary legendarium corpus. | R4: https://www.tolkienestate.com/writing/ | S4: Seeded
A5: ENT-0004 | B5: Teleri and Sindar | C5: SRC-026 | D5: Tolkien's Legendarium | E5: Legendarium (literary corpus) | F5: Elven peoples | G5: PPL-102 | H5: =IFERROR(VLOOKUP(G5,'Master Taxonomy'!$A$2:$B$1656,2,FALSE),"") | K5: Related Eldarin peoples whose histories include maritime, forest, and Beleriandic cultures. | L5: Kinship, migration, geography, and cultural development. | M5: The umbrella conceals several distinct peoples and political histories. | N5: Partial source for sea-elf and woodland-elf developments. | O5: Primary canon | P5: Official reference reviewed | Q5: Tolkien Estate setting overview and primary legendarium corpus. | R5: https://www.tolkienestate.com/writing/ | S5: Seeded
A6: ENT-0005 | B6: Avari | C6: SRC-026 | D6: Tolkien's Legendarium | E6: Legendarium (literary corpus) | F6: Elven peoples | G6: PPL-102 | H6: =IFERROR(VLOOKUP(G6,'Master Taxonomy'!$A$2:$B$1656,2,FALSE),"") | K6: Elves who refused the Great Journey, comprising multiple unenumerated peoples. | L6: Historical choice and later cultural divergence. | M6: Not synonymous with evil, dark, or subterranean elves. | N6: Useful corrective to moralized elf subrace taxonomies. | O6: Primary canon | P6: Official reference reviewed | Q6: Tolkien Estate setting overview and primary legendarium corpus. | R6: https://www.tolkienestate.com/writing/ | S6: Seeded
A7: ENT-0006 | B7: Khazâd (Dwarves) | C7: SRC-026 | D7: Tolkien's Legendarium | E7: Legendarium (literary corpus) | F7: Created people | G7: PPL-103 | H7: =IFERROR(VLOOKUP(G7,'Master Taxonomy'!$A$2:$B$1656,2,FALSE),"") | K7: A people fashioned by Aulë and adopted into Ilúvatar's design, organized in kindreds and houses. | L7: Created ancestry, craft tradition, kinship, and long memory. | M7: Their origin and eschatology are specific to Tolkien's cosmology. | N7: Central modern template for dwarven peoples. | O7: Primary canon | P7: Official reference reviewed | Q7: Tolkien Estate setting overview and primary legendarium corpus. | R7: https://www.tolkienestate.com/writing/ | S7: Seeded
A8: ENT-0007 | B8: Hobbits | C8: SRC-026 | D8: Tolkien's Legendarium | E8: Legendarium (literary corpus) | F8: Human-related people | G8: PPL-104 | H8: =IFERROR(VLOOKUP(G8,'Master Taxonomy'!$A$2:$B$1656,2,FALSE),"") | K8: A small-statured people associated with agrarian domesticity, resilience, and obscurity. | L8: Natural people with cultural and regional branches. | M8: They are a people and culture, not inherently an adventuring class. | N8: Primary model for halflings and domestic smallfolk. | O8: Primary canon | P8: Official reference reviewed | Q8: Tolkien Estate setting overview and primary legendarium corpus. | R8: https://www.tolkienestate.com/writing/ | S8: Seeded
A9: ENT-0008 | B9: Men (Atani and later peoples) | C9: SRC-026 | D9: Tolkien's Legendarium | E9: Legendarium (literary corpus) | F9: Mortal people | G9: PPL-101 | H9: =IFERROR(VLOOKUP(G9,'Master Taxonomy'!$A$2:$B$1656,2,FALSE),"") | K9: The mortal Secondborn Children of Ilúvatar, divided across many nations and histories. | L9: Natural people; mortality is metaphysically significant. | M9: Human cultures must not be collapsed into one archetypal society. | N9: Baseline human plurality in epic fantasy. | O9: Primary canon | P9: Official reference reviewed | Q9: Tolkien Estate setting overview and primary legendarium corpus. | R9: https://www.tolkienestate.com/writing/ | S9: Seeded
A10: ENT-0009 | B10: Dúnedain | C10: SRC-026 | D10: Tolkien's Legendarium | E10: Legendarium (literary corpus) | F10: Human lineage and culture | G10: PPL-101 | H10: =IFERROR(VLOOKUP(G10,'Master Taxonomy'!$A$2:$B$1656,2,FALSE),"") | I10: ROL-125 | J10: Ranger | K10: Long-lived Númenórean-descended human peoples, including northern and southern branches. | L10: Lineage, inherited longevity, culture, and historical institutions. | M10: Not a separate species; 'ranger' applies especially to a later northern role. | N10: Long-lived lost-kingdom human and ranger analogues. | O10: Primary canon | P10: Official reference reviewed | Q10: Tolkien Estate setting overview and primary legendarium corpus. | R10: https://www.tolkienestate.com/writing/ | S10: Seeded
A11: ENT-0010 | B11: Ents | C11: SRC-026 | D11: Tolkien's Legendarium | E11: Legendarium (literary corpus) | F11: Nonhuman people | G11: PPL-901 | H11: =IFERROR(VLOOKUP(G11,'Master Taxonomy'!$A$2:$B$1656,2,FALSE),"") | I11: PPL-203 | J11: Dryads and Tree-Bound Beings | K11: Ancient tree-shepherds with personhood, language, memory, and ecological vocation. | L11: Created or awakened nature-associated beings. | M11: Not simply animated trees or generic elementals. | N11: Major treefolk and ecological guardian archetype. | O11: Primary canon | P11: Official reference reviewed | Q11: Tolkien Estate setting overview and primary legendarium corpus. | R11: https://www.tolkienestate.com/writing/ | S11: Seeded
A12: ENT-0011 | B12: Ainur | C12: SRC-026 | D12: Tolkien's Legendarium | E12: Legendarium (literary corpus) | F12: Primordial spiritual beings | G12: PPL-400 | H12: =IFERROR(VLOOKUP(G12,'Master Taxonomy'!$A$2:$B$1656,2,FALSE),"") | K12: Pre-cosmic spirits who participate in the shaping and governance of the created world. | L12: Created spiritual nature and delegated cosmic authority. | M12: They are neither a biological race nor a single moral faction. | N12: Comparable to angelic or demiurgic orders only with caution. | O12: Primary canon | P12: Official reference reviewed | Q12: Tolkien Estate setting overview and primary legendarium corpus. | R12: https://www.tolkienestate.com/writing/ | S12: Seeded
A13: ENT-0012 | B13: Valar | C13: SRC-026 | D13: Tolkien's Legendarium | E13: Legendarium (literary corpus) | F13: Divine governing order | G13: PPL-401 | H13: =IFERROR(VLOOKUP(G13,'Master Taxonomy'!$A$2:$B$1656,2,FALSE),"") | I13: PPL-405 | J13: Divine Servitors | K13: The greatest Ainur who enter Arda and exercise delegated guardianship over it. | L13: Spiritual nature and divinely delegated authority. | M13: Often called gods by inhabitants, but subordinate to Ilúvatar. | N13: Functional analogue to pantheons, not exact polytheistic deities. | O13: Primary canon | P13: Official reference reviewed | Q13: Tolkien Estate setting overview and primary legendarium corpus. | R13: https://www.tolkienestate.com/writing/ | S13: Seeded
A14: ENT-0013 | B14: Maiar | C14: SRC-026 | D14: Tolkien's Legendarium | E14: Legendarium (literary corpus) | F14: Lesser Ainur | G14: PPL-404 | H14: =IFERROR(VLOOKUP(G14,'Master Taxonomy'!$A$2:$B$1656,2,FALSE),"") | I14: PPL-405 | J14: Divine Servitors | K14: Ainur of lesser order who serve, teach, rule, tempt, or oppose within Arda. | L14: Spiritual nature; variable embodiment and allegiance. | M14: Includes radically different figures and cannot be treated as one profession. | N14: Angel, spirit-lord, and embodied emissary analogues. | O14: Primary canon | P14: Official reference reviewed | Q14: Tolkien Estate setting overview and primary legendarium corpus. | R14: https://www.tolkienestate.com/writing/ | S14: Seeded
A15: ENT-0014 | B15: Istari (Wizards) | C15: SRC-026 | D15: Tolkien's Legendarium | E15: Legendarium (literary corpus) | F15: Invested emissary order | G15: ROL-301 | H15: =IFERROR(VLOOKUP(G15,'Master Taxonomy'!$A$2:$B$1656,2,FALSE),"") | I15: PPL-405 | J15: Divine Servitors | K15: Maiar sent in constrained embodied form to counsel resistance against Sauron. | L15: Delegated mission, spiritual nature, knowledge, and limited embodied power. | M15: ‘Wizard’ here denotes an order and identity, not merely a learned spellcaster class. | N15: A key example of one source term crossing role, being-type, and institution. | O15: Primary canon | P15: Official reference reviewed | Q15: Tolkien Estate setting overview and primary legendarium corpus. | R15: https://www.tolkienestate.com/writing/ | S15: Seeded
A16: ENT-0015 | B16: Orcs | C16: SRC-026 | D16: Tolkien's Legendarium | E16: Legendarium (literary corpus) | F16: Corrupted or bred people | G16: PPL-106 | H16: =IFERROR(VLOOKUP(G16,'Master Taxonomy'!$A$2:$B$1656,2,FALSE),"") | K16: Hostile speaking peoples associated with the powers of Morgoth and Sauron. | L16: Corruption, breeding, domination, and disputed textual origins. | M16: Their ultimate origin varies across Tolkien's developing conceptions. | N16: Foundational but ethically contested model for fantasy orcs. | O16: Primary canon | P16: Official reference reviewed | Q16: Tolkien Estate setting overview and primary legendarium corpus. | R16: https://www.tolkienestate.com/writing/ | S16: Seeded
A17: ENT-0016 | B17: Trolls | C17: SRC-026 | D17: Tolkien's Legendarium | E17: Legendarium (literary corpus) | F17: Created or corrupted beings | G17: PPL-110 | H17: =IFERROR(VLOOKUP(G17,'Master Taxonomy'!$A$2:$B$1656,2,FALSE),"") | K17: Large hostile beings appearing in several forms and periods. | L17: Corruptive making, imitation, and physical might. | M17: Different troll kinds have different intelligence and vulnerabilities. | N17: Influential giant-brute and troll archetype. | O17: Primary canon | P17: Official reference reviewed | Q17: Tolkien Estate setting overview and primary legendarium corpus. | R17: https://www.tolkienestate.com/writing/ | S17: Seeded
A18: ENT-0017 | B18: Balrogs | C18: SRC-026 | D18: Tolkien's Legendarium | E18: Legendarium (literary corpus) | F18: Fallen primordial spirits | G18: PPL-504 | H18: =IFERROR(VLOOKUP(G18,'Master Taxonomy'!$A$2:$B$1656,2,FALSE),"") | I18: PPL-501 | J18: Demons | K18: Corrupted Maiar of fire and shadow serving Morgoth. | L18: Spiritual nature, corruption, terror, and elemental manifestation. | M18: Not a biological demon species or generic fire monster. | N18: Major fallen-angelic demon and ancient lieutenant archetype. | O18: Primary canon | P18: Official reference reviewed | Q18: Tolkien Estate setting overview and primary legendarium corpus. | R18: https://www.tolkienestate.com/writing/ | S18: Seeded
A19: ENT-0018 | B19: Dragons | C19: SRC-026 | D19: Tolkien's Legendarium | E19: Legendarium (literary corpus) | F19: Created monster-kind | G19: PPL-801 | H19: =IFERROR(VLOOKUP(G19,'Master Taxonomy'!$A$2:$B$1656,2,FALSE),"") | K19: Powerful intelligent draconic beings first bred by Morgoth, including winged and wingless forms. | L19: Created monstrous lineage, cunning, physical power, and often speech. | M19: The corpus distinguishes individuals and forms rather than a game taxonomy of colors. | N19: Central Western literary dragon lineage. | O19: Primary canon | P19: Official reference reviewed | Q19: Tolkien Estate setting overview and primary legendarium corpus. | R19: https://www.tolkienestate.com/writing/ | S19: Seeded
A20: ENT-0019 | B20: Great Eagles | C20: SRC-026 | D20: Tolkien's Legendarium | E20: Legendarium (literary corpus) | F20: Sapient great beasts | G20: PPL-820 | H20: =IFERROR(VLOOKUP(G20,'Master Taxonomy'!$A$2:$B$1656,2,FALSE),"") | K20: Enormous intelligent eagles associated with Manwë and decisive interventions. | L20: Natural or spiritually elevated beasthood and divine association. | M20: They are agents with their own limits, not a routine transport mechanism. | N20: Divine messenger and rescue-beast analogue. | O20: Primary canon | P20: Official reference reviewed | Q20: Tolkien Estate setting overview and primary legendarium corpus. | R20: https://www.tolkienestate.com/writing/ | S20: Seeded
A21: ENT-0020 | B21: Great Spiders | C21: SRC-026 | D21: Tolkien's Legendarium | E21: Legendarium (literary corpus) | F21: Monstrous lineage | G21: PPL-818 | H21: =IFERROR(VLOOKUP(G21,'Master Taxonomy'!$A$2:$B$1656,2,FALSE),"") | K21: Predatory giant spiders descending from or echoing Ungoliant's monstrous lineage. | L21: Monstrous descent, appetite, poison, webs, and dark ecology. | M21: Ungoliant's own ontology remains exceptional and obscure. | N21: Foundational giant-spider and devouring-darkness archetype. | O21: Primary canon | P21: Official reference reviewed | Q21: Tolkien Estate setting overview and primary legendarium corpus. | R21: https://www.tolkienestate.com/writing/ | S21: Seeded
A22: ENT-0021 | B22: Nazgûl (Ringwraiths) | C22: SRC-026 | D22: Tolkien's Legendarium | E22: Legendarium (literary corpus) | F22: Transformed undead-like servants | G22: PPL-606 | H22: =IFERROR(VLOOKUP(G22,'Master Taxonomy'!$A$2:$B$1656,2,FALSE),"") | I22: STA-402 | J22: Relic Bearer | K22: Human kings and lords reduced to spectral servitude through Rings of Power. | L22: Artifact-mediated corruption, prolonged life, domination, and disembodiment. | M22: They are neither generic ghosts nor self-directed undead. | N22: Primary cursed-relic wraith and dark-lieutenant model. | O22: Primary canon | P22: Official reference reviewed | Q22: Tolkien Estate setting overview and primary legendarium corpus. | R22: https://www.tolkienestate.com/writing/ | S22: Seeded
A23: ENT-0022 | B23: Barrow-wights | C23: SRC-026 | D23: Tolkien's Legendarium | E23: Legendarium (literary corpus) | F23: Malignant undead spirits | G23: PPL-606 | H23: =IFERROR(VLOOKUP(G23,'Master Taxonomy'!$A$2:$B$1656,2,FALSE),"") | K23: Hostile spirits inhabiting ancient burial places and remains. | L23: Necromantic occupation of tombs and corpse-associated haunting. | M23: Distinct from the Nazgûl despite the shared English term 'wight.' | N23: Barrow-dead and tomb guardian undead analogue. | O23: Primary canon | P23: Official reference reviewed | Q23: Tolkien Estate setting overview and primary legendarium corpus. | R23: https://www.tolkienestate.com/writing/ | S23: Seeded
A24: ENT-0023 | B24: Beornings and skin-changers | C24: SRC-026 | D24: Tolkien's Legendarium | E24: Legendarium (literary corpus) | F24: Human lineage / shapeshifters | G24: PPL-1001 | H24: =IFERROR(VLOOKUP(G24,'Master Taxonomy'!$A$2:$B$1656,2,FALSE),"") | I24: ROL-511 | J24: Shapeshifting Warden | K24: Human-associated people or lineage linked to voluntary bear transformation and wilderness guardianship. | L24: Innate or inherited shapeshifting. | M24: Not presented as a conventional contagious were-creature curse. | N24: Positive guardian-shapeshifter and werebear analogue. | O24: Primary canon | P24: Official reference reviewed | Q24: Tolkien Estate setting overview and primary legendarium corpus. | R24: https://www.tolkienestate.com/writing/ | S24: Seeded
A25: ENT-0024 | B25: Rangers of the North | C25: SRC-026 | D25: Tolkien's Legendarium | E25: Legendarium (literary corpus) | F25: Martial vocation and remnant institution | G25: ROL-125 | H25: =IFERROR(VLOOKUP(G25,'Master Taxonomy'!$A$2:$B$1656,2,FALSE),"") | I25: INS-220 | J25: Adventuring Company | K25: Dúnedain guardians operating in dispersed secrecy across the former northern kingdom. | L25: Training, lineage, fieldcraft, and inherited political duty. | M25: Ranger is a historical vocation here, not a spellcasting class. | N25: Influential wilderness guardian and hidden-heir support archetype. | O25: Primary canon | P25: Official reference reviewed | Q25: Tolkien Estate setting overview and primary legendarium corpus. | R25: https://www.tolkienestate.com/writing/ | S25: Seeded
A26: ENT-0025 | B26: Rohirrim | C26: SRC-026 | D26: Tolkien's Legendarium | E26: Legendarium (literary corpus) | F26: Human culture and military tradition | G26: ROL-116 | H26: =IFERROR(VLOOKUP(G26,'Master Taxonomy'!$A$2:$B$1656,2,FALSE),"") | I26: CIV-205 | J26: Nomadic Horse Culture | K26: A settled human kingdom whose identity and warfare center strongly on horses and mounted retinues. | L26: Culture, horsemanship, fealty, and military organization. | M26: They are not strictly nomadic; the horse-culture tag is comparative, not exact. | N26: Mounted heroic culture and cavalry kingdom analogue. | O26: Primary canon | P26: Official reference reviewed | Q26: Tolkien Estate setting overview and primary legendarium corpus. | R26: https://www.tolkienestate.com/writing/ | S26: Seeded
A27: ENT-0026 | B27: Children of the Forest | C27: SRC-046 | D27: A Song of Ice and Fire | E27: Novel continuity | F27: Nonhuman people | G27: PPL-200 | H27: =IFERROR(VLOOKUP(G27,'Master Taxonomy'!$A$2:$B$1656,2,FALSE),"") | I27: PPL-206 | J27: Land and Watershed Spirits | K27: An ancient nonhuman people associated with the forests, weirwoods, greenseeing, and deep history. | L27: Innate gifts, ritual knowledge, and ecological-cultural relationship. | M27: They are a distinct people, not simply fairies or Tolkien-style elves. | N27: Partial analogue to elder nature peoples and land-linked fae. | O27: Primary canon | P27: Primary text reviewed | Q27: George R. R. Martin's primary novel corpus and official world-book listings. | R27: https://georgerrmartin.com/all-books/cover-gallery/a-song-of-ice-and-fire/ | S27: Seeded
A28: ENT-0027 | B28: Giants | C28: SRC-046 | D28: A Song of Ice and Fire | E28: Novel continuity | F28: Nonhuman people | G28: PPL-108 | H28: =IFERROR(VLOOKUP(G28,'Master Taxonomy'!$A$2:$B$1656,2,FALSE),"") | K28: Large sapient beings of the far North with their own language and culture. | L28: Natural ancestry and northern ecology. | M28: They are a people rather than interchangeable giant monsters. | N28: Giantfolk and remnant elder-people analogue. | O28: Primary canon | P28: Primary text reviewed | Q28: George R. R. Martin's primary novel corpus and official world-book listings. | R28: https://georgerrmartin.com/all-books/cover-gallery/a-song-of-ice-and-fire/ | S28: Seeded
A29: ENT-0028 | B29: The Others | C29: SRC-046 | D29: A Song of Ice and Fire | E29: Novel continuity | F29: Mysterious nonhuman beings | G29: PPL-200 | H29: =IFERROR(VLOOKUP(G29,'Master Taxonomy'!$A$2:$B$1656,2,FALSE),"") | I29: PWR-203 | J29: Ice and Cold Magic | K29: Elegant, deadly beings of supernatural cold whose origin and full nature remain unresolved in the novels. | L29: Unknown or disputed supernatural ontology; cold-associated power. | M29: They should not be classified as undead merely because they animate wights. | N29: Ice-fae, deathly outsider, and apocalyptic elder-being analogues. | O29: Primary canon | P29: Primary text reviewed | Q29: George R. R. Martin's primary novel corpus and official world-book listings. | R29: https://georgerrmartin.com/all-books/cover-gallery/a-song-of-ice-and-fire/ | S29: Seeded
A30: ENT-0029 | B30: Wights | C30: SRC-046 | D30: A Song of Ice and Fire | E30: Novel continuity | F30: Animated dead | G30: PPL-604 | H30: =IFERROR(VLOOKUP(G30,'Master Taxonomy'!$A$2:$B$1656,2,FALSE),"") | I30: STA-115 | J30: Undead Servitude | K30: Corpses reanimated as servants or extensions of the Others' power. | L30: External supernatural animation. | M30: Their agency and mechanics differ from disease-based zombies. | N30: Puppet-undead and necromantic army analogue. | O30: Primary canon | P30: Primary text reviewed | Q30: George R. R. Martin's primary novel corpus and official world-book listings. | R30: https://georgerrmartin.com/all-books/cover-gallery/a-song-of-ice-and-fire/ | S30: Seeded
A31: ENT-0030 | B31: Dragons | C31: SRC-046 | D31: A Song of Ice and Fire | E31: Novel continuity | F31: Magical animal species | G31: PPL-801 | H31: =IFERROR(VLOOKUP(G31,'Master Taxonomy'!$A$2:$B$1656,2,FALSE),"") | K31: Rare fire-breathing dragons linked to Valyrian power, conquest, and magical resurgence. | L31: Biology intertwined with magic, breeding, and uncertain ritual conditions. | M31: They are animal-like yet intelligent and symbolically dynastic, not conventional speaking sages. | N31: War-dragon, dynastic weapon, and returning-magic archetype. | O31: Primary canon | P31: Primary text reviewed | Q31: George R. R. Martin's primary novel corpus and official world-book listings. | R31: https://georgerrmartin.com/all-books/cover-gallery/a-song-of-ice-and-fire/ | S31: Seeded
A32: ENT-0031 | B32: Direwolves | C32: SRC-046 | D32: A Song of Ice and Fire | E32: Novel continuity | F32: Megafaunal species | G32: PPL-819 | H32: =IFERROR(VLOOKUP(G32,'Master Taxonomy'!$A$2:$B$1656,2,FALSE),"") | K32: Oversized wolves of northern ecology and Stark symbolism. | L32: Natural species with possible magical bonds. | M32: Their narrative role combines animal companion, omen, and heraldic identity. | N32: Dire animal and soul-bonded companion analogue. | O32: Primary canon | P32: Primary text reviewed | Q32: George R. R. Martin's primary novel corpus and official world-book listings. | R32: https://georgerrmartin.com/all-books/cover-gallery/a-song-of-ice-and-fire/ | S32: Seeded
A33: ENT-0032 | B33: Skinchangers | C33: SRC-046 | D33: A Song of Ice and Fire | E33: Novel continuity | F33: Innate magical practitioners | G33: ROL-511 | H33: =IFERROR(VLOOKUP(G33,'Master Taxonomy'!$A$2:$B$1656,2,FALSE),"") | I33: PWR-310 | J33: Shapeshifting | K33: People able to enter and influence animal minds, sometimes called wargs when linked to wolves. | L33: Innate gift, psychic projection, and animal bond. | M33: This is mind-transference, not bodily transformation. | N33: Warg, beast-mind, and animal-possession archetype. | O33: Primary canon | P33: Primary text reviewed | Q33: George R. R. Martin's primary novel corpus and official world-book listings. | R33: https://georgerrmartin.com/all-books/cover-gallery/a-song-of-ice-and-fire/ | S33: Seeded
A34: ENT-0033 | B34: Greenseers | C34: SRC-046 | D34: A Song of Ice and Fire | E34: Novel continuity | F34: Visionary magical role | G34: ROL-316 | H34: =IFERROR(VLOOKUP(G34,'Master Taxonomy'!$A$2:$B$1656,2,FALSE),"") | I34: PPL-206 | J34: Land and Watershed Spirits | K34: Rare gifted figures associated with green dreams, weirwoods, memory, and remote perception. | L34: Innate vision mediated by living sacred networks. | M34: They are not generic druids; prophecy and memory are central. | N34: Ecological oracle and world-memory seer analogue. | O34: Primary canon | P34: Primary text reviewed | Q34: George R. R. Martin's primary novel corpus and official world-book listings. | R34: https://georgerrmartin.com/all-books/cover-gallery/a-song-of-ice-and-fire/ | S34: Seeded
A35: ENT-0034 | B35: Maesters | C35: SRC-046 | D35: A Song of Ice and Fire | E35: Novel continuity | F35: Scholarly professional order | G35: ROL-624 | H35: =IFERROR(VLOOKUP(G35,'Master Taxonomy'!$A$2:$B$1656,2,FALSE),"") | I35: MEC-112; INS-108 | J35: Healer; Scholarly Society | K35: A trained order serving noble households in medicine, letters, counsel, and specialized learning. | L35: Institutional education and chains denoting fields of study. | M35: Mostly nonmagical despite operating in a fantasy world. | N35: Scholar-bureaucrat, court physician, and learned order archetype. | O35: Primary canon | P35: Primary text reviewed | Q35: George R. R. Martin's primary novel corpus and official world-book listings. | R35: https://georgerrmartin.com/all-books/cover-gallery/a-song-of-ice-and-fire/ | S35: Seeded
A36: ENT-0035 | B36: Faceless Men | C36: SRC-046 | D36: A Song of Ice and Fire | E36: Novel continuity | F36: Religious assassin order | G36: ROL-835 | H36: =IFERROR(VLOOKUP(G36,'Master Taxonomy'!$A$2:$B$1656,2,FALSE),"") | I36: INS-211 | J36: Assassin Order | K36: An esoteric assassins' order combining disguise, death ritual, theology, and paid service. | L36: Training, identity effacement, poisons, disguise, and sacred ideology. | M36: They are not reducible to a thieves' guild or stealth class. | N36: Ritual assassin, death cult, and identity-erasure order analogue. | O36: Primary canon | P36: Primary text reviewed | Q36: George R. R. Martin's primary novel corpus and official world-book listings. | R36: https://georgerrmartin.com/all-books/cover-gallery/a-song-of-ice-and-fire/ | S36: Seeded
A37: ENT-0036 | B37: Night's Watch | C37: SRC-046 | D37: A Song of Ice and Fire | E37: Novel continuity | F37: Military-protective order | G37: INS-200 | H37: =IFERROR(VLOOKUP(G37,'Master Taxonomy'!$A$2:$B$1656,2,FALSE),"") | I37: ROL-125 | J37: Ranger | K37: A sworn frontier brotherhood tasked with guarding the Wall and realms of men. | L37: Oaths, institutional roles, fortifications, and fieldcraft. | M37: Its members include stewards and builders as well as rangers. | N37: Frontier order, penal brotherhood, and monster-border guard archetype. | O37: Primary canon | P37: Primary text reviewed | Q37: George R. R. Martin's primary novel corpus and official world-book listings. | R37: https://georgerrmartin.com/all-books/cover-gallery/a-song-of-ice-and-fire/ | S37: Seeded
A38: ENT-0037 | B38: Kingsguard | C38: SRC-046 | D38: A Song of Ice and Fire | E38: Novel continuity | F38: Royal knightly order | G38: INS-202 | H38: =IFERROR(VLOOKUP(G38,'Master Taxonomy'!$A$2:$B$1656,2,FALSE),"") | I38: ROL-115 | J38: Knight | K38: Seven sworn knights charged with lifelong protection of the monarch and royal family. | L38: Oath, elite martial status, court office, and celibate service. | M38: The role is simultaneously honor ideal, political institution, and narrative test of vows. | N38: Elite royal bodyguard and oath-conflict archetype. | O38: Primary canon | P38: Primary text reviewed | Q38: George R. R. Martin's primary novel corpus and official world-book listings. | R38: https://georgerrmartin.com/all-books/cover-gallery/a-song-of-ice-and-fire/ | S38: Seeded
A39: ENT-0038 | B39: Red Priests and Priestesses | C39: SRC-046 | D39: A Song of Ice and Fire | E39: Novel continuity | F39: Religious magical vocation | G39: ROL-401 | H39: =IFERROR(VLOOKUP(G39,'Master Taxonomy'!$A$2:$B$1656,2,FALSE),"") | I39: PWR-201; ROL-409 | J39: Fire Magic; Prophet | K39: Clergy of R'hllor associated with fire ritual, visions, conversion, and occasional miracles. | L39: Faith, ritual fire, sacrifice, prophecy, and uncertain divine agency. | M39: Individual capabilities vary; theology and magic cannot be assumed identical. | N39: Fire priest, apocalyptic missionary, and miracle-worker analogue. | O39: Primary canon | P39: Primary text reviewed | Q39: George R. R. Martin's primary novel corpus and official world-book listings. | R39: https://georgerrmartin.com/all-books/cover-gallery/a-song-of-ice-and-fire/ | S39: Seeded
A40: ENT-0039 | B40: Warlocks of Qarth | C40: SRC-046 | D40: A Song of Ice and Fire | E40: Novel continuity | F40: Arcane fraternity | G40: ROL-304 | H40: =IFERROR(VLOOKUP(G40,'Master Taxonomy'!$A$2:$B$1656,2,FALSE),"") | I40: INS-102 | J40: Mage Guild | K40: A Qartheen magical fraternity associated with the House of the Undying and shade of the evening. | L40: Ritual initiation, altered perception, and institutional lore. | M40: Their title is source-specific and not equivalent to pact magic in every game. | N40: Esoteric mage guild and decadent occult order analogue. | O40: Primary canon | P40: Primary text reviewed | Q40: George R. R. Martin's primary novel corpus and official world-book listings. | R40: https://georgerrmartin.com/all-books/cover-gallery/a-song-of-ice-and-fire/ | S40: Seeded
A41: ENT-0040 | B41: Shadowbinders | C41: SRC-046 | D41: A Song of Ice and Fire | E41: Novel continuity | F41: Occult magical role | G41: ROL-328 | H41: =IFERROR(VLOOKUP(G41,'Master Taxonomy'!$A$2:$B$1656,2,FALSE),"") | I41: PWR-208 | J41: Shadow and Darkness Magic | K41: Practitioners associated with Asshai, shadows, glamours, and dangerous ritual arts. | L41: Ritual knowledge, shadow manipulation, sacrifice, and obscure traditions. | M41: The novels intentionally leave mechanisms and limits uncertain. | N41: Shadow mage and forbidden ritualist analogue. | O41: Primary canon | P41: Primary text reviewed | Q41: George R. R. Martin's primary novel corpus and official world-book listings. | R41: https://georgerrmartin.com/all-books/cover-gallery/a-song-of-ice-and-fire/ | S41: Seeded
A42: ENT-0041 | B42: Guild of Alchemists (Pyromancers) | C42: SRC-046 | D42: A Song of Ice and Fire | E42: Novel continuity | F42: Artificer-alchemist guild | G42: ROL-338 | H42: =IFERROR(VLOOKUP(G42,'Master Taxonomy'!$A$2:$B$1656,2,FALSE),"") | I42: ROL-321; INS-102 | J42: Pyromancer; Mage Guild | K42: A King's Landing guild that manufactures and controls volatile wildfire. | L42: Specialized chemistry or magic, guarded formulae, and urban privilege. | M42: ‘Pyromancer’ here is an institutional title, not merely a fire-spell caster. | N42: Explosives guild, state alchemist, and secretive artificer analogue. | O42: Primary canon | P42: Primary text reviewed | Q42: George R. R. Martin's primary novel corpus and official world-book listings. | R42: https://georgerrmartin.com/all-books/cover-gallery/a-song-of-ice-and-fire/ | S42: Seeded
A43: ENT-0042 | B43: Dothraki bloodriders and mounted warriors | C43: SRC-046 | D43: A Song of Ice and Fire | E43: Novel continuity | F43: Martial-cultural role | G43: ROL-132 | H43: =IFERROR(VLOOKUP(G43,'Master Taxonomy'!$A$2:$B$1656,2,FALSE),"") | I43: CIV-205 | J43: Nomadic Horse Culture | K43: Mounted warriors embedded in a mobile pastoral and raiding culture, with bloodriders bound personally to a khal. | L43: Horsemanship, bows, arakhs, kinship, and personal loyalty. | M43: A complex fictional culture should not be reduced to a generic barbarian class. | N43: Steppe-inspired cavalry and oath-companion analogue. | O43: Primary canon | P43: Primary text reviewed | Q43: George R. R. Martin's primary novel corpus and official world-book listings. | R43: https://georgerrmartin.com/all-books/cover-gallery/a-song-of-ice-and-fire/ | S43: Seeded
A44: ENT-0043 | B44: Unsullied | C44: SRC-046 | D44: A Song of Ice and Fire | E44: Novel continuity | F44: Engineered military caste | G44: ROL-104 | H44: =IFERROR(VLOOKUP(G44,'Master Taxonomy'!$A$2:$B$1656,2,FALSE),"") | I44: ROL-102 | J44: Soldier | K44: Slave soldiers trained from childhood for formation discipline and obedience. | L44: Coercive institutional conditioning, drill, spear-and-shield tactics. | M44: Their identity is a produced social condition, not a biological people. | N44: Elite conditioned infantry and eunuch guard analogue. | O44: Primary canon | P44: Primary text reviewed | Q44: George R. R. Martin's primary novel corpus and official world-book listings. | R44: https://georgerrmartin.com/all-books/cover-gallery/a-song-of-ice-and-fire/ | S44: Seeded
... A48: ENT-0047 | B48: Valyrian dragonlords | C48: SRC-046 | D48: A Song of Ice and Fire | E48: Novel continuity | F48: Ruling magical culture | G48: CIV-110 | H48: =IFERROR(VLOOKUP(G48,'Master Taxonomy'!$A$2:$B$1656,2,FALSE),"") | I48: ROL-150 | J48: Dragon Rider | K48: An aristocratic civilization whose military and political dominance depended heavily on dragons. | L48: Bloodline ideology, dragon mastery, sorcery, slavery, and imperial institutions. | M48: This is a civilizational formation, not a player class. | N48: Dragon-rider empire and magical imperial elite archetype. | O48: Primary canon | P48: Primary text reviewed | Q48: George R. R. Martin's primary novel corpus and official world-book listings. | R48: https://georgerrmartin.com/all-books/cover-gallery/a-song-of-ice-and-fire/ | S48: Seeded
A49: ENT-0048 | B49: Humans | C49: SRC-047 | D49: The Witcher | E49: Book continuity | F49: People | G49: PPL-101 | H49: =IFERROR(VLOOKUP(G49,'Master Taxonomy'!$A$2:$B$1656,2,FALSE),"") | K49: The dominant mortal population across many Northern Kingdoms and Nilfgaardian territories. | L49: Natural ancestry and diverse cultures. | M49: Human political communities are not one culture or moral bloc. | N49: Baseline human plurality. | O49: Primary canon | P49: Official reference reviewed | Q49: Sapkowski's primary book continuity; official franchise material used for orientation. | R49: https://www.andrzejsapkowski.pl/ | S49: Seeded
A50: ENT-0049 | B50: Aen Seidhe | C50: SRC-047 | D50: The Witcher | E50: Book continuity | F50: Elven people | G50: PPL-102 | H50: =IFERROR(VLOOKUP(G50,'Master Taxonomy'!$A$2:$B$1656,2,FALSE),"") | K50: Elves of the Continent, marked by long life, dispossession, political division, and cultural memory. | L50: Natural or otherworldly ancestry, longevity, and historical culture. | M50: Not interchangeable with Tolkien's Elves or generic woodland elves. | N50: Dispossessed elder people and long-lived minority analogue. | O50: Primary canon | P50: Official reference reviewed | Q50: Sapkowski's primary book continuity; official franchise material used for orientation. | R50: https://www.andrzejsapkowski.pl/ | S50: Seeded
A51: ENT-0050 | B51: Aen Elle | C51: SRC-047 | D51: The Witcher | E51: Book continuity | F51: Otherworldly elven people | G51: PPL-102 | H51: =IFERROR(VLOOKUP(G51,'Master Taxonomy'!$A$2:$B$1656,2,FALSE),"") | I51: PPL-211 | J51: Wild Hunt Beings | K51: An elven people inhabiting another world and linked to the riders known as the Wild Hunt. | L51: Otherworldly ancestry, interworld travel, and imperial power. | M51: Their social position and cosmology differ sharply from the Aen Seidhe. | N51: Otherworld elf, faerie host, and planar empire analogue. | O51: Primary canon | P51: Official reference reviewed | Q51: Sapkowski's primary book continuity; official franchise material used for orientation. | R51: https://www.andrzejsapkowski.pl/ | S51: Seeded
A52: ENT-0051 | B52: Dwarves | C52: SRC-047 | D52: The Witcher | E52: Book continuity | F52: People | G52: PPL-103 | H52: =IFERROR(VLOOKUP(G52,'Master Taxonomy'!$A$2:$B$1656,2,FALSE),"") | K52: Long-lived nonhuman people integrated unevenly into human realms and trades. | L52: Natural ancestry, community networks, craft, commerce, and military service. | M52: Their social history is shaped by racism and coexistence, not only mining stereotypes. | N52: Urbanized and diasporic dwarf analogue. | O52: Primary canon | P52: Official reference reviewed | Q52: Sapkowski's primary book continuity; official franchise material used for orientation. | R52: https://www.andrzejsapkowski.pl/ | S52: Seeded
A53: ENT-0052 | B53: Gnomes | C53: SRC-047 | D53: The Witcher | E53: Book continuity | F53: People | G53: PPL-105 | H53: =IFERROR(VLOOKUP(G53,'Master Taxonomy'!$A$2:$B$1656,2,FALSE),"") | K53: An old nonhuman people associated with craftsmanship and settlement before later arrivals. | L53: Natural ancestry and cultural history. | M53: They are distinct from dwarves despite overlapping craft associations. | N53: Small elder-craft people analogue. | O53: Primary canon | P53: Official reference reviewed | Q53: Sapkowski's primary book continuity; official franchise material used for orientation. | R53: https://www.andrzejsapkowski.pl/ | S53: Seeded
A54: ENT-0053 | B54: Halflings | C54: SRC-047 | D54: The Witcher | E54: Book continuity | F54: People | G54: PPL-104 | H54: =IFERROR(VLOOKUP(G54,'Master Taxonomy'!$A$2:$B$1656,2,FALSE),"") | K54: Small-statured nonhuman people living within the Continent's mixed societies. | L54: Natural ancestry and local culture. | M54: Not defined solely by pastoral domesticity or stealth mechanics. | N54: Halfling and integrated smallfolk analogue. | O54: Primary canon | P54: Official reference reviewed | Q54: Sapkowski's primary book continuity; official franchise material used for orientation. | R54: https://www.andrzejsapkowski.pl/ | S54: Seeded
A55: ENT-0054 | B55: Dryads of Brokilon | C55: SRC-047 | D55: The Witcher | E55: Book continuity | F55: Forest people / transformed community | G55: PPL-203 | H55: =IFERROR(VLOOKUP(G55,'Master Taxonomy'!$A$2:$B$1656,2,FALSE),"") | I55: ROL-512 | J55: Forest Warden | K55: A female forest society defending Brokilon and incorporating outsiders through distinctive practices. | L55: Forest-linked identity, archery, ritual, and community reproduction. | M55: The source combines peoplehood, culture, and transformation rather than a simple plant species. | N55: Militant forest guardian and liminal dryad society analogue. | O55: Primary canon | P55: Official reference reviewed | Q55: Sapkowski's primary book continuity; official franchise material used for orientation. | R55: https://www.andrzejsapkowski.pl/ | S55: Seeded
A56: ENT-0055 | B56: Witchers | C56: SRC-047 | D56: The Witcher | E56: Book continuity | F56: Transformed professional order | G56: ROL-810 | H56: =IFERROR(VLOOKUP(G56,'Master Taxonomy'!$A$2:$B$1656,2,FALSE),"") | I56: STA-206; INS-208 | J56: Alchemical Enhancement; Monster-Hunter Order | K56: Professionally trained and alchemically mutated monster hunters using swords, potions, signs, and field knowledge. | L56: Training, mutation, alchemy, equipment, and school traditions. | M56: Witcher is simultaneously profession, transformed condition, and institutional lineage—not a species. | N56: Canonical alchemical monster-hunter archetype. | O56: Primary canon | P56: Official reference reviewed | Q56: Sapkowski's primary book continuity; official franchise material used for orientation. | R56: https://www.andrzejsapkowski.pl/ | S56: Seeded
A57: ENT-0056 | B57: Witcher schools | C57: SRC-047 | D57: The Witcher | E57: Franchise-spanning institutional layer | F57: Training orders | G57: INS-209 | H57: =IFERROR(VLOOKUP(G57,'Master Taxonomy'!$A$2:$B$1656,2,FALSE),"") | I57: INS-208 | J57: Monster-Hunter Order | K57: Distinct training lineages or institutions associated with witcher creation and practice. | L57: Institutional inheritance, techniques, symbols, and regional histories. | M57: The number, status, and detail of schools vary across books, games, and licensed adaptations. | N57: Monster-hunter school and prestige tradition analogue. | O57: Primary canon | P57: Official reference reviewed | Q57: Sapkowski's primary book continuity; official franchise material used for orientation. | R57: https://www.andrzejsapkowski.pl/ | S57: Seeded
A58: ENT-0057 | B58: Sorcerers and sorceresses | C58: SRC-047 | D58: The Witcher | E58: Book continuity | F58: Magical profession and elite | G58: ROL-301 | H58: =IFERROR(VLOOKUP(G58,'Master Taxonomy'!$A$2:$B$1656,2,FALSE),"") | I58: INS-102 | J58: Mage Guild | K58: Highly trained magic users who often combine scholarship, court service, politics, and personal ambition. | L58: Education, innate aptitude, magical theory, and institutions. | M58: Gendered titles do not imply different power systems. | N58: Court mage, academy wizard, and transnational magical elite analogue. | O58: Primary canon | P58: Official reference reviewed | Q58: Sapkowski's primary book continuity; official franchise material used for orientation. | R58: https://www.andrzejsapkowski.pl/ | S58: Seeded
A59: ENT-0058 | B59: Aretuza | C59: SRC-047 | D59: The Witcher | E59: Book continuity | F59: Mage academy | G59: INS-308 | H59: =IFERROR(VLOOKUP(G59,'Master Taxonomy'!$A$2:$B$1656,2,FALSE),"") | I59: INS-102 | J59: Mage Guild | K59: An elite institution for training female magic users and socializing them into political networks. | L59: Formal education, discipline, patronage, and institutional authority. | M59: It is an institution rather than a class or spell tradition. | N59: Magical boarding academy and elite professional network analogue. | O59: Primary canon | P59: Official reference reviewed | Q59: Sapkowski's primary book continuity; official franchise material used for orientation. | R59: https://www.andrzejsapkowski.pl/ | S59: Seeded
A60: ENT-0059 | B60: Ban Ard | C60: SRC-047 | D60: The Witcher | E60: Book continuity | F60: Mage academy | G60: INS-308 | H60: =IFERROR(VLOOKUP(G60,'Master Taxonomy'!$A$2:$B$1656,2,FALSE),"") | I60: INS-102 | J60: Mage Guild | K60: A major institution associated with the education of male mages. | L60: Formal magical education and professional networking. | M60: Adaptations may change its prominence or details. | N60: Parallel mage-academy archetype. | O60: Primary canon | P60: Official reference reviewed | Q60: Sapkowski's primary book continuity; official franchise material used for orientation. | R60: https://www.andrzejsapkowski.pl/ | S60: Seeded
A61: ENT-0060 | B61: Druids | C61: SRC-047 | D61: The Witcher | E61: Book continuity | F61: Nature-spiritual vocation | G61: ROL-501 | H61: =IFERROR(VLOOKUP(G61,'Master Taxonomy'!$A$2:$B$1656,2,FALSE),"") | I61: INS-307 | J61: Druid Circle | K61: Practitioners organized in groves and circles, associated with nature, healing, wisdom, and local authority. | L61: Training, spiritual practice, herbal knowledge, and nature magic. | M61: They are not merely shapeshifting game druids. | N61: Druidic college, healer, and ecological mediator analogue. | O61: Primary canon | P61: Official reference reviewed | Q61: Sapkowski's primary book continuity; official franchise material used for orientation. | R61: https://www.andrzejsapkowski.pl/ | S61: Seeded
A62: ENT-0061 | B62: Higher vampires | C62: SRC-047 | D62: The Witcher | E62: Book and game continuities distinguished | F62: Nonhuman people / monster kind | G62: PPL-607 | H62: =IFERROR(VLOOKUP(G62,'Master Taxonomy'!$A$2:$B$1656,2,FALSE),"") | K62: Powerful intelligent beings called vampires whose origin and biology differ from conventional human undead. | L62: Post-Conjunction or otherworldly species, innate powers, and long life. | M62: They should not automatically be treated as reanimated corpses or contagious undead. | N62: Vampire-by-function but species-like in ontology. | O62: Primary canon | P62: Official reference reviewed | Q62: Sapkowski's primary book continuity; official franchise material used for orientation. | R62: https://www.andrzejsapkowski.pl/ | S62: Seeded
A63: ENT-0062 | B63: Bruxae and related vampire kinds | C63: SRC-047 | D63: The Witcher | E63: Book continuity | F63: Monster kind | G63: PPL-607 | H63: =IFERROR(VLOOKUP(G63,'Master Taxonomy'!$A$2:$B$1656,2,FALSE),"") | K63: Predatory vampire forms combining humanoid intelligence, transformation, speed, and sonic or blood-associated traits. | L63: Innate monster physiology and predation. | M63: The setting's vampire taxonomy is plural rather than one universal template. | N63: Monstrous vampire subtype analogue. | O63: Primary canon | P63: Official reference reviewed | Q63: Sapkowski's primary book continuity; official franchise material used for orientation. | R63: https://www.andrzejsapkowski.pl/ | S63: Seeded
A64: ENT-0063 | B64: Dopplers | C64: SRC-047 | D64: The Witcher | E64: Book continuity | F64: Mutable people | G64: PPL-1002 | H64: =IFERROR(VLOOKUP(G64,'Master Taxonomy'!$A$2:$B$1656,2,FALSE),"") | K64: Intelligent shapeshifters able to imitate other persons with remarkable physical and behavioral precision. | L64: Innate transformation and mimicry. | M64: They possess personhood and moral agency; disguise does not define them as inherently villainous. | N64: Ethical doppelganger and identity-mimic analogue. | O64: Primary canon | P64: Official reference reviewed | Q64: Sapkowski's primary book continuity; official franchise material used for orientation. | R64: https://www.andrzejsapkowski.pl/ | S64: Seeded
A65: ENT-0064 | B65: Werewolves | C65: SRC-047 | D65: The Witcher | E65: Book continuity | F65: Cursed shapeshifters | G65: PPL-1003 | H65: =IFERROR(VLOOKUP(G65,'Master Taxonomy'!$A$2:$B$1656,2,FALSE),"") | I65: STA-201 | J65: Lycanthropy and Therianthropic Curse | K65: Humans or humanlike beings affected by lupine transformation through curse or condition. | L65: Curse, transformation, predatory impulse, and possible ritual cures. | M65: Cases vary and should not be forced into one infection model. | N65: Lycanthrope and curse-remediation archetype. | O65: Primary canon | P65: Official reference reviewed | Q65: Sapkowski's primary book continuity; official franchise material used for orientation. | R65: https://www.andrzejsapkowski.pl/ | S65: Seeded
A66: ENT-0065 | B66: Leshens | C66: SRC-047 | D66: The Witcher | E66: Book/game franchise | F66: Forest monster or spirit | G66: PPL-206 | H66: =IFERROR(VLOOKUP(G66,'Master Taxonomy'!$A$2:$B$1656,2,FALSE),"") | I66: ROL-512 | J66: Forest Warden | K66: Ancient forest-associated entities that command animals, roots, fear, and territorial power. | L66: Place-bound nature power and predatory guardianship. | M66: Game portrayals are more systematized than sparse literary references. | N66: Dark forest guardian and hostile genius-loci analogue. | O66: Primary canon | P66: Official reference reviewed | Q66: Sapkowski's primary book continuity; official franchise material used for orientation. | R66: https://www.andrzejsapkowski.pl/ | S66: Seeded
A67: ENT-0066 | B67: Noonwraiths and nightwraiths | C67: SRC-047 | D67: The Witcher | E67: Game continuity | F67: Spectral cursed dead | G67: PPL-601 | H67: =IFERROR(VLOOKUP(G67,'Master Taxonomy'!$A$2:$B$1656,2,FALSE),"") | I67: STA-311 | J67: Cursed State | K67: Spectral beings tied to traumatic death, place, time, and unresolved grievance. | L67: Curse, haunting, memory, and environmental conditions. | M67: These are game-system monster categories, not a universal book taxonomy. | N67: Time-bound revenant and tragic haunting analogue. | O67: Primary canon | P67: Official reference reviewed | Q67: Sapkowski's primary book continuity; official franchise material used for orientation. | R67: https://www.andrzejsapkowski.pl/ | S67: Seeded
A68: ENT-0067 | B68: Botchlings | C68: SRC-047 | D68: The Witcher | E68: Book/game franchise | F68: Cursed revenant-like monster | G68: PPL-602 | H68: =IFERROR(VLOOKUP(G68,'Master Taxonomy'!$A$2:$B$1656,2,FALSE),"") | I68: STA-311 | J68: Cursed State | K68: Grotesque beings associated with improperly buried or rejected infants and potentially transformable ritual outcomes. | L68: Curse, burial failure, family trauma, and ritual response. | M68: Their classification blends folklore, tragedy, and monster mechanics. | N68: Domestic revenant and burial-taboo monster analogue. | O68: Primary canon | P68: Official reference reviewed | Q68: Sapkowski's primary book continuity; official franchise material used for orientation. | R68: https://www.andrzejsapkowski.pl/ | S68: Seeded
A69: ENT-0068 | B69: Djinn | C69: SRC-047 | D69: The Witcher | E69: Book continuity | F69: Elemental otherworldly being | G69: PPL-302 | H69: =IFERROR(VLOOKUP(G69,'Master Taxonomy'!$A$2:$B$1656,2,FALSE),"") | K69: Extremely powerful air-associated beings subject to magical binding and wishes. | L69: Innate elemental power and coercive binding. | M69: Their wish function emerges through captivity rather than benevolent service. | N69: Dangerous bound-genie analogue. | O69: Primary canon | P69: Official reference reviewed | Q69: Sapkowski's primary book continuity; official franchise material used for orientation. | R69: https://www.andrzejsapkowski.pl/ | S69: Seeded
A70: ENT-0069 | B70: Dragons | C70: SRC-047 | D70: The Witcher | E70: Book continuity | F70: Rare intelligent creatures | G70: PPL-801 | H70: =IFERROR(VLOOKUP(G70,'Master Taxonomy'!$A$2:$B$1656,2,FALSE),"") | K70: Rare draconic beings including differentiated kinds and exceptionally intelligent golden dragons. | L70: Natural or magical species, flight, breath, and intelligence. | M70: Witcher ethics distinguish sapient or rare creatures from indiscriminate monster targets. | N70: Protected dragon, monster-hunting dilemma, and polymorphic dragon analogue. | O70: Primary canon | P70: Official reference reviewed | Q70: Sapkowski's primary book continuity; official franchise material used for orientation. | R70: https://www.andrzejsapkowski.pl/ | S70: Seeded
A71: ENT-0070 | B71: The Wild Hunt | C71: SRC-047 | D71: The Witcher | E71: Book and game continuities distinguished | F71: Otherworldly host and military formation | G71: PPL-211 | H71: =IFERROR(VLOOKUP(G71,'Master Taxonomy'!$A$2:$B$1656,2,FALSE),"") | I71: INS-200 | J71: Martial and Protective Organizations | K71: A terrifying spectral-seeming host linked to the Aen Elle and interworld raiding. | L71: Otherworldly technology or magic, cavalry, illusion, and organized power. | M71: Its apparent spectrality can conceal embodied political actors. | N71: Faerie host, death cavalry, and planar raider analogue. | O71: Primary canon | P71: Official reference reviewed | Q71: Sapkowski's primary book continuity; official franchise material used for orientation. | R71: https://www.andrzejsapkowski.pl/ | S71: Seeded
A72: ENT-0071 | B72: Signs | C72: SRC-047 | D72: The Witcher | E72: Book/game franchise | F72: Compact magical technique | G72: PWR-502 | H72: =IFERROR(VLOOKUP(G72,'Master Taxonomy'!$A$2:$B$1656,2,FALSE),"") | K72: Simple or rapidly executed magical signs used by witchers for limited tactical effects. | L72: Training, gesture, concentration, and modest magical aptitude. | M72: They are not equivalent to full sorcerous spellcasting. | N72: Martial cantrip and utility-sign system analogue. | O72: Primary canon | P72: Official reference reviewed | Q72: Sapkowski's primary book continuity; official franchise material used for orientation. | R72: https://www.andrzejsapkowski.pl/ | S72: Seeded
A73: ENT-0072 | B73: Witcher potions and decoctions | C73: SRC-047 | D73: The Witcher | E73: Book/game franchise | F73: Alchemical power tradition | G73: PWR-513 | H73: =IFERROR(VLOOKUP(G73,'Master Taxonomy'!$A$2:$B$1656,2,FALSE),"") | I73: STA-206 | J73: Alchemical Enhancement | K73: Toxic preparations designed for witcher physiology, enhancing combat and sensory performance. | L73: Specialized ingredients, recipes, mutation tolerance, and toxicity management. | M73: Game inventories systematize a literary practice differently across titles. | N73: Restricted combat alchemy and risk-resource system analogue. | O73: Primary canon | P73: Official reference reviewed | Q73: Sapkowski's primary book continuity; official franchise material used for orientation. | R73: https://www.andrzejsapkowski.pl/ | S73: Seeded
A74: ENT-0073 | B74: Barbarian | C74: SRC-089 | D74: Dungeons & Dragons | E74: 2024 core rules | F74: Playable class | G74: ROL-112 | H74: =IFERROR(VLOOKUP(G74,'Master Taxonomy'!$A$2:$B$1656,2,FALSE),"") | K74: A martial class centered on rage, toughness, and forceful combat. | L74: Class features, Rage resource, weapon use, and subclass specialization. | M74: A mechanical class, not a claim that any culture is 'barbaric.' | N74: Berserker-style durable striker class. | O74: Primary canon | P74: Official reference reviewed | Q74: Official D&D 2024 Basic Rules and Player's Handbook reference pages. | R74: https://www.dndbeyond.com/sources/dnd/br-2024/character-classes | S74: Seeded
A75: ENT-0074 | B75: Bard | C75: SRC-089 | D75: Dungeons & Dragons | E75: 2024 core rules | F75: Playable class | G75: ROL-606 | H75: =IFERROR(VLOOKUP(G75,'Master Taxonomy'!$A$2:$B$1656,2,FALSE),"") | K75: A versatile spellcasting and expertise class using inspiration, performance, lore, and social capability. | L75: Learned magic, Bardic Inspiration, skills, and subclass. | M75: Not every in-world musician is a Bard class member. | N75: Support-caster, trickster, and lorekeeper hybrid. | O75: Primary canon | P75: Official reference reviewed | Q75: Official D&D 2024 Basic Rules and Player's Handbook reference pages. | R75: https://www.dndbeyond.com/sources/dnd/br-2024/character-classes | S75: Seeded
A76: ENT-0075 | B76: Cleric | C76: SRC-089 | D76: Dungeons & Dragons | E76: 2024 core rules | F76: Playable class | G76: ROL-402 | H76: =IFERROR(VLOOKUP(G76,'Master Taxonomy'!$A$2:$B$1656,2,FALSE),"") | I76: ROL-401 | J76: Priest | K76: A divine spellcasting class shaped mechanically by sacred power and domain choices. | L76: Divine magic, prepared spells, Channel Divinity, and subclass. | M76: Class membership is not identical to holding a priestly office. | N76: Armored divine caster and miracle-worker role. | O76: Primary canon | P76: Official reference reviewed | Q76: Official D&D 2024 Basic Rules and Player's Handbook reference pages. | R76: https://www.dndbeyond.com/sources/dnd/br-2024/character-classes | S76: Seeded
A77: ENT-0076 | B77: Druid | C77: SRC-089 | D77: Dungeons & Dragons | E77: 2024 core rules | F77: Playable class | G77: ROL-501 | H77: =IFERROR(VLOOKUP(G77,'Master Taxonomy'!$A$2:$B$1656,2,FALSE),"") | K77: A nature-oriented spellcaster with Wild Shape and circle specialization. | L77: Primal magic, transformation, nature knowledge, and subclass. | M77: The class synthesizes multiple historical and fictional nature-mage traditions. | N77: Nature caster and shapeshifting controller. | O77: Primary canon | P77: Official reference reviewed | Q77: Official D&D 2024 Basic Rules and Player's Handbook reference pages. | R77: https://www.dndbeyond.com/sources/dnd/br-2024/character-classes | S77: Seeded
A78: ENT-0077 | B78: Fighter | C78: SRC-089 | D78: Dungeons & Dragons | E78: 2024 core rules | F78: Playable class | G78: ROL-101 | H78: =IFERROR(VLOOKUP(G78,'Master Taxonomy'!$A$2:$B$1656,2,FALSE),"") | K78: A highly customizable martial class defined by weapon mastery, tactical resilience, and subclass. | L78: Training, equipment, extra attacks, and fighting specialization. | M78: The mechanical class is narrower than every person who fights. | N78: Baseline martial class and build platform. | O78: Primary canon | P78: Official reference reviewed | Q78: Official D&D 2024 Basic Rules and Player's Handbook reference pages. | R78: https://www.dndbeyond.com/sources/dnd/br-2024/character-classes | S78: Seeded
A79: ENT-0078 | B79: Monk | C79: SRC-089 | D79: Dungeons & Dragons | E79: 2024 core rules | F79: Playable class | G79: ROL-123 | H79: =IFERROR(VLOOKUP(G79,'Master Taxonomy'!$A$2:$B$1656,2,FALSE),"") | K79: A mobile unarmed or specialized-weapon martial class using disciplined focus. | L79: Training, Focus Points, movement, strikes, and subclass. | M79: Combines monastic and martial-arts imagery that should be treated as a game synthesis. | N79: Mobile martial artist and resource-based skirmisher. | O79: Primary canon | P79: Official reference reviewed | Q79: Official D&D 2024 Basic Rules and Player's Handbook reference pages. | R79: https://www.dndbeyond.com/sources/dnd/br-2024/character-classes | S79: Seeded
A80: ENT-0079 | B80: Paladin | C80: SRC-089 | D80: Dungeons & Dragons | E80: 2024 core rules | F80: Playable class | G80: ROL-117 | H80: =IFERROR(VLOOKUP(G80,'Master Taxonomy'!$A$2:$B$1656,2,FALSE),"") | K80: An oath-defined armored class combining martial combat, healing, and divine magic. | L80: Sacred oath, Lay on Hands, smites, spells, and aura features. | M80: Faith, morality, and institutional membership vary by setting and subclass. | N80: Holy knight, oath warrior, and support tank. | O80: Primary canon | P80: Official reference reviewed | Q80: Official D&D 2024 Basic Rules and Player's Handbook reference pages. | R80: https://www.dndbeyond.com/sources/dnd/br-2024/character-classes | S80: Seeded
A81: ENT-0080 | B81: Ranger | C81: SRC-089 | D81: Dungeons & Dragons | E81: 2024 core rules | F81: Playable class | G81: ROL-125 | H81: =IFERROR(VLOOKUP(G81,'Master Taxonomy'!$A$2:$B$1656,2,FALSE),"") | K81: A wilderness-oriented martial-spellcasting class specializing in tracking, exploration, and chosen tactics. | L81: Training, nature magic, Hunter's Mark, skills, and subclass. | M81: It is a rules package rather than one universal social profession. | N81: Wilderness scout, hunter, and martial-primal hybrid. | O81: Primary canon | P81: Official reference reviewed | Q81: Official D&D 2024 Basic Rules and Player's Handbook reference pages. | R81: https://www.dndbeyond.com/sources/dnd/br-2024/character-classes | S81: Seeded
A82: ENT-0081 | B82: Rogue | C82: SRC-089 | D82: Dungeons & Dragons | E82: 2024 core rules | F82: Playable class | G82: ROL-205 | H82: =IFERROR(VLOOKUP(G82,'Master Taxonomy'!$A$2:$B$1656,2,FALSE),"") | K82: A skill-focused class using precision, mobility, expertise, and opportunistic attacks. | L82: Training, Expertise, Sneak Attack, cunning actions, and subclass. | M82: Rogue does not inherently mean criminal or thief. | N82: Skill specialist and precision striker. | O82: Primary canon | P82: Official reference reviewed | Q82: Official D&D 2024 Basic Rules and Player's Handbook reference pages. | R82: https://www.dndbeyond.com/sources/dnd/br-2024/character-classes | S82: Seeded
A83: ENT-0082 | B83: Sorcerer | C83: SRC-089 | D83: Dungeons & Dragons | E83: 2024 core rules | F83: Playable class | G83: ROL-302 | H83: =IFERROR(VLOOKUP(G83,'Master Taxonomy'!$A$2:$B$1656,2,FALSE),"") | I83: PWR-102 | J83: Innate Sorcery | K83: An arcane spellcaster whose magic is framed as inherent or internal and reshaped through metamagic. | L83: Innate power, Sorcery Points, metamagic, and subclass origin. | M83: The class's innate/learned contrast is system-specific. | N83: Innate flexible caster. | O83: Primary canon | P83: Official reference reviewed | Q83: Official D&D 2024 Basic Rules and Player's Handbook reference pages. | R83: https://www.dndbeyond.com/sources/dnd/br-2024/character-classes | S83: Seeded
A84: ENT-0083 | B84: Warlock | C84: SRC-089 | D84: Dungeons & Dragons | E84: 2024 core rules | F84: Playable class | G84: ROL-304 | H84: =IFERROR(VLOOKUP(G84,'Master Taxonomy'!$A$2:$B$1656,2,FALSE),"") | I84: PWR-104 | J84: Pact and Contract Magic | K84: An occult spellcaster defined by a pact or patron relationship, invocations, and distinctive spell recovery. | L84: Patron-granted power, pact choices, invocations, and spells. | M84: ‘Warlock’ has very different meanings across fantasy works. | N84: Pact caster and customizable occult specialist. | O84: Primary canon | P84: Official reference reviewed | Q84: Official D&D 2024 Basic Rules and Player's Handbook reference pages. | R84: https://www.dndbeyond.com/sources/dnd/br-2024/character-classes | S84: Seeded
A85: ENT-0084 | B85: Wizard | C85: SRC-089 | D85: Dungeons & Dragons | E85: 2024 core rules | F85: Playable class | G85: ROL-301 | H85: =IFERROR(VLOOKUP(G85,'Master Taxonomy'!$A$2:$B$1656,2,FALSE),"") | I85: ROL-306 | J85: Magical Scholar | K85: A learned arcane spellcaster using a spellbook, broad preparation, and school or tradition specialization. | L85: Study, notation, spell acquisition, preparation, and subclass. | M85: The learned wizard model is a game convention, not the only meaning of wizard. | N85: Scholarly generalist caster. | O85: Primary canon | P85: Official reference reviewed | Q85: Official D&D 2024 Basic Rules and Player's Handbook reference pages. | R85: https://www.dndbeyond.com/sources/dnd/br-2024/character-classes | S85: Seeded
A86: ENT-0085 | B86: Aasimar | C86: SRC-089 | D86: Dungeons & Dragons | E86: 2024 core rules | F86: Playable species | G86: PPL-402 | H86: =IFERROR(VLOOKUP(G86,'Master Taxonomy'!$A$2:$B$1656,2,FALSE),"") | K86: A playable people marked by celestial influence and supernatural manifestations. | L86: Ancestry or metaphysical heritage represented through species traits. | M86: They are not necessarily literal demigods; this is the closest normalized family. | N86: Celestial-touched or divine-blooded people. | O86: Primary canon | P86: Official reference reviewed | Q86: Official D&D 2024 Basic Rules and Player's Handbook reference pages. | R86: https://www.dndbeyond.com/sources/dnd/br-2024/character-classes | S86: Seeded
A87: ENT-0086 | B87: Dragonborn | C87: SRC-089 | D87: Dungeons & Dragons | E87: 2024 core rules | F87: Playable species | G87: PPL-114 | H87: =IFERROR(VLOOKUP(G87,'Master Taxonomy'!$A$2:$B$1656,2,FALSE),"") | K87: A playable draconic humanoid people with breath weapons and draconic traits. | L87: Ancestry, elemental breath, and lineage choice. | M87: They are distinct from dragons, half-dragons, and unrelated reptilian peoples. | N87: Draconic humanoid ancestry. | O87: Primary canon | P87: Official reference reviewed | Q87: Official D&D 2024 Basic Rules and Player's Handbook reference pages. | R87: https://www.dndbeyond.com/sources/dnd/br-2024/character-classes | S87: Seeded
A88: ENT-0087 | B88: Dwarf | C88: SRC-089 | D88: Dungeons & Dragons | E88: 2024 core rules | F88: Playable species | G88: PPL-103 | H88: =IFERROR(VLOOKUP(G88,'Master Taxonomy'!$A$2:$B$1656,2,FALSE),"") | K88: A playable dwarf people represented through resilience and culturally familiar fantasy traits. | L88: Species rules and setting-dependent culture. | M88: Rules traits should not be mistaken for universal dwarven culture. | N88: Game-mechanical dwarf ancestry. | O88: Primary canon | P88: Official reference reviewed | Q88: Official D&D 2024 Basic Rules and Player's Handbook reference pages. | R88: https://www.dndbeyond.com/sources/dnd/br-2024/character-classes | S88: Seeded
A89: ENT-0088 | B89: Elf | C89: SRC-089 | D89: Dungeons & Dragons | E89: 2024 core rules | F89: Playable species | G89: PPL-102 | H89: =IFERROR(VLOOKUP(G89,'Master Taxonomy'!$A$2:$B$1656,2,FALSE),"") | K89: A playable long-lived, fey-associated people with lineages and innate magical traits. | L89: Species rules, lineage, perception, and setting lore. | M89: D&D elves are not canonically identical to Tolkien's Quendi. | N89: Game-mechanical elf ancestry. | O89: Primary canon | P89: Official reference reviewed | Q89: Official D&D 2024 Basic Rules and Player's Handbook reference pages. | R89: https://www.dndbeyond.com/sources/dnd/br-2024/character-classes | S89: Seeded
A90: ENT-0089 | B90: Gnome | C90: SRC-089 | D90: Dungeons & Dragons | E90: 2024 core rules | F90: Playable species | G90: PPL-105 | H90: =IFERROR(VLOOKUP(G90,'Master Taxonomy'!$A$2:$B$1656,2,FALSE),"") | K90: A playable small people with magical resilience and lineage-associated abilities. | L90: Species traits, lineage, and setting-dependent culture. | M90: The normalized label includes a tinkerfolk pattern that does not describe every D&D gnome. | N90: Game-mechanical gnome ancestry. | O90: Primary canon | P90: Official reference reviewed | Q90: Official D&D 2024 Basic Rules and Player's Handbook reference pages. | R90: https://www.dndbeyond.com/sources/dnd/br-2024/character-classes | S90: Seeded
A91: ENT-0090 | B91: Goliath | C91: SRC-089 | D91: Dungeons & Dragons | E91: 2024 core rules | F91: Playable species | G91: PPL-108 | H91: =IFERROR(VLOOKUP(G91,'Master Taxonomy'!$A$2:$B$1656,2,FALSE),"") | K91: A playable giant-descended or giant-associated humanoid people with size and giant-ancestry traits. | L91: Species traits and giant lineage. | M91: They are not generic giants or necessarily one culture. | N91: Playable giantkin ancestry. | O91: Primary canon | P91: Official reference reviewed | Q91: Official D&D 2024 Basic Rules and Player's Handbook reference pages. | R91: https://www.dndbeyond.com/sources/dnd/br-2024/character-classes | S91: Seeded
A92: ENT-0091 | B92: Halfling | C92: SRC-089 | D92: Dungeons & Dragons | E92: 2024 core rules | F92: Playable species | G92: PPL-104 | H92: =IFERROR(VLOOKUP(G92,'Master Taxonomy'!$A$2:$B$1656,2,FALSE),"") | K92: A playable small people associated mechanically with luck, bravery, and nimbleness. | L92: Species traits and setting-dependent culture. | M92: D&D halflings evolved from but are not identical to Tolkien's Hobbits. | N92: Game-mechanical halfling ancestry. | O92: Primary canon | P92: Official reference reviewed | Q92: Official D&D 2024 Basic Rules and Player's Handbook reference pages. | R92: https://www.dndbeyond.com/sources/dnd/br-2024/character-classes | S92: Seeded
A93: ENT-0092 | B93: Human | C93: SRC-089 | D93: Dungeons & Dragons | E93: 2024 core rules | F93: Playable species | G93: PPL-101 | H93: =IFERROR(VLOOKUP(G93,'Master Taxonomy'!$A$2:$B$1656,2,FALSE),"") | K93: A flexible playable human option represented through general adaptability. | L93: Species rules and player-selected capabilities. | M93: Mechanical flexibility is not an essential claim about real humans. | N93: Baseline adaptable ancestry. | O93: Primary canon | P93: Official reference reviewed | Q93: Official D&D 2024 Basic Rules and Player's Handbook reference pages. | R93: https://www.dndbeyond.com/sources/dnd/br-2024/character-classes | S93: Seeded
A94: ENT-0093 | B94: Orc | C94: SRC-089 | D94: Dungeons & Dragons | E94: 2024 core rules | F94: Playable species | G94: PPL-106 | H94: =IFERROR(VLOOKUP(G94,'Master Taxonomy'!$A$2:$B$1656,2,FALSE),"") | K94: A playable orc people represented with endurance, mobility, and powerful build. | L94: Species traits and setting-dependent culture. | M94: Modern playable orcs should not be collapsed into inherently evil monster populations. | N94: Playable orc ancestry. | O94: Primary canon | P94: Official reference reviewed | Q94: Official D&D 2024 Basic Rules and Player's Handbook reference pages. | R94: https://www.dndbeyond.com/sources/dnd/br-2024/character-classes | S94: Seeded
A95: ENT-0094 | B95: Tiefling | C95: SRC-089 | D95: Dungeons & Dragons | E95: 2024 core rules | F95: Playable species | G95: PPL-500 | H95: =IFERROR(VLOOKUP(G95,'Master Taxonomy'!$A$2:$B$1656,2,FALSE),"") | I95: PPL-1006 | J95: Mixed-Ancestry and Half-Blood Peoples | K95: A playable people marked by fiendish legacy, infernal options, and supernatural traits. | L95: Ancestral or metaphysical legacy represented through species traits. | M95: Tieflings are people, not fiends, and need not be corrupt or evil. | N95: Fiend-touched or infernal-descended people. | O95: Primary canon | P95: Official reference reviewed | Q95: Official D&D 2024 Basic Rules and Player's Handbook reference pages. | R95: https://www.dndbeyond.com/sources/dnd/br-2024/character-classes | S95: Seeded
A96: ENT-0095 | B96: Subclass | C96: SRC-089 | D96: Dungeons & Dragons | E96: 2024 core rules | F96: Character-build mechanic | G96: MEC-304 | H96: =IFERROR(VLOOKUP(G96,'Master Taxonomy'!$A$2:$B$1656,2,FALSE),"") | K96: A class specialization chosen within the core class framework. | L96: Rules progression and feature selection. | M96: Subclasses may represent schools, oaths, patrons, professions, bloodlines, or techniques depending on class. | N96: General specialization layer. | O96: Primary canon | P96: Official reference reviewed | Q96: Official D&D 2024 Basic Rules and Player's Handbook reference pages. | R96: https://www.dndbeyond.com/sources/dnd/br-2024/character-classes | S96: Seeded
A97: ENT-0096 | B97: Background | C97: SRC-089 | D97: Dungeons & Dragons | E97: 2024 core rules | F97: Character-build mechanic | G97: MEC-300 | H97: =IFERROR(VLOOKUP(G97,'Master Taxonomy'!$A$2:$B$1656,2,FALSE),"") | K97: A rules package representing prior life, aptitudes, proficiencies, and origin elements. | L97: Character creation choices and selected benefits. | M97: A background is not an ancestry or current class. | N97: Origin and prior-profession layer. | O97: Primary canon | P97: Official reference reviewed | Q97: Official D&D 2024 Basic Rules and Player's Handbook reference pages. | R97: https://www.dndbeyond.com/sources/dnd/br-2024/character-classes | S97: Seeded
A98: ENT-0097 | B98: Multiclassing | C98: SRC-089 | D98: Dungeons & Dragons | E98: 2024 core rules | F98: Character-build mechanic | G98: MEC-303 | H98: =IFERROR(VLOOKUP(G98,'Master Taxonomy'!$A$2:$B$1656,2,FALSE),"") | K98: A progression model in which a character combines levels from multiple classes. | L98: Level allocation and prerequisites. | M98: Mechanical combination does not automatically imply multiple social professions in the fiction. | N98: Hybrid build and cross-training model. | O98: Primary canon | P98: Official reference reviewed | Q98: Official D&D 2024 Basic Rules and Player's Handbook reference pages. | R98: https://www.dndbeyond.com/sources/dnd/br-2024/character-classes | S98: Seeded
A99: ENT-0098 | B99: Human | C99: SRC-128 | D99: Tactics Ogre: Reborn | E99: Reborn game continuity | F99: Playable people | G99: PPL-101 | H99: =IFERROR(VLOOKUP(G99,'Master Taxonomy'!$A$2:$B$1656,2,FALSE),"") | K99: The principal human peoples of the Valerian setting. | L99: Natural ancestry and regional culture. | M99: Human factions are politically and ethnically differentiated. | N99: Baseline human ancestry. | O99: Primary canon | P99: Official reference reviewed | Q99: Square Enix official character and class overview for Tactics Ogre: Reborn. | R99: https://www.square-enix-games.com/en_US/news/tactics-ogre-reborn-characters-classes | S99: Seeded
A100: ENT-0099 | B100: Winged | C100: SRC-128 | D100: Tactics Ogre: Reborn | E100: Reborn game continuity | F100: Playable people | G100: PPL-115 | H100: =IFERROR(VLOOKUP(G100,'Master Taxonomy'!$A$2:$B$1656,2,FALSE),"") | K100: Humanoids with functional wings and aerial mobility. | L100: Natural ancestry and flight. | M100: A setting-specific people rather than a universal angelic category. | N100: Winged humanoid and aerial unit analogue. | O100: Primary canon | P100: Official reference reviewed | Q100: Square Enix official character and class overview for Tactics Ogre: Reborn. | R100: https://www.square-enix-games.com/en_US/news/tactics-ogre-reborn-characters-classes | S100: Seeded
A101: ENT-0100 | B101: Lizardman | C101: SRC-128 | D101: Tactics Ogre: Reborn | E101: Reborn game continuity | F101: Playable people | G101: PPL-112 | H101: =IFERROR(VLOOKUP(G101,'Master Taxonomy'!$A$2:$B$1656,2,FALSE),"") | K101: Reptilian humanoids available in specialized martial roles. | L101: Natural ancestry and class access. | M101: Do not merge automatically with dragons or serpentfolk. | N101: Lizardfolk ancestry. | O101: Primary canon | P101: Official reference reviewed | Q101: Square Enix official character and class overview for Tactics Ogre: Reborn. | R101: https://www.square-enix-games.com/en_US/news/tactics-ogre-reborn-characters-classes | S101: Seeded
A102: ENT-0101 | B102: Lamia | C102: SRC-128 | D102: Tactics Ogre: Reborn | E102: Reborn game continuity | F102: Playable people | G102: PPL-113 | H102: =IFERROR(VLOOKUP(G102,'Master Taxonomy'!$A$2:$B$1656,2,FALSE),"") | K102: Serpentine humanoids with setting-specific class options. | L102: Natural ancestry and class access. | M102: The term has different meanings across myth and games. | N102: Lamia and serpentfolk ancestry. | O102: Primary canon | P102: Official reference reviewed | Q102: Square Enix official character and class overview for Tactics Ogre: Reborn. | R102: https://www.square-enix-games.com/en_US/news/tactics-ogre-reborn-characters-classes | S102: Seeded
A103: ENT-0102 | B103: Orc | C103: SRC-128 | D103: Tactics Ogre: Reborn | E103: Reborn game continuity | F103: Playable people | G103: PPL-106 | H103: =IFERROR(VLOOKUP(G103,'Master Taxonomy'!$A$2:$B$1656,2,FALSE),"") | K103: An orcish humanoid people participating in the setting's conflicts. | L103: Natural ancestry and class access. | M103: Playable peoplehood should be distinguished from generic monster status. | N103: Orc ancestry. | O103: Primary canon | P103: Official reference reviewed | Q103: Square Enix official character and class overview for Tactics Ogre: Reborn. | R103: https://www.square-enix-games.com/en_US/news/tactics-ogre-reborn-characters-classes | S103: Seeded
...

Sheet Controlled Vocab
A1: Axis | B1: Value | C1: Definition | D1: Use
A2: Record_Type | B2: Species / ancestry | C2: A heritable or naturally reproduced people or biological kind. | D2: Use the most source-faithful type; add other axes rather than forcing one label.
A3: Record_Type | B3: Metaphysical kind | C3: A category defined primarily by cosmology, spiritual substance, or mode of existence. | D3: Use the most source-faithful type; add other axes rather than forcing one label.
A4: Record_Type | B4: Culture / ethnicity | C4: A historically and socially constituted people; not assumed to be biologically distinct. | D4: Use the most source-faithful type; add other axes rather than forcing one label.
A5: Record_Type | B5: Lineage / bloodline | C5: A descent group carrying inherited status, traits, or powers. | D5: Use the most source-faithful type; add other axes rather than forcing one label.
A6: Record_Type | B6: Creature type | C6: A bestiary or rules grouping that may combine unrelated ontologies. | D6: Use the most source-faithful type; add other axes rather than forcing one label.
A7: Record_Type | B7: Profession | C7: Work performed through training, employment, or livelihood. | D7: Use the most source-faithful type; add other axes rather than forcing one label.
A8: Record_Type | B8: Game class | C8: A formal rules package governing progression and abilities. | D8: Use the most source-faithful type; add other axes rather than forcing one label.
A9: Record_Type | B9: Subclass / specialization | C9: A narrower branch within a class, job, school, or build. | D9: Use the most source-faithful type; add other axes rather than forcing one label.
A10: Record_Type | B10: Job | C10: A changeable or unlockable game role, especially in job-system games. | D10: Use the most source-faithful type; add other axes rather than forcing one label.
A11: Record_Type | B11: Social office | C11: A recognized title or position within a society or institution. | D11: Use the most source-faithful type; add other axes rather than forcing one label.
A12: Record_Type | B12: Religious office | C12: An ordained, initiated, or ritually recognized sacred position. | D12: Use the most source-faithful type; add other axes rather than forcing one label.
... A163: Priority_Score | B163: 5 — Very high | C163: Foundational or unusually distinctive contribution. | D163: Apply consistently across Source Priority's seven positive criteria and redundancy penalty.

Sheet Relationship Rules
A1: Relation | B1: Directionality | C1: Scope | D1: Use_When | E1: Do_Not_Use_When | F1: Example
A2: Canonical alias | B2: Symmetric | C2: Same continuity | D2: Use when two names denote the same entity, people, office, or concept. | E2: Do not use for translations that change the underlying concept. | F2: Quendi ↔ Elves within a specified Tolkien context.
A3: Exact equivalent | B3: Symmetric | C3: Cross-setting | D3: Use only when ontology, function, power basis, and narrative role align. | E3: Do not use merely because two concepts share a label. | F3: Rare; most cross-setting links should be partial or functional.
A4: Subtype-of | B4: Directed | C4: Within or across taxonomies | D4: Use for a narrower normalized or canonical category. | E4: Do not confuse with member-of an organization. | F4: Higher vampire subtype-of source vampire taxonomy.
A5: Member-of | B5: Directed | C5: Institutional / social | D5: Use for membership in a school, order, faction, people, or party. | E5: Do not use when the relation is transformation or ancestry. | F5: A witcher member-of a witcher school.
A6: Version-of | B6: Directed | C6: Edition / adaptation | D6: Use for materially divergent rules editions or portrayals. | E6: Do not merge versioned entries when powers or ontology change. | F6: Game-continuity Wild Hunt version-of franchise concept.
A7: Adaptation-of | B7: Directed | C7: Cross-media | D7: Use where a film, game, anime, or series adapts a specific source. | E7: Do not imply fidelity; record divergences separately. | F7: Television continuity adaptation-of novel continuity.
A8: Inspired-by | B8: Directed | C8: Historical influence | D8: Use only with documented or strongly evidenced influence. | E8: Do not infer influence from resemblance alone. | F8: Later halfling tradition inspired-by Tolkienian hobbits, where documented.
A9: Close analogue | B9: Symmetric | C9: Comparative | D9: Use when several major dimensions align but the concepts remain distinct. | E9: Do not erase source-specific metaphysics. | F9: Two learned court-mage institutions with different cosmologies.
A10: Partial analogue | B10: Symmetric | C10: Comparative | D10: Use when one or two dimensions align. | E10: Always name the shared axis in notes. | F10: Others partial analogue to ice-fae on effect and narrative threat.
A11: Functional analogue | B11: Symmetric | C11: Narrative / social | D11: Use when roles are similar despite different powers or origins. | E11: Do not imply common ancestry or influence. | F11: Night's Watch functional analogue to a frontier monster-guard order.
A12: Mechanical analogue | B12: Symmetric | C12: Game mechanics | D12: Use for shared combat or progression roles. | E12: Keep mechanics separate from in-world profession. | F12: Knight mechanical analogue to tank/defender.
... A23: Decontextualized-as | B23: Directed | C23: Adaptation / critical analysis | D23: Use when an adaptation retains a name, image, or ability while removing substantial ritual, social, historical, or cosmological context. | E23: Do not use as a moral judgment without naming the specific context that changed or disappeared. | F23: A sacred object decontextualized-as a generic equippable relic bonus.

Sheet Coverage
A1: Taxonomy Domain | B1: Count | D1: Source Medium | E1: Count | G1: Evidence Level | H1: Count | J1: Seed Source | K1: Entries
A2: People & Beings | B2: =COUNTIF('Master Taxonomy'!$C$2:$C$1656,A2) | D2: Literature | E2: =COUNTIF('Source Corpus'!$D$2:$D$282,D2) | G2: Primary text reviewed | H2: =COUNTIF('Seed Catalogue'!$P$2:$P$452,G2) | J2: Mahābhārata — BORI Critical Edition | K2: =COUNTIF('Seed Catalogue'!$D$2:$D$452,J2)
A3: Roles & Vocations | B3: =COUNTIF('Master Taxonomy'!$C$2:$C$1656,A3) | D3: Manga / Anime | E3: =COUNTIF('Source Corpus'!$D$2:$D$282,D3) | G3: Official reference reviewed | H3: =COUNTIF('Seed Catalogue'!$P$2:$P$452,G3) | J3: Tactics Ogre: Reborn | K3: =COUNTIF('Seed Catalogue'!$D$2:$D$452,J3)
A4: Power Traditions | B4: =COUNTIF('Master Taxonomy'!$C$2:$C$1656,A4) | D4: Tabletop RPG | E4: =COUNTIF('Source Corpus'!$D$2:$D$282,D4) | G4: Secondary reference reviewed | H4: =COUNTIF('Seed Catalogue'!$P$2:$P$452,G4) | J4: Final Fantasy | K4: =COUNTIF('Seed Catalogue'!$D$2:$D$452,J4)
A5: States & Transformations | B5: =COUNTIF('Master Taxonomy'!$C$2:$C$1656,A5) | D5: Mythology / Folklore | E5: =COUNTIF('Source Corpus'!$D$2:$D$282,D5) | G5: Orientation only | H5: =COUNTIF('Seed Catalogue'!$P$2:$P$452,G5) | J5: Warcraft | K5: =COUNTIF('Seed Catalogue'!$D$2:$D$452,J5)
A6: Institutions & Affiliations | B6: =COUNTIF('Master Taxonomy'!$C$2:$C$1656,A6) | D6: Video Game / JRPG Franchise | E6: =COUNTIF('Source Corpus'!$D$2:$D$282,D6) | G6: Needs verification | H6: =COUNTIF('Seed Catalogue'!$P$2:$P$452,G6) | J6: Age of Mythology: Retold | K6: =COUNTIF('Seed Catalogue'!$D$2:$D$452,J6)
A7: Narrative Archetypes | B7: =COUNTIF('Master Taxonomy'!$C$2:$C$1656,A7) | D7: Video Game / Action RPG Franchise | E7: =COUNTIF('Source Corpus'!$D$2:$D$282,D7) | J7: Tolkien's Legendarium | K7: =COUNTIF('Seed Catalogue'!$D$2:$D$452,J7)
A8: Civilization & Culture Archetypes | B8: =COUNTIF('Master Taxonomy'!$C$2:$C$1656,A8) | D8: Television | E8: =COUNTIF('Source Corpus'!$D$2:$D$282,D8) | J8: The Witcher | K8: =COUNTIF('Seed Catalogue'!$D$2:$D$452,J8)
A9: Game-Mechanical Archetypes | B9: =COUNTIF('Master Taxonomy'!$C$2:$C$1656,A9) | D9: Light Novel / Anime | E9: =COUNTIF('Source Corpus'!$D$2:$D$282,D9) | J9: Dungeons & Dragons | K9: =COUNTIF('Seed Catalogue'!$D$2:$D$452,J9)
A10: Artifacts, Relics, Weapons & Vehicles | B10: =COUNTIF('Master Taxonomy'!$C$2:$C$1656,A10) | D10: Video Game / CRPG | E10: =COUNTIF('Source Corpus'!$D$2:$D$282,D10) | J10: The Elder Scrolls | K10: =COUNTIF('Seed Catalogue'!$D$2:$D$452,J10)
A11: Cosmologies, Realms & Sacred Geography | B11: =COUNTIF('Master Taxonomy'!$C$2:$C$1656,A11) | D11: Film | E11: =COUNTIF('Source Corpus'!$D$2:$D$282,D11) | J11: A Song of Ice and Fire | K11: =COUNTIF('Seed Catalogue'!$D$2:$D$452,J11)
A12: Metaphysical Laws, Rituals & Exchanges | B12: =COUNTIF('Master Taxonomy'!$C$2:$C$1656,A12) | D12: Animated Television | E12: =COUNTIF('Source Corpus'!$D$2:$D$282,D12) | J12: Warhammer: The Old World | K12: =COUNTIF('Seed Catalogue'!$D$2:$D$452,J12)
D13: Tabletop RPG Setting | E13: =COUNTIF('Source Corpus'!$D$2:$D$282,D13) | J13: Darkest Dungeon | K13: =COUNTIF('Seed Catalogue'!$D$2:$D$452,J13)
D14: Video Game / Tactical RPG | E14: =COUNTIF('Source Corpus'!$D$2:$D$282,D14) | J14: Final Fantasy XIV | K14: =COUNTIF('Seed Catalogue'!$D$2:$D$452,J14)
A16: Visual summaries

Sheet Data Dictionary
A1: Sheet | B1: Field | C1: Data_Type | D1: Required | E1: Definition | F1: Guidance
A2: Master Taxonomy | B2: Archetype_ID | C2: Text / key | D2: Yes | E2: Stable normalized identifier. | F2: Prefix indicates domain, including ART (artifacts), COS (cosmology), and LAW (metaphysical laws); never reuse retired IDs.
A3: Master Taxonomy | B3: Preferred_Name | C3: Text | D3: Yes | E3: Human-readable normalized archetype label. | F3: Use comparative language such as '-derived' where exact equivalence is unsafe.
A4: Master Taxonomy | B4: Domain | C4: Controlled text | D4: Yes | E4: One of the eleven top-level analytical domains. | F4: See Controlled Vocab and Start Here.
A5: Master Taxonomy | B5: Parent_ID | C5: Text / foreign key | D5: No for roots | E5: Immediate parent in the normalized hierarchy. | F5: Must reference an Archetype_ID or remain blank for root records.
A6: Master Taxonomy | B6: Tier | C6: Integer | D6: Yes | E6: Hierarchy depth, with 1 as a domain root. | F6: Used for navigation, not importance.
A7: Master Taxonomy | B7: Core_Definition | C7: Long text | D7: Yes | E7: Minimal inclusion rule for the archetype. | F7: Define by ontology/function, not by a franchise example.
A8: Master Taxonomy | B8: Key_Distinctions | C8: Long text | D8: Yes | E8: Boundaries against neighboring or commonly confused concepts. | F8: Record what the category excludes.
A9: Master Taxonomy | B9: Common_Variants | C9: Long text | D9: No | E9: Recurring subforms, presentations, or implementations. | F9: Separate variants with semicolons.
A10: Master Taxonomy | B10: Typical_Functions | C10: Long text | D10: No | E10: Frequent social, narrative, combat, or mechanical functions. | F10: Descriptive, not essential or morally deterministic.
A11: Master Taxonomy | B11: Representative_Terms | C11: Long text | D11: No | E11: Common labels encountered across sources. | F11: Terms are examples, not automatic synonyms.
A12: Master Taxonomy | B12: Cross_Cultural_Caution | C12: Long text | D12: No | E12: Risk of flattening living, historical, or culture-specific traditions. | F12: Use especially for religious, folkloric, and non-Western categories.
... A125: Character Viz Guide | B125: Principle | C125: Text | D125: Yes | E125: Version 4 normalized-concept interaction and visual-grammar rule. | F125: Defines the public explorer's normalized-concept graph and evidence boundary.

Sheet Research Queue
A1: Queue_ID | B1: Workstream | C1: Scope | D1: Goal | E1: Priority | F1: Status
A2: RQ-001 | B2: Primary-citation deep pass | C2: Tolkien, ASOIAF, Witcher, Tactics Ogre | D2: Replace corpus-level references with book/chapter, rules page, codex, or in-game entry citations. | E2: High | F2: Open
A3: RQ-002 | B3: Adaptation divergence | C3: Tolkien, ASOIAF, Witcher, Fullmetal Alchemist | D3: Create paired records where screen or game adaptations materially change ontology, powers, institutions, or terminology. | E3: High | F3: Open
A4: RQ-003 | B4: D&D edition history | C4: Dungeons & Dragons | D4: Separate OD&D, AD&D, 3e, 4e, 5e-2014, and 5e-2024 class/species taxonomies. | E4: High | F4: Open
A5: RQ-004 | B5: Final Fantasy title matrix | C5: Final Fantasy | D5: Record job appearance, meaning, and mechanics per numbered and tactical title rather than only recurring franchise patterns. | E5: High | F5: Open
A6: RQ-005 | B6: Live-service snapshots | C6: World of Warcraft, Final Fantasy XIV, Guild Wars 2 | D6: Store dated snapshots for playable races, classes/jobs, and specialization structures. | E6: High | F6: Open
A7: RQ-006 | B7: Japanese folklore layer | C7: Mythology / folklore and Japanese media | D7: Separate yōkai, kami, onryō, oni, tengu, kitsune, tsukumogami, and modern media transformations using specialist sources. | E7: High | F7: Open
A8: RQ-007 | B8: Chinese cosmology and cultivation | C8: Xianxia, wuxia, xuanhuan | D8: Expand cultivation realms, sect roles, immortals, spirits, demons, alchemy, talismans, formations, and heavenly bureaucracy without treating all works as one system. | E8: High | F8: Open
A9: RQ-008 | B9: Korean fantasy ecosystems | C9: Manhwa, web novels, folklore | D9: Distinguish hunter/gate systems, constellations, regressors, murim traditions, dokkaebi, and indigenous mythic elements. | E9: Major | F9: Open
A10: RQ-009 | B10: South Asian traditions | C10: Epic, puranic, folkloric, and modern fantasy | D10: Develop culturally specific records for yaksha, rakshasa, naga, gandharva, apsara, asura/deva relations, siddha, and modern reinterpretations. | E10: High | F10: In progress — Version 2.0 Mahābhārata source-complex pass seeded
A11: RQ-010 | B11: West Asian and Persian traditions | C11: Arabic, Persian, Turkic, and adjacent sources | D11: Separate jinn traditions, divs, peri, ghul, Simurgh, epic heroes, occult sciences, and modern fantasy adaptations. | E11: High | F11: Open
A12: RQ-011 | B12: African traditions | C12: Regional folklore, literature, games, screen media | D12: Build culture-specific—not continent-level—records with relevant scholarship and language-sensitive terminology. | E12: High | F12: Open
... A27: RQ-026 | B27: Darkest Dungeon version and DLC split | C27: Darkest Dungeon base game, DLC, and sequel boundary | D27: Verify the selective innovation records, separate DLC-specific mechanics and states, and keep Darkest Dungeon II as a distinct mechanical model. | E27: Major | F27: Open

Sheet Source Priority
A1: Source Priority — Marginal Archetype Value | W1: Criterion weight | X1: Points
A2: Ranks sources by the new conceptual coverage they can add, rather than by the raw number of named classes, creatures, or characters. | W2: Archetype novelty | X2: 25
A3: The scores are a transparent baseline. Editorial review may override them when cultural importance, evidence quality, adaptation history, or corpus boundaries require judgment. | W3: Domain breadth | X3: 15
W4: Coverage-gap value | X4: 15
W5: Historical influence | X5: 15
A6: Baseline_Rank | B6: Source_ID | C6: Title_or_Franchise | D6: Medium | E6: Region_Tradition | F6: Existing_Seed_Entries | G6: Archetype_Novelty | H6: Domain_Breadth | I6: Coverage_Gap_Value | J6: Historical_Influence | K6: Conceptual_Depth | L6: Adaptation_Value | M6: Source_Quality | N6: Redundancy_Penalty | O6: Marginal_Value_Score | P6: Recommended_Treatment | Q6: Editorial_Basis | R6: Priority_Rationale | S6: Review_Status | T6: Reference_URL | U6: Last_Reviewed | W6: Conceptual depth | X6: 10
A7: 1 | B7: SRC-277 | C7: Mahābhārata — BORI Critical Edition | D7: Critical Edition / Epic Literature | E7: South Asia / Sanskrit | F7: =COUNTIF('Seed Catalogue'!$C$2:$C$452,B7) | G7: 5 | H7: 5 | I7: 5 | J7: 5 | K7: 5 | L7: 4 | M7: 5 | N7: 0 | O7: =ROUND(G7/5*$X$2+H7/5*$X$3+I7/5*$X$4+J7/5*$X$5+K7/5*$X$6+L7/5*$X$7+M7/5*$X$8-N7/5*$X$9,1) | P7: =IF(O7>=$X$12,"Foundational deep pass",IF(O7>=$X$13,"Major deep pass",IF(O7>=$X$14,"Targeted innovation pass",IF(O7>=$X$15,"Sampling pass","Reference / defer")))) | Q7: BORI Critical Edition override | R7: Highest-priority reference witness for the current South Asian deep pass, with explicit limits regarding regional and living traditions. | S7: Editorial override — review required | T7: https://bori.ac.in/department/mahabharata/ | U7: 46236 | W7: Adaptation value | X7: 10
A8: 2 | B8: SRC-278 | C8: Bhagavad Gītā (Mahābhārata, Bhīṣma Parva) | D8: Epic-Philosophical Text / Sacred Narrative | E8: South Asia / Sanskrit | F8: =COUNTIF('Seed Catalogue'!$C$2:$C$452,B8) | G8: 5 | H8: 5 | I8: 5 | J8: 5 | K8: 5 | L8: 5 | M8: 5 | N8: 1 | O8: =ROUND(G8/5*$X$2+H8/5*$X$3+I8/5*$X$4+J8/5*$X$5+K8/5*$X$6+L8/5*$X$7+M8/5*$X$8-N8/5*$X$9,1) | P8: =IF(O8>=$X$12,"Foundational deep pass",IF(O8>=$X$13,"Major deep pass",IF(O8>=$X$14,"Targeted innovation pass",IF(O8>=$X$15,"Sampling pass","Reference / defer")))) | Q8: Bhagavad Gītā embedded-text override | R8: Exceptionally influential philosophical and revelatory material; preserve its embedded, sacred, and commentarial contexts. | S8: Editorial override — review required | T8: https://www.gitasupersite.iitk.ac.in/ | U8: 46236 | W8: Source quality | X8: 10
A9: 3 | B9: SRC-013 | C9: Ancient Egyptian Mythology | D9: Mythology / Folklore | E9: Ancient Egypt | F9: =COUNTIF('Seed Catalogue'!$C$2:$C$452,B9) | G9: 5 | H9: 5 | I9: 5 | J9: 5 | K9: 5 | L9: 5 | M9: 4 | N9: 1 | O9: =ROUND(G9/5*$X$2+H9/5*$X$3+I9/5*$X$4+J9/5*$X$5+K9/5*$X$6+L9/5*$X$7+M9/5*$X$8-N9/5*$X$9,1) | P9: =IF(O9>=$X$12,"Foundational deep pass",IF(O9>=$X$13,"Major deep pass",IF(O9>=$X$14,"Targeted innovation pass",IF(O9>=$X$15,"Sampling pass","Reference / defer")))) | Q9: Egyptian traditions override | R9: Afterlife judgment, sacred names, divine kingship, temple cosmology, and composite divine embodiment. | S9: Editorial override — review required | T9: https://en.wikipedia.org/wiki/Ancient_Egyptian_Mythology | U9: 46236 | W9: Redundancy penalty | X9: 20
A10: 4 | B10: SRC-279 | C10: Chinese Mythology and Religious Traditions | D10: Mythology / Religion / Folklore | E10: China and Sinosphere | F10: =COUNTIF('Seed Catalogue'!$C$2:$C$452,B10) | G10: 5 | H10: 5 | I10: 5 | J10: 5 | K10: 5 | L10: 5 | M10: 4 | N10: 1 | O10: =ROUND(G10/5*$X$2+H10/5*$X$3+I10/5*$X$4+J10/5*$X$5+K10/5*$X$6+L10/5*$X$7+M10/5*$X$8-N10/5*$X$9,1) | P10: =IF(O10>=$X$12,"Foundational deep pass",IF(O10>=$X$13,"Major deep pass",IF(O10>=$X$14,"Targeted innovation pass",IF(O10>=$X$15,"Sampling pass","Reference / defer")))) | Q10: Chinese source-complex override | R10: Celestial bureaucracy, immortals, talismans, registers, underworld courts, and multiple religious-literary systems fill major gaps. | S10: Editorial override — review required | T10: https://ctext.org/ | U10: 46236
A11: 5 | B11: SRC-003 | C11: Irish Mythological Cycle | D11: Mythology / Folklore | E11: Ireland | F11: =COUNTIF('Seed Catalogue'!$C$2:$C$452,B11) | G11: 5 | H11: 5 | I11: 5 | J11: 5 | K11: 5 | L11: 5 | M11: 4 | N11: 1 | O11: =ROUND(G11/5*$X$2+H11/5*$X$3+I11/5*$X$4+J11/5*$X$5+K11/5*$X$6+L11/5*$X$7+M11/5*$X$8-N11/5*$X$9,1) | P11: =IF(O11>=$X$12,"Foundational deep pass",IF(O11>=$X$13,"Major deep pass",IF(O11>=$X$14,"Targeted innovation pass",IF(O11>=$X$15,"Sampling pass","Reference / defer")))) | Q11: Irish source-complex override | R11: Geasa, sovereignty, otherworld peoples, poet-satirists, kinship, and transformation address major framework gaps. | S11: Editorial override — review required | T11: https://en.wikipedia.org/wiki/Irish_Mythological_Cycle | U11: 46236 | W11: Recommended treatment | X11: Minimum score
A12: 6 | B12: SRC-019 | C12: Japanese Yōkai and Kami Traditions | D12: Mythology / Folklore | E12: Japan | F12: =COUNTIF('Seed Catalogue'!$C$2:$C$452,B12) | G12: 5 | H12: 5 | I12: 5 | J12: 5 | K12: 5 | L12: 5 | M12: 4 | N12: 1 | O12: =ROUND(G12/5*$X$2+H12/5*$X$3+I12/5*$X$4+J12/5*$X$5+K12/5*$X$6+L12/5*$X$7+M12/5*$X$8-N12/5*$X$9,1) | P12: =IF(O12>=$X$12,"Foundational deep pass",IF(O12>=$X$13,"Major deep pass",IF(O12>=$X$14,"Targeted innovation pass",IF(O12>=$X$15,"Sampling pass","Reference / defer")))) | Q12: Japanese traditions override | R12: Kami, yōkai, purity, place, ritual offices, object spirits, and adaptation transformations address major gaps. | S12: Editorial override — review required | T12: https://en.wikipedia.org/wiki/Japanese_Y%C5%8Dkai_and_Kami_Traditions | U12: 46236 | W12: Foundational deep pass | X12: 75
A13: 7 | B13: SRC-010 | C13: Jinn Traditions | D13: Mythology / Folklore | E13: Middle East / Islamic world | F13: =COUNTIF('Seed Catalogue'!$C$2:$C$452,B13) | G13: 5 | H13: 5 | I13: 5 | J13: 5 | K13: 5 | L13: 5 | M13: 4 | N13: 1 | O13: =ROUND(G13/5*$X$2+H13/5*$X$3+I13/5*$X$4+J13/5*$X$5+K13/5*$X$6+L13/5*$X$7+M13/5*$X$8-N13/5*$X$9,1) | P13: =IF(O13>=$X$12,"Foundational deep pass",IF(O13>=$X$13,"Major deep pass",IF(O13>=$X$14,"Targeted innovation pass",IF(O13>=$X$15,"Sampling pass","Reference / defer")))) | Q13: Jinn-traditions override | R13: High ontology and social-personhood value; must remain distinct from generic demon categories. | S13: Editorial override — review required | T13: https://en.wikipedia.org/wiki/Jinn_Traditions | U13: 46236 | W13: Major deep pass | X13: 60
A14: 8 | B14: SRC-016 | C14: Journey to the West | D14: Novel / Mythic Fantasy | E14: China | F14: =COUNTIF('Seed Catalogue'!$C$2:$C$452,B14) | G14: 5 | H14: 5 | I14: 5 | J14: 5 | K14: 5 | L14: 5 | M14: 4 | N14: 1 | O14: =ROUND(G14/5*$X$2+H14/5*$X$3+I14/5*$X$4+J14/5*$X$5+K14/5*$X$6+L14/5*$X$7+M14/5*$X$8-N14/5*$X$9,1) | P14: =IF(O14>=$X$12,"Foundational deep pass",IF(O14>=$X$13,"Major deep pass",IF(O14>=$X$14,"Targeted innovation pass",IF(O14>=$X$15,"Sampling pass","Reference / defer")))) | Q14: Journey to the West override | R14: Celestial bureaucracy, immortals, pilgrimage, transformations, demon sociality, artifacts, and divine administration. | S14: Editorial override — review required | T14: https://en.wikipedia.org/wiki/Journey_to_the_West | U14: 46236 | W14: Targeted innovation pass | X14: 45
A15: 9 | B15: SRC-014 | C15: Mahābhārata (epic tradition) | D15: Epic Literature / Sacred Narrative | E15: South Asia / Sanskrit and regional traditions | F15: =COUNTIF('Seed Catalogue'!$C$2:$C$452,B15) | G15: 5 | H15: 5 | I15: 5 | J15: 5 | K15: 5 | L15: 5 | M15: 4 | N15: 1 | O15: =ROUND(G15/5*$X$2+H15/5*$X$3+I15/5*$X$4+J15/5*$X$5+K15/5*$X$6+L15/5*$X$7+M15/5*$X$8-N15/5*$X$9,1) | P15: =IF(O15>=$X$12,"Foundational deep pass",IF(O15>=$X$13,"Major deep pass",IF(O15>=$X$14,"Targeted innovation pass",IF(O15>=$X$15,"Sampling pass","Reference / defer")))) | Q15: Mahābhārata source-complex override | R15: Foundational multi-domain source; Version 2.0 begins a deep pass but regional and textual layers remain major priorities. | S15: Editorial override — review required | T15: https://bori.ac.in/department/mahabharata/ | U15: 46236 | W15: Sampling pass | X15: 30
A16: 10 | B16: SRC-280 | C16: Mexica (Aztec) Mythology and Ritual Traditions | D16: Mythology / Religion / Sacred History | E16: Mesoamerica / Central Mexico / Nahua | F16: =COUNTIF('Seed Catalogue'!$C$2:$C$452,B16) | G16: 5 | H16: 5 | I16: 5 | J16: 5 | K16: 5 | L16: 5 | M16: 4 | N16: 1 | O16: =ROUND(G16/5*$X$2+H16/5*$X$3+I16/5*$X$4+J16/5*$X$5+K16/5*$X$6+L16/5*$X$7+M16/5*$X$8-N16/5*$X$9,1) | P16: =IF(O16>=$X$12,"Foundational deep pass",IF(O16>=$X$13,"Major deep pass",IF(O16>=$X$14,"Targeted innovation pass",IF(O16>=$X$15,"Sampling pass","Reference / defer")))) | Q16: Mexica source-complex override | R16: Calendrical cosmology, cosmic maintenance, offerings, world ages, sacred warfare, and place-based identity are underrepresented. | S16: Editorial override — review required | T16: https://www.britishmuseum.org/collection/galleries/mexico | U16: 46236 | W16: Changing the weights recalculates Marginal_Value_Score and Recommended_Treatment; Baseline_Rank and row order remain fixed until the table is re-sorted.
A17: 11 | B17: SRC-009 | C17: One Thousand and One Nights | D17: Frame Tale / Folklore | E17: Middle East / South Asia | F17: =COUNTIF('Seed Catalogue'!$C$2:$C$452,B17) | G17: 5 | H17: 5 | I17: 5 | J17: 5 | K17: 5 | L17: 5 | M17: 4 | N17: 1 | O17: =ROUND(G17/5*$X$2+H17/5*$X$3+I17/5*$X$4+J17/5*$X$5+K17/5*$X$6+L17/5*$X$7+M17/5*$X$8-N17/5*$X$9,1) | P17: =IF(O17>=$X$12,"Foundational deep pass",IF(O17>=$X$13,"Major deep pass",IF(O17>=$X$14,"Targeted innovation pass",IF(O17>=$X$15,"Sampling pass","Reference / defer")))) | Q17: Nights source-complex override | R17: Jinn, talismans, merchants, nested stories, travel, and occult roles add high marginal value. | S17: Editorial override — review required | T17: https://en.wikipedia.org/wiki/One_Thousand_and_One_Nights | U17: 46236
A18: 12 | B18: SRC-015 | C18: Ramayana | D18: Epic Literature | E18: South and Southeast Asia | F18: =COUNTIF('Seed Catalogue'!$C$2:$C$452,B18) | G18: 5 | H18: 5 | I18: 5 | J18: 5 | K18: 5 | L18: 5 | M18: 4 | N18: 1 | O18: =ROUND(G18/5*$X$2+H18/5*$X$3+I18/5*$X$4+J18/5*$X$5+K18/5*$X$6+L18/5*$X$7+M18/5*$X$8-N18/5*$X$9,1) | P18: =IF(O18>=$X$12,"Foundational deep pass",IF(O18>=$X$13,"Major deep pass",IF(O18>=$X$14,"Targeted innovation pass",IF(O18>=$X$15,"Sampling pass","Reference / defer")))) | Q18: Rāmāyaṇa source-complex override | R18: Divine embodiment, exile, sacred weapons, alliance with nonhuman peoples, kingship, and adaptation history. | S18: Editorial override — review required | T18: https://en.wikipedia.org/wiki/Ramayana | U18: 46236
A19: 13 | B19: SRC-022 | C19: Yorùbá Òrìṣà Traditions | D19: Mythology / Religion / Folklore | E19: West Africa / Yorùbá | F19: =COUNTIF('Seed Catalogue'!$C$2:$C$452,B19) | G19: 5 | H19: 5 | I19: 5 | J19: 5 | K19: 5 | L19: 5 | M19: 4 | N19: 1 | O19: =ROUND(G19/5*$X$2+H19/5*$X$3+I19/5*$X$4+J19/5*$X$5+K19/5*$X$6+L19/5*$X$7+M19/5*$X$8-N19/5*$X$9,1) | P19: =IF(O19>=$X$12,"Foundational deep pass",IF(O19>=$X$13,"Major deep pass",IF(O19>=$X$14,"Targeted innovation pass",IF(O19>=$X$15,"Sampling pass","Reference / defer")))) | Q19: Yorùbá/Ifá priority override | R19: Divination, destiny, òrìṣà relations, possession, praise, ritual authority, and living sacred context are major gaps. | S19: Editorial override — review required | T19: https://en.wikipedia.org/wiki/Yor%C3%B9b%C3%A1_%C3%92r%C3%AC%E1%B9%A3%C3%A0_Traditions | U19: 46236
A20: 14 | B20: SRC-021 | C20: Popol Vuh | D20: Epic / Sacred Narrative | E20: Mesoamerica / K'iche' Maya | F20: =COUNTIF('Seed Catalogue'!$C$2:$C$452,B20) | G20: 5 | H20: 5 | I20: 5 | J20: 5 | K20: 5 | L20: 4 | M20: 4 | N20: 1 | O20: =ROUND(G20/5*$X$2+H20/5*$X$3+I20/5*$X$4+J20/5*$X$5+K20/5*$X$6+L20/5*$X$7+M20/5*$X$8-N20/5*$X$9,1) | P20: =IF(O20>=$X$12,"Foundational deep pass",IF(O20>=$X$13,"Major deep pass",IF(O20>=$X$14,"Targeted innovation pass",IF(O20>=$X$15,"Sampling pass","Reference / defer")))) | Q20: Popol Vuh override | R20: Creation, hero twins, underworld trials, animal relations, and K'iche' sacred narrative provide high marginal value. | S20: Editorial override — review required | T20: https://en.wikipedia.org/wiki/Popol_Vuh | U20: 46236
A21: 15 | B21: SRC-011 | C21: Shahnameh | D21: Epic Literature | E21: Persian / Iranian | F21: =COUNTIF('Seed Catalogue'!$C$2:$C$452,B21) | G21: 5 | H21: 5 | I21: 5 | J21: 5 | K21: 5 | L21: 4 | M21: 4 | N21: 1 | O21: =ROUND(G21/5*$X$2+H21/5*$X$3+I21/5*$X$4+J21/5*$X$5+K21/5*$X$6+L21/5*$X$7+M21/5*$X$8-N21/5*$X$9,1) | P21: =IF(O21>=$X$12,"Foundational deep pass",IF(O21>=$X$13,"Major deep pass",IF(O21>=$X$14,"Targeted innovation pass",IF(O21>=$X$15,"Sampling pass","Reference / defer")))) | Q21: Persian epic override | R21: Royal glory, divs, peris, Simurgh, hero houses, and tragic kingship fill major gaps. | S21: Editorial override — review required | T21: https://en.wikipedia.org/wiki/Shahnameh | U21: 46236
A22: 16 | B22: SRC-012 | C22: Epic of Gilgamesh | D22: Epic Literature | E22: Mesopotamia | F22: =COUNTIF('Seed Catalogue'!$C$2:$C$452,B22) | G22: 5 | H22: 5 | I22: 4 | J22: 5 | K22: 5 | L22: 4 | M22: 5 | N22: 1 | O22: =ROUND(G22/5*$X$2+H22/5*$X$3+I22/5*$X$4+J22/5*$X$5+K22/5*$X$6+L22/5*$X$7+M22/5*$X$8-N22/5*$X$9,1) | P22: =IF(O22>=$X$12,"Foundational deep pass",IF(O22>=$X$13,"Major deep pass",IF(O22>=$X$14,"Targeted innovation pass",IF(O22>=$X$15,"Sampling pass","Reference / defer")))) | Q22: Mesopotamian epic override | R22: Foundational kingship, monster guardians, divine conflict, and immortality-quest material. | S22: Editorial override — review required | T22: https://en.wikipedia.org/wiki/Epic_of_Gilgamesh | U22: 46236
A23: 17 | B23: SRC-005 | C23: Arthurian Legend | D23: Literature / Mythic Cycle | E23: Britain / France / Europe | F23: =COUNTIF('Seed Catalogue'!$C$2:$C$452,B23) | G23: 5 | H23: 5 | I23: 4 | J23: 5 | K23: 5 | L23: 4 | M23: 4 | N23: 1 | O23: =ROUND(G23/5*$X$2+H23/5*$X$3+I23/5*$X$4+J23/5*$X$5+K23/5*$X$6+L23/5*$X$7+M23/5*$X$8-N23/5*$X$9,1) | P23: =IF(O23>=$X$12,"Foundational deep pass",IF(O23>=$X$13,"Major deep pass",IF(O23>=$X$14,"Targeted innovation pass",IF(O23>=$X$15,"Sampling pass","Reference / defer")))) | Q23: Mythic/epic source baseline | R23: High ontology, cosmology, ritual, narrative, and historical-influence value; prioritize source-specific deep research. | S23: Heuristic baseline — editorial review required | T23: https://en.wikipedia.org/wiki/Arthurian_Legend | U23: 46236
A24: 18 | B24: SRC-006 | C24: Kalevala | D24: Epic / Folklore | E24: Finland / Karelia | F24: =COUNTIF('Seed Catalogue'!$C$2:$C$452,B24) | G24: 5 | H24: 5 | I24: 4 | J24: 5 | K24: 5 | L24: 4 | M24: 4 | N24: 1 | O24: =ROUND(G24/5*$X$2+H24/5*$X$3+I24/5*$X$4+J24/5*$X$5+K24/5*$X$6+L24/5*$X$7+M24/5*$X$8-N24/5*$X$9,1) | P24: =IF(O24>=$X$12,"Foundational deep pass",IF(O24>=$X$13,"Major deep pass",IF(O24>=$X$14,"Targeted innovation pass",IF(O24>=$X$15,"Sampling pass","Reference / defer")))) | Q24: Finnic epic override | R24: Song magic, smithing, artifact quests, and cosmological poetics add distinctive models. | S24: Editorial override — review required | T24: https://en.wikipedia.org/wiki/Kalevala | U24: 46236
A25: 19 | B25: SRC-004 | C25: The Mabinogion | D25: Literature / Mythic Cycle | E25: Wales | F25: =COUNTIF('Seed Catalogue'!$C$2:$C$452,B25) | G25: 5 | H25: 5 | I25: 4 | J25: 5 | K25: 5 | L25: 4 | M25: 4 | N25: 1 | O25: =ROUND(G25/5*$X$2+H25/5*$X$3+I25/5*$X$4+J25/5*$X$5+K25/5*$X$6+L25/5*$X$7+M25/5*$X$8-N25/5*$X$9,1) | P25: =IF(O25>=$X$12,"Foundational deep pass",IF(O25>=$X$13,"Major deep pass",IF(O25>=$X$14,"Targeted innovation pass",IF(O25>=$X$15,"Sampling pass","Reference / defer")))) | Q25: Welsh mythic-cycle override | R25: High value for transformation, sovereignty, otherworld journeys, and kinship structures. | S25: Editorial override — review required | T25: https://en.wikipedia.org/wiki/The_Mabinogion | U25: 46236
A26: 20 | B26: SRC-020 | C26: Korean Mythology and Folklore | D26: Mythology / Folklore | E26: Korea | F26: =COUNTIF('Seed Catalogue'!$C$2:$C$452,B26) | G26: 5 | H26: 5 | I26: 4 | J26: 4 | K26: 5 | L26: 4 | M26: 4 | N26: 1 | O26: =ROUND(G26/5*$X$2+H26/5*$X$3+I26/5*$X$4+J26/5*$X$5+K26/5*$X$6+L26/5*$X$7+M26/5*$X$8-N26/5*$X$9,1) | P26: =IF(O26>=$X$12,"Foundational deep pass",IF(O26>=$X$13,"Major deep pass",IF(O26>=$X$14,"Targeted innovation pass",IF(O26>=$X$15,"Sampling pass","Reference / defer")))) | Q26: Mythic/epic source baseline | R26: High ontology, cosmology, ritual, narrative, and historical-influence value; prioritize source-specific deep research. | S26: Heuristic baseline — editorial review required | T26: https://en.wikipedia.org/wiki/Korean_Mythology_and_Folklore | U26: 46236
A27: 21 | B27: SRC-024 | C27: Māori Mythology | D27: Mythology / Folklore | E27: Aotearoa New Zealand | F27: =COUNTIF('Seed Catalogue'!$C$2:$C$452,B27) | G27: 5 | H27: 5 | I27: 4 | J27: 4 | K27: 5 | L27: 4 | M27: 4 | N27: 1 | O27: =ROUND(G27/5*$X$2+H27/5*$X$3+I27/5*$X$4+J27/5*$X$5+K27/5*$X$6+L27/5*$X$7+M27/5*$X$8-N27/5*$X$9,1) | P27: =IF(O27>=$X$12,"Foundational deep pass",IF(O27>=$X$13,"Major deep pass",IF(O27>=$X$14,"Targeted innovation pass",IF(O27>=$X$15,"Sampling pass","Reference / defer")))) | Q27: Mythic/epic source baseline | R27: High ontology, cosmology, ritual, narrative, and historical-influence value; prioritize source-specific deep research. | S27: Heuristic baseline — editorial review required | T27: https://en.wikipedia.org/wiki/M%C4%81ori_Mythology | U27: 46236
A28: 22 | B28: SRC-025 | C28: Polynesian Māui Cycles | D28: Mythology / Folklore | E28: Polynesia | F28: =COUNTIF('Seed Catalogue'!$C$2:$C$452,B28) | G28: 5 | H28: 5 | I28: 4 | J28: 4 | K28: 5 | L28: 4 | M28: 4 | N28: 1 | O28: =ROUND(G28/5*$X$2+H28/5*$X$3+I28/5*$X$4+J28/5*$X$5+K28/5*$X$6+L28/5*$X$7+M28/5*$X$8-N28/5*$X$9,1) | P28: =IF(O28>=$X$12,"Foundational deep pass",IF(O28>=$X$13,"Major deep pass",IF(O28>=$X$14,"Targeted innovation pass",IF(O28>=$X$15,"Sampling pass","Reference / defer")))) | Q28: Mythic/epic source baseline | R28: High ontology, cosmology, ritual, narrative, and historical-influence value; prioritize source-specific deep research. | S28: Heuristic baseline — editorial review required | T28: https://en.wikipedia.org/wiki/Polynesian_M%C4%81ui_Cycles | U28: 46236
... A287: 281 | B287: SRC-135 | C287: Warcraft | D287: Video Game / Strategy and MMORPG Franchise | E287: United States | F287: =COUNTIF('Seed Catalogue'!$C$2:$C$452,B287) | G287: 3 | H287: 3 | I287: 2 | J287: 5 | K287: 3 | L287: 4 | M287: 4 | N287: 5 | O287: =ROUND(G287/5*$X$2+H287/5*$X$3+I287/5*$X$4+J287/5*$X$5+K287/5*$X$6+L287/5*$X$7+M287/5*$X$8-N287/5*$X$9,1) | P287: =IF(O287>=$X$12,"Foundational deep pass",IF(O287>=$X$13,"Major deep pass",IF(O287>=$X$14,"Targeted innovation pass",IF(O287>=$X$15,"Sampling pass","Reference / defer")))) | Q287: Game-system baseline | R287: Prioritize distinctive mechanics, transformations, adaptation operations, and setting innovations rather than complete class repetition. | S287: Heuristic baseline — editorial review required | T287: https://worldofwarcraft.blizzard.com/game/classes | U287: 46236

Sheet Term Metadata
A1: Term Metadata — Language, Witness, and Sacred-Context Controls
A2: Preserves original-language terminology, textual layers, translation variants, and culturally specific cautions for source records.
A3: A normalized archetype is a comparison coordinate; it does not replace the term's meaning within its linguistic, ritual, literary, or living tradition.
A4: Term_ID | B4: Source_Entry_ID | C4: Source_ID | D4: Canonical_Term | E4: Original_Language | F4: Original_Script | G4: Transliteration | H4: Literal_Gloss | I4: Period_or_Layer | J4: Region_or_Tradition | K4: Textual_Witness | L4: Tradition_Status | M4: Translation_Variants | N4: Sacred_Context_Caution | O4: Novelty_Classification | P4: Citation_Granularity | Q4: Reference_URL | R4: Review_Status
A5: TRM-0001 | B5: ENT-0317 | C5: SRC-277 | D5: deva | E5: Sanskrit | F5: देव | G5: deva | H5: shining/divine being; no single exhaustive gloss | I5: Epic-wide | J5: South Asia / Sanskrit Mahābhārata tradition | K5: BORI Critical Edition reference structure; Ganguli English translation reviewed at parva level | L5: Epic / sacred literary tradition | M5: god; deity; divine being | N5: Do not treat deva as a biological race or assume every occurrence has identical theological status. | O5: New subtype / source-specific refinement | P5: Parva-level | Q5: https://bori.ac.in/department/mahabharata/ | R5: Seeded
A6: TRM-0002 | B6: ENT-0318 | C6: SRC-277 | D6: asura | E6: Sanskrit | F6: असुर | G6: asura | H6: source-specific divine/adversarial being; no single adequate English gloss | I6: Epic-wide | J6: South Asia / Sanskrit Mahābhārata tradition | K6: BORI Critical Edition reference structure; Ganguli English translation reviewed at parva level | L6: Epic / sacred literary tradition | M6: asura; anti-god; demon (often misleading) | N6: Avoid automatic translation as demon or devil; preserve shared divine genealogies and textual variation. | O6: New subtype / source-specific refinement | P6: Parva-level | Q6: https://bori.ac.in/department/mahabharata/ | R6: Seeded
A7: TRM-0003 | B7: ENT-0319 | C7: SRC-277 | D7: rākṣasa | E7: Sanskrit | F7: राक्षस | G7: rākṣasa | H7: source-specific class of powerful nonhuman beings | I7: Epic-wide | J7: South Asia / Sanskrit Mahābhārata tradition | K7: BORI Critical Edition reference structure; Ganguli English translation reviewed at parva level | L7: Epic / sacred literary tradition | M7: rakshasa; raksasa; demon (often misleading) | N7: Do not homogenize rākṣasas as an evil species or detach the term from South Asian literary and religious histories. | O7: New subtype / source-specific refinement | P7: Parva-level | Q7: https://bori.ac.in/department/mahabharata/ | R7: Seeded
A8: TRM-0004 | B8: ENT-0320 | C8: SRC-277 | D8: yakṣa | E8: Sanskrit | F8: यक्ष | G8: yakṣa | H8: source-specific nonhuman being, often linked to place, wealth, or guardianship | I8: Epic-wide | J8: South Asia / Sanskrit Mahābhārata tradition | K8: BORI Critical Edition reference structure; Ganguli English translation reviewed at parva level | L8: Epic / sacred literary tradition | M8: yaksha; nature spirit; tutelary being | N8: Generic fairy, goblin, or nature-spirit translations are only partial. | O8: New subtype / source-specific refinement | P8: Parva-level | Q8: https://bori.ac.in/department/mahabharata/ | R8: Seeded
A9: TRM-0005 | B9: ENT-0321 | C9: SRC-277 | D9: gandharva | E9: Sanskrit | F9: गन्धर्व | G9: gandharva | H9: celestial being; no single exhaustive gloss | I9: Epic-wide | J9: South Asia / Sanskrit Mahābhārata tradition | K9: BORI Critical Edition reference structure; Ganguli English translation reviewed at parva level | L9: Epic / sacred literary tradition | M9: gandharva; celestial musician | N9: Musical association does not make gandharvas equivalent to a bard species or angelic choir. | O9: New subtype / source-specific refinement | P9: Parva-level | Q9: https://bori.ac.in/department/mahabharata/ | R9: Seeded
A10: TRM-0006 | B10: ENT-0322 | C10: SRC-277 | D10: apsaras / apsarā | E10: Sanskrit | F10: अप्सरस् / अप्सरा | G10: apsaras / apsarā | H10: celestial female being; no single exhaustive gloss | I10: Epic-wide | J10: South Asia / Sanskrit Mahābhārata tradition | K10: BORI Critical Edition reference structure; Ganguli English translation reviewed at parva level | L10: Epic / sacred literary tradition | M10: apsara; celestial nymph; heavenly dancer | N10: Avoid reducing apsarases to seductresses, dancers, or a uniform species. | O10: New subtype / source-specific refinement | P10: Parva-level | Q10: https://bori.ac.in/department/mahabharata/ | R10: Seeded
A11: TRM-0007 | B11: ENT-0323 | C11: SRC-277 | D11: nāga | E11: Sanskrit | F11: नाग | G11: nāga | H11: serpent; source-specific serpent being or lineage | I11: Epic-wide | J11: South Asia / Sanskrit Mahābhārata tradition | K11: BORI Critical Edition reference structure; Ganguli English translation reviewed at parva level | L11: Epic / sacred literary tradition | M11: naga; serpent being; serpent people | N11: Do not equate nāga automatically with dragon, snake monster, or reptilian humanoid. | O11: New subtype / source-specific refinement | P11: Parva-level | Q11: https://bori.ac.in/department/mahabharata/ | R11: Seeded
A12: TRM-0008 | B12: ENT-0324 | C12: SRC-277 | D12: pitṛ | E12: Sanskrit | F12: पितृ | G12: pitṛ | H12: father/ancestor; ancestor being | I12: Epic-wide | J12: South Asia / Sanskrit Mahābhārata tradition | K12: BORI Critical Edition reference structure; Ganguli English translation reviewed at parva level | L12: Epic / sacred literary tradition | M12: pitri; ancestor; ancestral being | N12: Preserve ritual and kinship context; pitṛs are not generic ghosts or undead. | O12: New subtype / source-specific refinement | P12: Parva-level | Q12: https://bori.ac.in/department/mahabharata/ | R12: Seeded
A13: TRM-0009 | B13: ENT-0326 | C13: SRC-277 | D13: avatāra | E13: Sanskrit | F13: अवतार | G13: avatāra | H13: descent | I13: Epic and later theological vocabulary | J13: South Asia / Sanskrit Mahābhārata tradition | K13: BORI Critical Edition reference structure; Ganguli English translation reviewed at parva level | L13: Epic / sacred literary tradition | M13: avatar; incarnation; divine descent | N13: Do not confuse avatāra with a game avatar, player body, possession, or generic shapeshifting. | O13: New subtype / source-specific refinement | P13: Parva-level | Q13: https://bori.ac.in/department/mahabharata/ | R13: Seeded
A14: TRM-0010 | B14: ENT-0327 | C14: SRC-277 | D14: aṃśa | E14: Sanskrit | F14: अंश | G14: aṃśa | H14: portion; share; part | I14: Genealogical and theological passages | J14: South Asia / Sanskrit Mahābhārata tradition | K14: BORI Critical Edition reference structure; Ganguli English translation reviewed at parva level | L14: Epic / sacred literary tradition | M14: portion; aspect; partial incarnation | N14: The relation between part and source is not a numerical power percentage. | O14: New subtype / source-specific refinement | P14: Parva-level | Q14: https://bori.ac.in/department/mahabharata/ | R14: Seeded
A15: TRM-0011 | B15: ENT-0329 | C15: SRC-277 | D15: ṛṣi | E15: Sanskrit | F15: ऋषि | G15: ṛṣi | H15: seer/sage; no single adequate English gloss | I15: Epic-wide | J15: South Asia / Sanskrit Mahābhārata tradition | K15: BORI Critical Edition reference structure; Ganguli English translation reviewed at parva level | L15: Epic / sacred literary tradition | M15: rishi; sage; seer | N15: Do not map automatically to wizard, druid, priest, or hermit. | O15: New subtype / source-specific refinement | P15: Parva-level | Q15: https://bori.ac.in/department/mahabharata/ | R15: Seeded
... A64: TRM-0060 | B64: ENT-0397 | C64: SRC-277 | D64: svayaṃvara | E64: Sanskrit | F64: स्वयंवर | G64: svayaṃvara | H64: self-choice/selection in marriage, context-dependent | I64: Marriage narratives | J64: South Asia / Sanskrit Mahābhārata tradition | K64: BORI Critical Edition reference structure; Ganguli English translation reviewed at parva level | L64: Epic / sacred literary tradition | M64: swayamvara; bride-choice ceremony; marriage contest | N64: Do not reduce to a tournament prize; agency, lineage, public recognition, and politics vary by episode. | O64: New subtype / source-specific refinement | P64: Parva-level | Q64: https://bori.ac.in/department/mahabharata/ | R64: Seeded

Sheet Adaptation Crosswalk
A1: Adaptation Crosswalk — From Traditional Concept to Media System
A2: Records how mythic, literary, religious, folkloric, and historical concepts are transformed into factions, units, resources, classes, items, bosses, and progression systems.
A3: The crosswalk describes preservation and transformation; it does not use an adaptation as evidence for what an earlier tradition 'really' means.
A4: Crosswalk_ID | B4: Traditional_Source_ID | C4: Traditional_Concept | D4: Traditional_Record_Type | E4: Adaptation_Source_ID | F4: Adaptation_Title | G4: Adapted_Concept | H4: Game_Form | I4: Adaptation_Operation | J4: Preserved_Dimension | K4: Changed_or_Lost | L4: Mechanical_Function | M4: Equivalence_Level | N4: Evidence_Level | O4: Source_Reference | P4: Reference_URL | Q4: Review_Status
A5: XWK-0001 | C5: Deity or divine patron | D5: Divine person / cultic relationship | E5: SRC-281 | F5: Age of Mythology: Retold | G5: Major god choice | H5: Initial faction/build selection | I5: Factionalization | J5: Divine portfolio, name, iconography, and patron relation | K5: Narrative, cult, regional history, ritual diversity, and theological ambiguity are compressed into bonuses and a tech tree. | L5: Defines starting bonuses, first god power, technologies, and later branches | M5: Partial analogy | N5: Official reference reviewed | O5: Age of Mythology: Retold official game and expansion materials. | P5: https://www.ageofempires.com/games/age-of-mythology-retold/ | Q5: Seeded
